Workbook

Sheet Приложение 1
G1: Приложение 1
F2: УТВЕРЖДАЮ
F3: руководитель ГБУ КК "Центр развития спорта"
F4: ______________ В.П. Колпаков
F5: согласно приказу
F6: № ____ от "____"_______ 20___ г.
G7: _
A8: Календарный план официальных физкультурных и спортивных мероприятий государственного бюджетного учреждения Краснодарского края "Центр развития спорта" на 2026 год в части обеспечения наградной атрибутикой за счет субсидий на финансовое обеспечение выполнения государственного задания на оказание государственных услуг (выполнение работ) в 2026 году | Z8: УТВЕРЖДАЮ
A10: № п/п | B10: Наименование мероприятия | C10: Вид соревнований | D10: Возраст | E10: Дата проведения (начало мероприятия) | F10: Дата проведения (конец мероприятия) | G10: Место проведения | H10: Количество кубков | Q10: Количество медалей | Z10: Грамоты | AC10: Услуги по изготовлению и поставке | AE10: Всего по виду спорта
H11: 1 место Кол-во, шт. | I11: Стоимость 1 шт. | J11: Итого | K11: 2 место Кол-во, шт. | L11: Стоимость 1 шт. | M11: Итого | N11: 3 место Кол-во, шт. | O11: Стоимость 1 шт. | P11: Итого | Q11: 1 место Кол-во, шт. | R11: Стоимость 1 шт. | S11: Итого | T11: 2 место Кол-во, шт. | U11: Стоимость 1 шт. | V11: Итого | W11: 3 место Количество, шт. | X11: Стоимость 1 | Y11: Итого | Z11: Кол-во, шт. | AA11: Стоимость 1 шт. | AB11: Итого | AC11: Кол-во ед наградного материала | AD11: Сумма
B12: ФИЗКУЛЬТУРНЫЕ МЕРОПРИЯТИЯ СРЕДИ РАЗЛИЧНЫХ ВОЗРАСТНЫХ ГРУПП НАСЕЛЕНИЯ И ИНВАЛИДОВ
B13: ГОТОВ К ТРУДУ И ОБОРОНЕ
A14: 1 | B14: Краевой фестиваль Всероссийского физкультурно-спортивного комплекса «Готов к труду и обороне» (ГТО) среди семейных команд | C14: КС | D14: мальчики, девочки 9-10 лет, мужчины, женщины 25-64 года | E14: 46162 | F14: 46172 | G14: г. Туапсе | H14: 1 | I14: 3400 | J14: =H14*I14 -> 3400 | K14: 1 | L14: 3000 | M14: =K14*L14 -> 3000 | N14: 1 | O14: 2900 | P14: =N14*O14 -> 2900 | Q14: 4 | R14: 190 | S14: =Q14*R14 -> 760 | T14: 4 | U14: 190 | V14: =T14*U14 -> 760 | W14: 4 | X14: 190 | Y14: =W14*X14 -> 760 | Z14: 15 | AA14: 6 | AB14: =Z14*AA14 -> 90 | AC14: =H14+K14+N14+Q14+T14+W14+Z14 -> 30 | AD14: =J14+M14+P14+S14+V14+Y14+AB14 -> 11670 | AF14: 15
A15: 2 | B15: Краевой Фестиваль Всероссийского физкультурно-спортивного комплекса «Готов к труду и обороне» (ГТО) среди обучающихся образовательных организаций высшего образования | C15: КС | D15: от 18 до 24 лет | E15: 46066 | F15: 46066 | G15: Краснодарский край | H15: 1 | I15: 3400 | J15: =H15*I15 -> 3400 | K15: 1 | L15: 3000 | M15: =K15*L15 -> 3000 | N15: 1 | O15: 2900 | P15: =N15*O15 -> 2900 | Q15: 4 | R15: 190 | S15: =Q15*R15 -> 760 | T15: 4 | U15: 190 | V15: =T15*U15 -> 760 | W15: 4 | X15: 190 | Y15: =W15*X15 -> 760 | Z15: 15 | AA15: 6 | AB15: =Z15*AA15 -> 90 | AC15: =H15+K15+N15+Q15+T15+W15+Z15 -> 30 | AD15: =J15+M15+P15+S15+V15+Y15+AB15 -> 11670 | AF15: 27
A16: 3 | B16: Краевой Фестиваль Всероссийского физкультурно-спортивного комплекса «Готов к труду и обороне» (ГТО) среди граждан, проживающих в сельской местности | C16: КС | D16: от 16 до 49 лет | E16: 46193 | F16: 46193 | G16: Краснодарский край | H16: 1 | I16: 3400 | J16: =H16*I16 -> 3400 | K16: 1 | L16: 3000 | M16: =K16*L16 -> 3000 | N16: 1 | O16: 2900 | P16: =N16*O16 -> 2900 | Q16: 8 | R16: 190 | S16: =Q16*R16 -> 1520 | T16: 8 | U16: 190 | V16: =T16*U16 -> 1520 | W16: 8 | X16: 190 | Y16: =W16*X16 -> 1520 | Z16: 27 | AA16: 6 | AB16: =Z16*AA16 -> 162 | AC16: =H16+K16+N16+Q16+T16+W16+Z16 -> 54 | AD16: =J16+M16+P16+S16+V16+Y16+AB16 -> 14022
A17: 4 | B17: Физкультурное мероприятие "Всекубанский казачий слет "Готов к труду и обороне" | C17: КС | D17: от 20 до 49 лет | E17: 46305 | F17: 46305 | G17: Краснодарский край | H17: 1 | I17: 3400 | J17: =H17*I17 -> 3400 | K17: 1 | L17: 3000 | M17: =K17*L17 -> 3000 | N17: 1 | O17: 2900 | P17: =N17*O17 -> 2900 | Q17: 4 | R17: 190 | S17: =Q17*R17 -> 760 | T17: 4 | U17: 190 | V17: =T17*U17 -> 760 | W17: 4 | X17: 190 | Y17: =W17*X17 -> 760 | Z17: 15 | AA17: 6 | AB17: =Z17*AA17 -> 90 | AC17: =H17+K17+N17+Q17+T17+W17+Z17 -> 30 | AD17: =J17+M17+P17+S17+V17+Y17+AB17 -> 11670
A18: 5 | B18: Краевой фестиваль чемпионов Всероссийского физкультурно-спортивного комплекса "Готов к труду и обороне" | C18: КС | D18: от 18 до 49 | E18: 46291 | F18: 46291 | G18: Краснодарский край | H18: 1 | I18: 3400 | J18: =H18*I18 -> 3400 | K18: 1 | L18: 3000 | M18: =K18*L18 -> 3000 | N18: 1 | O18: 2900 | P18: =N18*O18 -> 2900 | Q18: 5 | R18: 190 | S18: =Q18*R18 -> 950 | T18: 5 | U18: 190 | V18: =T18*U18 -> 950 | W18: 5 | X18: 190 | Y18: =W18*X18 -> 950 | Z18: 15 | AA18: 6 | AB18: =Z18*AA18 -> 90 | AC18: =H18+K18+N18+Q18+T18+W18+Z18 -> 33 | AD18: =J18+M18+P18+S18+V18+Y18+AB18 -> 12240
A19: 6 | B19: Краевой день бега "Кросс Нации" в рамках Всероссийского дня бега "Кросс Нации" | C19: КС | D19: согласно положению | E19: сентябрь | F19: сентябрь | G19: согласно положению | Q19: 118 | R19: 190 | S19: =Q19*R19 -> 22420 | T19: 118 | U19: 190 | V19: =T19*U19 -> 22420 | W19: 118 | X19: 190 | Y19: =W19*X19 -> 22420 | Z19: 354 | AA19: 6 | AB19: =Z19*AA19 -> 2124 | AC19: =H19+K19+N19+Q19+T19+W19+Z19 -> 708 | AD19: =J19+M19+P19+S19+V19+Y19+AB19 -> 69384
A20: 7 | B20: Краевые соревнования по городошному спорту среди ветеранов физической культуры и спорта Кубани | C20: КС | D20: 35 лет и старше | E20: октябрь | F20: октябрь | G20: согласно положению | Q20: 6 | R20: 190 | S20: =Q20*R20 -> 1140 | T20: 6 | U20: 190 | V20: =T20*U20 -> 1140 | W20: 6 | X20: 190 | Y20: =W20*X20 -> 1140 | Z20: 18 | AA20: 6 | AB20: =Z20*AA20 -> 108 | AC20: =H20+K20+N20+Q20+T20+W20+Z20 -> 36 | AD20: =J20+M20+P20+S20+V20+Y20+AB20 -> 3528
A21: 8 | B21: Всекубанская эстафета «Спортсмены Кубани – в ознаменование Победы в Великой Отечественной войне 1941-1945 годов» | C21: КС | D21: согласно положению | E21: июнь | F21: июнь | G21: согласно положению | Q21: 118 | R21: 190 | S21: =Q21*R21 -> 22420 | T21: 118 | U21: 190 | V21: =T21*U21 -> 22420 | W21: 118 | X21: 190 | Y21: =W21*X21 -> 22420 | Z21: 354 | AA21: 6 | AB21: =Z21*AA21 -> 2124 | AC21: =H21+K21+N21+Q21+T21+W21+Z21 -> 708 | AD21: =J21+M21+P21+S21+V21+Y21+AB21 -> 69384
A22: 3 | B22: Краевой Фестиваль Всероссийского физкультурно-спортивного комплекса "Готов к труду и обороне" (ГТО) среди трудовых коллективов, посвященного празднованию 80-летия Победы советского народа в Великой Отечественной войне 1941-1945 годов | C22: КС | D22: мужчины, женщины 25-64 года | E22: 46067 | F22: 46067 | G22: Краснодарский край | H22: 1 | I22: 3300 | J22: =H22*I22 -> 3300 | K22: 1 | L22: 2850 | M22: =K22*L22 -> 2850 | N22: 1 | O22: 2750 | P22: =N22*O22 -> 2750 | Q22: 8 | R22: 190 | S22: =Q22*R22 -> 1520 | T22: 8 | U22: 190 | V22: =T22*U22 -> 1520 | W22: 8 | X22: 190 | Y22: =W22*X22 -> 1520 | Z22: 27 | AA22: 6 | AB22: =Z22*AA22 -> 162 | AE22: =H22+K22+N22+Q22+T22+W22+Z22 -> 54 | AF22: =J22+M22+P22+S22+V22+Y22+AB22 -> 13622 | AH22: положение 12.01.2026
A23: 4 | B23: Краевой фестиваль Всероссийского физкультурно-спортивного комплекса «Готов к труду и обороне» (ГТО) среди обучающихся профессиональных образовательных организаций | C23: КС | D23: юноши, девушки 16-19 лет | E23: 46066 | F23: 46066 | G23: Краснодарский край | H23: 1 | I23: 3300 | J23: =H23*I23 -> 3300 | K23: 1 | L23: 2850 | M23: =K23*L23 -> 2850 | N23: 1 | O23: 2750 | P23: =N23*O23 -> 2750 | Q23: 4 | R23: 190 | S23: =Q23*R23 -> 760 | T23: 4 | U23: 190 | V23: =T23*U23 -> 760 | W23: 4 | X23: 190 | Y23: =W23*X23 -> 760 | Z23: 15 | AA23: 6 | AB23: =Z23*AA23 -> 90 | AE23: =H23+K23+N23+Q23+T23+W23+AB23 -> 105 | AF23: =J23+M23+P23+S23+V23+Y23+AB23 -> 11270 | AH23: положение 12.01.2026
A24: 5 | B24: Краевые соревнования юных хоккеистов ,,Золотая шайба" | C24: КС | D24: 2013-2014 г.р. | E24: 46040 | F24: 46042 | G24: г.Горячий ключ | H24: 1 | I24: 3300 | J24: =H24*I24 -> 3300 | K24: 1 | L24: 2850 | M24: =K24*L24 -> 2850 | N24: 1 | O24: 2750 | P24: =N24*O24 -> 2750 | Q24: 19 | R24: 190 | S24: =Q24*R24 -> 3610 | T24: 19 | U24: 190 | V24: =T24*U24 -> 3610 | W24: 19 | X24: 190 | Y24: =W24*X24 -> 3610 | Z24: 60 | AA24: 6 | AB24: =Z24*AA24 -> 360 | AE24: =H24+K24+N24+Q24+T24+W24+Z24 -> 120 | AF24: =J24+M24+P24+S24+V24+Y24+AB24 -> 20090 | AH24: положение 24.12.2026
A25: 6 | B25: Краевые соревнования юных хоккеистов ,,Золотая шайба" | C25: КС | D25: 2015-2016 г.р. | E25: 46044 | F25: 46046 | G25: г.Горячий ключ | H25: 1 | I25: 3300 | J25: =H25*I25 -> 3300 | K25: 1 | L25: 2850 | M25: =K25*L25 -> 2850 | N25: 1 | O25: 2750 | P25: =N25*O25 -> 2750 | Q25: 19 | R25: 190 | S25: =Q25*R25 -> 3610 | T25: 19 | U25: 190 | V25: =T25*U25 -> 3610 | W25: 19 | X25: 190 | Y25: =W25*X25 -> 3610 | Z25: 60 | AA25: 6 | AB25: =Z25*AA25 -> 360 | AE25: =H25+K25+N25+Q25+T25+W25+Z25 -> 120 | AF25: =J25+M25+P25+S25+V25+Y25+AB25 -> 20090 | AH25: положение 24.12.2026
A26: 7 | B26: Краевые соревнования юных хоккеистов ,,Золотая шайба" | C26: КС | D26: 2009-2010 г.р. | E26: 46037 | F26: 46039 | G26: г.Краснодар | H26: 1 | I26: 3300 | J26: =H26*I26 -> 3300 | K26: 1 | L26: 2850 | M26: =K26*L26 -> 2850 | N26: 1 | O26: 2750 | P26: =N26*O26 -> 2750 | Q26: 19 | R26: 190 | S26: =Q26*R26 -> 3610 | T26: 19 | U26: 190 | V26: =T26*U26 -> 3610 | W26: 19 | X26: 190 | Y26: =W26*X26 -> 3610 | Z26: 60 | AA26: 6 | AB26: =Z26*AA26 -> 360 | AE26: =H26+K26+N26+Q26+T26+W26+Z26 -> 120 | AF26: =J26+M26+P26+S26+V26+Y26+AB26 -> 20090 | AH26: положение 24.12.2026
A27: 8 | B27: Краевые соревнования юных хоккеистов ,,Золотая шайба" | C27: КС | D27: 2009-2010 г.р. | E27: 46036 | F27: 46036 | G27: г.Краснодар | H27: 1 | I27: 3300 | J27: =H27*I27 -> 3300 | K27: 1 | L27: 2850 | M27: =K27*L27 -> 2850 | N27: 1 | O27: 2750 | P27: =N27*O27 -> 2750 | Q27: 19 | R27: 190 | S27: =Q27*R27 -> 3610 | T27: 19 | U27: 190 | V27: =T27*U27 -> 3610 | W27: 19 | X27: 190 | Y27: =W27*X27 -> 3610 | Z27: 60 | AA27: 6 | AB27: =Z27*AA27 -> 360 | AE27: =H27+K27+N27+Q27+T27+W27+Z27 -> 120 | AF27: =J27+M27+P27+S27+V27+Y27+AB27 -> 20090 | AH27: положение 24.12.2026
B28: ФИЗКУЛЬТУРНЫЕ МЕРОПРИЯТИЯ
A29: 9 | B29: XXXV Универсиада Кубани среди высших учебных заведений (по видам спорта) | C29: КС | D29: юноши, девушки 1999 - 2006 г.р. | E29: январь | F29: май | G29: г. Краснодар | H29: 11 | I29: 3400 | J29: =H29*I29 -> 37400 | K29: 11 | L29: 3000 | M29: =K29*L29 -> 33000 | N29: 11 | O29: 2900 | P29: =N29*O29 -> 31900 | Q29: 159 | R29: 190 | S29: =Q29*R29 -> 30210 | T29: 159 | U29: 190 | V29: =T29*U29 -> 30210 | W29: 257 | X29: 190 | Y29: =W29*X29 -> 48830 | Z29: 610 | AA29: 6 | AB29: =Z29*AA29 -> 3660 | AC29: =H29+K29+N29+Q29+T29+W29+Z29 -> 1218 | AD29: =J29+M29+P29+S29+V29+Y29+AB29 -> 215210
A30: 10 | B30: XVII Спартакиада среди сборных команд органов исполнительной власти и структурных подразделений администрации Краснодарского края (по видам спорта) | C30: КС | D30: 18 лет и старше | E30: февраль | F30: декабрь | G30: г. Краснодар | H30: 21 | I30: 3400 | J30: =H30*I30 -> 71400 | K30: 21 | L30: 3000 | M30: =K30*L30 -> 63000 | N30: 21 | O30: 2900 | P30: =N30*O30 -> 60900 | Q30: 149 | R30: 190 | S30: =Q30*R30 -> 28310 | T30: 149 | U30: 190 | V30: =T30*U30 -> 28310 | W30: 149 | X30: 190 | Y30: =W30*X30 -> 28310 | Z30: 522 | AA30: 6 | AB30: =Z30*AA30 -> 3132 | AC30: =H30+K30+N30+Q30+T30+W30+Z30 -> 1032 | AD30: =J30+M30+P30+S30+V30+Y30+AB30 -> 283362
A31: 11 | B31: XXXIII Сельские спортивные игры Кубани | C31: КС | D31: мужчины, женщины 18 лет и старше | E31: 46037 | F31: 46203 | G31: муниципальные образования Краснодарского края | H31: 20 | I31: 3400 | J31: =H31*I31 -> 68000 | K31: 20 | L31: 3000 | M31: =K31*L31 -> 60000 | N31: 20 | O31: 2900 | P31: =N31*O31 -> 58000 | Q31: 116 | R31: 190 | S31: =Q31*R31 -> 22040 | T31: 116 | U31: 190 | V31: =T31*U31 -> 22040 | W31: 116 | X31: 190 | Y31: =W31*X31 -> 22040 | Z31: 408 | AA31: 6 | AB31: =Z31*AA31 -> 2448 | AC31: 500 | AD31: =J31+M31+P31+S31+V31+Y31+AB31 -> 254568
A32: 12 | B32: Турнир Краснодарского края по волейболу среди команд ветеранов в честь Дня Защитника Отечества | C32: КС | D32: мужчины 40 лет и старше, женщины 35 лет и старше | E32: 46065 | F32: 46068 | G32: п. Ольгинка (Туапсинский район) | H32: 6 | I32: 3400 | J32: =H32*I32 -> 20400 | K32: 6 | L32: 3000 | M32: =K32*L32 -> 18000 | N32: 6 | O32: 2900 | P32: =N32*O32 -> 17400 | Q32: 60 | R32: 190 | S32: =Q32*R32 -> 11400 | T32: 60 | U32: 190 | V32: =T32*U32 -> 11400 | W32: 60 | X32: 190 | Y32: =W32*X32 -> 11400 | Z32: 18 | AA32: 6 | AB32: =Z32*AA32 -> 108 | AC32: =H32+K32+N32+Q32+T32+W32+Z32 -> 216 | AD32: =J32+M32+P32+S32+V32+Y32+AB32 -> 90108 | AF32: 18
A33: 13 | B33: Краевой турнир по волейболу среди среди сильнейших команд ветеранов | C33: КС | D33: мужчины 40 лет и старше, женщины 35 лет и старше | E33: февраль | F33: февраль | G33: п. Ольгинка (Туапсинский район) | H33: 6 | I33: 3400 | J33: =H33*I33 -> 20400 | K33: 6 | L33: 3000 | M33: =K33*L33 -> 18000 | N33: 6 | O33: 2900 | P33: =N33*O33 -> 17400 | Q33: 60 | R33: 190 | S33: =Q33*R33 -> 11400 | T33: 60 | U33: 190 | V33: =T33*U33 -> 11400 | W33: 60 | X33: 190 | Y33: =W33*X33 -> 11400 | Z33: 20 | AA33: 6 | AB33: =Z33*AA33 -> 120 | AC33: =H33+K33+N33+Q33+T33+W33+Z33 -> 218 | AD33: =J33+M33+P33+S33+V33+Y33+AB33 -> 90120 | AF33: 18
A34: 14 | B34: Краевые соревнования по настольному теннису среди ветеранов физической культуры и спорта Кубани памяти МС МК ЗТР Г.М. Стрельникова | C34: КС | D34: мужчины 40-70+ лет, женщины 40-55+ лет | E34: март | F34: март | G34: согласно положению | Q34: 8 | R34: 190 | S34: =Q34*R34 -> 1520 | T34: 8 | U34: 190 | V34: =T34*U34 -> 1520 | W34: 16 | X34: 190 | Y34: =W34*X34 -> 3040 | Z34: 32 | AA34: 6 | AB34: =Z34*AA34 -> 192 | AC34: =H34+K34+N34+Q34+T34+W34+Z34 -> 64 | AD34: =J34+M34+P34+S34+V34+Y34+AB34 -> 6272 | AF34: 32
A35: 15 | B35: Краевой турнир по футболу среди смешанных детских команд (девочки и мальчики до 12 лет) I этап (региональный) | C35: КС | D35: девочки и мальчики до 12 лет | E35: 46113 | F35: 46142 | G35: г. Краснодар | H35: 1 | I35: 3400 | J35: =H35*I35 -> 3400 | K35: 1 | L35: 3000 | M35: =K35*L35 -> 3000 | N35: 1 | O35: 2900 | P35: =N35*O35 -> 2900 | Q35: 13 | R35: 190 | S35: =Q35*R35 -> 2470 | T35: 13 | U35: 190 | V35: =T35*U35 -> 2470 | W35: 13 | X35: 190 | Y35: =W35*X35 -> 2470 | Z35: 48 | AA35: 6 | AB35: =Z35*AA35 -> 288 | AC35: =H35+K35+N35+Q35+T35+W35+Z35 -> 90 | AD35: =J35+M35+P35+S35+V35+Y35+AB35 -> 16998 | AF35: 47
A36: 16 | B36: Краевой турнир по футболу "Кожаный мяч - Лига юных футболистов" II этап (региональный) | C36: КТ | D36: девочки и мальчики до 12, до 14 лет и до 16 лет, мальчики до 18 лет | E36: 46119 | F36: 46203 | G36: города и районы Краснодарского края, г. Краснодар | H36: 10 | I36: 3400 | J36: =H36*I36 -> 34000 | K36: 10 | L36: 3000 | M36: =K36*L36 -> 30000 | N36: 10 | O36: 2900 | P36: =N36*O36 -> 29000 | Q36: 143 | R36: 190 | S36: =Q36*R36 -> 27170 | T36: 143 | U36: 190 | V36: =T36*U36 -> 27170 | W36: 143 | X36: 190 | Y36: =W36*X36 -> 27170 | Z36: 520 | AA36: 6 | AB36: =Z36*AA36 -> 3120 | AC36: =H36+K36+N36+Q36+T36+W36+AA36 -> 465 | AD36: =J36+M36+P36+S36+V36+Y36+AB36 -> 177630 | AF36: 519
A37: 17 | B37: Краевой турнир по футболу "Кожаный мяч - детям" I этап (региональный) | C37: КТ | D37: мальчики до 10 лет | E37: 46266 | F37: 46295 | G37: г. Краснодар | H37: 1 | I37: 3400 | J37: =H37*I37 -> 3400 | K37: 1 | L37: 3000 | M37: =K37*L37 -> 3000 | N37: 1 | O37: 2900 | P37: =N37*O37 -> 2900 | Q37: 11 | R37: 190 | S37: =Q37*R37 -> 2090 | T37: 11 | U37: 190 | V37: =T37*U37 -> 2090 | W37: 11 | X37: 190 | Y37: =W37*X37 -> 2090 | Z37: 42 | AA37: 6 | AB37: =Z37*AA37 -> 252 | AC37: =H37+K37+N37+Q37+T37+W37+AA37 -> 42 | AD37: =J37+M37+P37+S37+V37+Y37+AB37 -> 15822 | AF37: 519
A38: 18 | B38: Физкультурное мероприятие по футболу среди мальчиков до 10 лет. Предварительный этап Финальный этап. | C38: КТ | D38: мальчики до 10 лет 2017г.р. | E38: 24.04.2026 23.05.2026 | F38: 17.05.2026 27.05.2026 | G38: п. Новомихайловский Туапсинский р-н | H38: 1 | I38: 3400 | J38: =H38*I38 -> 3400 | K38: 1 | L38: 3000 | M38: =K38*L38 -> 3000 | N38: 1 | O38: 2900 | P38: =N38*O38 -> 2900 | Q38: 15 | R38: 190 | S38: =Q38*R38 -> 2850 | T38: 15 | U38: 190 | V38: =T38*U38 -> 2850 | W38: 15 | X38: 190 | Y38: =W38*X38 -> 2850 | Z38: 53 | AA38: 6 | AB38: =Z38*AA38 -> 318 | AC38: =H38+K38+N38+Q38+T38+W38+Z38 -> 101 | AD38: =J38+M38+P38+S38+V38+Y38+AB38 -> 18168
A39: 19 | B39: Краевой турнир по футболу среди смешанных детских команд (девочки и мальчики до 10 лет) I этап (региональный) | C39: КС | D39: девочки и мальчики до 10 лет | E39: 46113 | F39: 46142 | G39: г. Краснодар | H39: 1 | I39: 3400 | J39: =H39*I39 -> 3400 | K39: 1 | L39: 3000 | M39: =K39*L39 -> 3000 | N39: 1 | O39: 2900 | P39: =N39*O39 -> 2900 | Q39: 11 | R39: 190 | S39: =Q39*R39 -> 2090 | T39: 11 | U39: 190 | V39: =T39*U39 -> 2090 | W39: 11 | X39: 190 | Y39: =W39*X39 -> 2090 | Z39: 42 | AA39: 6 | AB39: =Z39*AA39 -> 252 | AC39: =H39+K39+N39+Q39+T39+W39+Z39 -> 78 | AD39: =J39+M39+P39+S39+V39+Y39+AB39 -> 15822 | AF39: 41
A40: 20 | B40: Краевые семейные спортивные игры «Стартуем вместе» I этап, II этап | C40: КС | D40: согласно положению | E40: февраль | F40: июнь | G40: муниципальные образования Краснодарского края, г. Славянск-на -Кубани | H40: 2 | I40: 3400 | J40: =H40*I40 -> 6800 | K40: 2 | L40: 3000 | M40: =K40*L40 -> 6000 | N40: 2 | O40: 2900 | P40: =N40*O40 -> 5800 | Q40: 26 | R40: 190 | S40: =Q40*R40 -> 4940 | T40: 26 | U40: 190 | V40: =T40*U40 -> 4940 | W40: 26 | X40: 190 | Y40: =W40*X40 -> 4940 | Z40: 36 | AA40: 6 | AB40: =Z40*AA40 -> 216 | AC40: =H40+K40+N40+Q40+T40+W40+Z40 -> 120 | AD40: =J40+M40+P40+S40+V40+Y40+AB40 -> 33636
A41: 21 | B41: Спартакиада пенсионеров Краснодарского края 2026 года | C41: КС | D41: мужчины (60 лет и старше), женщины (55 лет и старше) | E41: май | F41: май | G41: г. Краснодар | H41: 1 | I41: 3400 | J41: =H41*I41 -> 3400 | K41: 1 | L41: 3000 | M41: =K41*L41 -> 3000 | N41: 1 | O41: 2900 | P41: =N41*O41 -> 2900 | Q41: 16 | R41: 190 | S41: =Q41*R41 -> 3040 | T41: 16 | U41: 190 | V41: =T41*U41 -> 3040 | W41: 16 | X41: 190 | Y41: =W41*X41 -> 3040 | Z41: 51 | AA41: 6 | AB41: =Z41*AA41 -> 306 | AC41: =H41+K41+N41+Q41+T41+W41+Z41 -> 102 | AD41: =J41+M41+P41+S41+V41+Y41+AB41 -> 18726
A42: 22 | B42: Первенство по волейболу среди мужских и женских команд ветеранов памяти В.П. Белянского | C42: ПК | D42: мужчины 40 лет и старше, женщины 35 лет и старше | E42: июнь | F42: июнь | G42: с. Ольгинка (Туапсинский район) | H42: 6 | I42: 3400 | J42: =H42*I42 -> 20400 | K42: 6 | L42: 3000 | M42: =K42*L42 -> 18000 | N42: 6 | O42: 2900 | P42: =N42*O42 -> 17400 | Q42: 60 | R42: 190 | S42: =Q42*R42 -> 11400 | T42: 60 | U42: 190 | V42: =T42*U42 -> 11400 | W42: 60 | X42: 190 | Y42: =W42*X42 -> 11400 | Z42: 20 | AA42: 6 | AB42: =Z42*AA42 -> 120 | AC42: =H42+K42+N42+Q42+T42+W42+Z42 -> 218 | AD42: =J42+M42+P42+S42+V42+Y42+AB42 -> 90120
A43: 23 | B43: Краевые соревнования среди ветеранов физической культуры и спорта Кубани, посвящённые Всероссийскому Дню физкультурника | C43: КС | D43: согласно положению | E43: июль | F43: июль | G43: согласно положению | Q43: 24 | R43: 190 | S43: =Q43*R43 -> 4560 | T43: 24 | U43: 190 | V43: =T43*U43 -> 4560 | W43: 24 | X43: 190 | Y43: =W43*X43 -> 4560 | Z43: 72 | AA43: 6 | AB43: =Z43*AA43 -> 432 | AC43: =H43+K43+N43+Q43+T43+W43+Z43 -> 144 | AD43: =J43+M43+P43+S43+V43+Y43+AB43 -> 14112
A44: 24 | B44: Весенний забег "Парковые тропы" | C44: ПК | D44: мальчики, девочки (4-15 лет), мужчины, женщины (16-61+) | E44: 46095 | F44: 46095 | G44: г. Краснодар | Q44: 42 | R44: 190 | S44: =Q44*R44 -> 7980 | T44: 42 | U44: 190 | V44: =T44*U44 -> 7980 | W44: 42 | X44: 190 | Y44: =W44*X44 -> 7980 | AA44: 6 | AB44: =Z44*AA44 -> 0 | AC44: =H44+K44+N44+Q44+T44+W44+Z44 -> 126 | AD44: =J44+M44+P44+S44+V44+Y44+AB44 -> 23940
A45: 25 | B45: Ночной забег- "Кубанская миля" | C45: КС | D45: 8 лет и старше | E45: декабрь | F45: декабрь | G45: по положению | Q45: 54 | R45: 190 | S45: =Q45*R45 -> 10260 | T45: 54 | U45: 190 | V45: =T45*U45 -> 10260 | W45: 54 | X45: 190 | Y45: =W45*X45 -> 10260 | Z45: 162 | AA45: 190 | AB45: =Z45*AA45 -> 30780 | AC45: =H45+K45+N45+Q45+T45+W45+Z45 -> 324 | AD45: =J45+M45+P45+S45+V45+Y45+AB45 -> 61560
A46: 26 | B46: Краевые соревнования среди школьников по самбо в рамках Всероссийской школьной лиги самбо на Кубок Губернатора Краснодарского края | C46: КГ | D46: 12-14 лет | E46: сентябрь | F46: ноябрь | G46: Краснодарский край | H46: 5 | I46: 7300 | J46: =H46*I46 -> 36500 | K46: 5 | L46: 6650 | M46: =K46*L46 -> 33250 | N46: 5 | O46: 6050 | P46: =N46*O46 -> 30250 | Q46: 72 | R46: 190 | S46: =Q46*R46 -> 13680 | T46: 72 | U46: 190 | V46: =T46*U46 -> 13680 | W46: 122 | X46: 190 | Y46: =W46*X46 -> 23180 | Z46: 695 | AA46: 6 | AB46: =Z46*AA46 -> 4170 | AC46: =H46+K46+N46+Q46+T46+W46+Z46 -> 976 | AD46: =J46+M46+P46+S46+V46+Y46+AB46 -> 154710
A47: 27 | B47: Краевой фестиваль "Я рисую самбо" | Z47: 30 | AA47: 6 | AB47: =Z47*AA47 -> 180 | AD47: =AB47 -> 180
A48: 28 | B48: Краевые спортивные игры "Спорт против наркотиков" I этап II этап | C48: КС | D48: 12-15 лет | E48: 12.05.2026 26.06.2026 | F48: 01.06.2026 26.06.2026 | G48: МО Краснодарского края | Q48: 24 | R48: 190 | S48: =Q48*R48 -> 4560 | T48: 24 | U48: 190 | V48: =T48*U48 -> 4560 | W48: 24 | X48: 190 | Y48: =W48*X48 -> 4560 | Z48: 72 | AA48: 6 | AB48: =Z48*AA48 -> 432 | AC48: =Q48+T48+W48+Z48 -> 144 | AD48: =S48+V48+Y48+AB48 -> 14112
A49: 29 | B49: 3 этап Краевых соревнований по пляжному волейболу среди команд ветеранов - "Кубок федерации 2026", посвященные Дню Победы в Великой Отечественной войне | C49: КС | D49: мужчины, женщины 35 лет и старше | E49: май | F49: май | G49: г. Краснодар | H49: 4 | I49: 3400 | J49: =H49*I49 -> 13600 | K49: 4 | L49: 3000 | M49: =K49*L49 -> 12000 | N49: 4 | O49: 2900 | P49: =N49*O49 -> 11600 | Q49: 8 | R49: 190 | S49: =Q49*R49 -> 1520 | T49: 8 | U49: 190 | V49: =T49*U49 -> 1520 | W49: 8 | X49: 190 | Y49: =W49*X49 -> 1520 | Z49: 40 | AA49: 6 | AB49: =Z49*AA49 -> 240 | AC49: =H49+K49+N49+Q49+T49+W49+Z49 -> 76 | AD49: =J49+M49+P49+S49+V49+Y49+AB49 -> 42000
A50: 30 | B50: 4 этап Краевых соревнований по пляжному волейболу среди команд ветеранов - "Кубок федерации 2026", посвященные Дню защиты детей | C50: КС | D50: мужчины, женщины 35 лет и старше | E50: май | F50: май | G50: г. Краснодар | H50: 3 | I50: 3400 | J50: =H50*I50 -> 10200 | K50: 3 | L50: 3000 | M50: =K50*L50 -> 9000 | N50: 3 | O50: 2900 | P50: =N50*O50 -> 8700 | Q50: 6 | R50: 190 | S50: =Q50*R50 -> 1140 | T50: 6 | U50: 190 | V50: =T50*U50 -> 1140 | W50: 6 | X50: 190 | Y50: =W50*X50 -> 1140 | Z50: 30 | AA50: 6 | AB50: =Z50*AA50 -> 180 | AC50: =H50+K50+N50+Q50+T50+W50+Z50 -> 57 | AD50: =J50+M50+P50+S50+V50+Y50+AB50 -> 31500
A51: 31 | B51: 5 этап Краевых соревнований по пляжному волейболу среди команд любителей - "Кубок федерации 2026", посвященные Дню России | C51: КС | D51: 18+ | E51: июнь | F51: июнь | G51: г. Краснодар | H51: 3 | I51: 3400 | J51: =H51*I51 -> 10200 | K51: 3 | L51: 3000 | M51: =K51*L51 -> 9000 | N51: 3 | O51: 2900 | P51: =N51*O51 -> 8700 | Q51: 6 | R51: 190 | S51: =Q51*R51 -> 1140 | T51: 6 | U51: 190 | V51: =T51*U51 -> 1140 | W51: 6 | X51: 190 | Y51: =W51*X51 -> 1140 | Z51: 30 | AA51: 6 | AB51: =Z51*AA51 -> 180 | AC51: =H51+K51+N51+Q51+T51+W51+Z51 -> 57 | AD51: =J51+M51+P51+S51+V51+Y51+AB51 -> 31500
A52: 32 | B52: 6 этап Краевых соревнований по пляжному волейболу среди команд любителей - "Кубок федерации 2026" | C52: КС | D52: 15+ | E52: июнь | F52: июнь | G52: г. Краснодар | H52: 3 | I52: 3400 | J52: =H52*I52 -> 10200 | K52: 3 | L52: 3000 | M52: =K52*L52 -> 9000 | N52: 3 | O52: 2900 | P52: =N52*O52 -> 8700 | Q52: 6 | R52: 190 | S52: =Q52*R52 -> 1140 | T52: 6 | U52: 190 | V52: =T52*U52 -> 1140 | W52: 6 | X52: 190 | Y52: =W52*X52 -> 1140 | Z52: 30 | AA52: 6 | AB52: =Z52*AA52 -> 180 | AC52: =H52+K52+N52+Q52+T52+W52+Z52 -> 57 | AD52: =J52+M52+P52+S52+V52+Y52+AB52 -> 31500
A53: 33 | B53: 7 этап Краевых соревнований по пляжному волейболу среди команд любителей - "Кубок федерации 2026", посвященные Дню семьи, любви и вернности | C53: КС | D53: женщины, мужчины | E53: июль | F53: июль | G53: г. Краснодар | H53: 3 | I53: 3400 | J53: =H53*I53 -> 10200 | K53: 3 | L53: 3000 | M53: =K53*L53 -> 9000 | N53: 3 | O53: 2900 | P53: =N53*O53 -> 8700 | Q53: 6 | R53: 190 | S53: =Q53*R53 -> 1140 | T53: 6 | U53: 190 | V53: =T53*U53 -> 1140 | W53: 6 | X53: 190 | Y53: =W53*X53 -> 1140 | Z53: 30 | AA53: 6 | AB53: =Z53*AA53 -> 180 | AC53: =H53+K53+N53+Q53+T53+W53+Z53 -> 57 | AD53: =J53+M53+P53+S53+V53+Y53+AB53 -> 31500
A54: 34 | B54: 8 этап Краевых соревнований по пляжному волейболу среди команд любителей - "Кубок федерации 2026", посвященные Международному Дню Дружбы | C54: КС | D54: женщины, мужчины | E54: июль | F54: июль | G54: г. Краснодар | H54: 3 | I54: 3400 | J54: =H54*I54 -> 10200 | K54: 3 | L54: 3000 | M54: =K54*L54 -> 9000 | N54: 3 | O54: 2900 | P54: =N54*O54 -> 8700 | Q54: 6 | R54: 190 | S54: =Q54*R54 -> 1140 | T54: 6 | U54: 190 | V54: =T54*U54 -> 1140 | W54: 6 | X54: 190 | Y54: =W54*X54 -> 1140 | Z54: 30 | AA54: 6 | AB54: =Z54*AA54 -> 180 | AC54: =H54+K54+N54+Q54+T54+W54+Z54 -> 57 | AD54: =J54+M54+P54+S54+V54+Y54+AB54 -> 31500
A55: 35 | B55: 9 этап Краевых соревнований по пляжному волейболу среди команд любителей - "Кубок федерации 2026", посвященные Дню Физкультурника | C55: КС | D55: женщины | E55: июль | F55: июль | G55: г. Краснодар | H55: 3 | I55: 3400 | J55: =H55*I55 -> 10200 | K55: 3 | L55: 3000 | M55: =K55*L55 -> 9000 | N55: 3 | O55: 2900 | P55: =N55*O55 -> 8700 | Q55: 6 | R55: 190 | S55: =Q55*R55 -> 1140 | T55: 6 | U55: 190 | V55: =T55*U55 -> 1140 | W55: 6 | X55: 190 | Y55: =W55*X55 -> 1140 | Z55: 30 | AA55: 6 | AB55: =Z55*AA55 -> 180 | AC55: =H55+K55+N55+Q55+T55+W55+Z55 -> 57 | AD55: =J55+M55+P55+S55+V55+Y55+AB55 -> 31500
A56: 36 | B56: 10 этап Краевых соревнований по пляжному волейболу среди команд любителей - "Кубок федерации 2026", посвященные Дню государственного флага РФ | C56: КС | D56: женщины | E56: июль | F56: июль | G56: г. Краснодар | H56: 3 | I56: 3400 | J56: =H56*I56 -> 10200 | K56: 3 | L56: 3000 | M56: =K56*L56 -> 9000 | N56: 3 | O56: 2900 | P56: =N56*O56 -> 8700 | Q56: 6 | R56: 190 | S56: =Q56*R56 -> 1140 | T56: 6 | U56: 190 | V56: =T56*U56 -> 1140 | W56: 6 | X56: 190 | Y56: =W56*X56 -> 1140 | Z56: 30 | AA56: 6 | AB56: =Z56*AA56 -> 180 | AC56: =H56+K56+N56+Q56+T56+W56+Z56 -> 57 | AD56: =J56+M56+P56+S56+V56+Y56+AB56 -> 31500
A57: 37 | B57: 11 этап Краевых соревнований по пляжному волейболу среди команд любителей - "Кубок федерации 2026", посвященные Дню Краснодарского края | C57: КС | D57: женщины | E57: июль | F57: июль | G57: г. Краснодар | H57: 3 | I57: 3400 | J57: =H57*I57 -> 10200 | K57: 3 | L57: 3000 | M57: =K57*L57 -> 9000 | N57: 3 | O57: 2900 | P57: =N57*O57 -> 8700 | Q57: 6 | R57: 190 | S57: =Q57*R57 -> 1140 | T57: 6 | U57: 190 | V57: =T57*U57 -> 1140 | W57: 6 | X57: 190 | Y57: =W57*X57 -> 1140 | Z57: 30 | AA57: 6 | AB57: =Z57*AA57 -> 180 | AC57: =H57+K57+N57+Q57+T57+W57+Z57 -> 57 | AD57: =J57+M57+P57+S57+V57+Y57+AB57 -> 31500
A58: 38 | B58: Спартакиада трудящихся Краснодарского края, посвященная празднованию 80-летия Победы советского народа в Великой Отечественной войне 1941-1945 годов | C58: КС | D58: согласно положению | E58: январь | F58: июнь | G58: МО Краснодарского края | H58: 44 | I58: 3400 | J58: =H58*I58 -> 149600 | K58: 44 | L58: 3000 | M58: =K58*L58 -> 132000 | N58: 44 | O58: 2900 | P58: =N58*O58 -> 127600 | Q58: 280 | R58: 190 | S58: =Q58*R58 -> 53200 | T58: 280 | U58: 190 | V58: =T58*U58 -> 53200 | W58: 280 | X58: 190 | Y58: =W58*X58 -> 53200 | Z58: 972 | AA58: 6 | AB58: =Z58*AA58 -> 5832 | AC58: =H58+K58+N58+Q58+T58+W58+Z58 -> 1944 | AD58: =J58+M58+P58+S58+V58+Y58+AB58 -> 574632
A59: 39 | B59: 12 этап Краевых соревнований по пляжному волейболу среди команд любителей - "Кубок федерации 2026", посвященные Дню города Краснодара | C59: КС | D59: женщины | E59: июль | F59: июль | G59: г. Краснодар | H59: 3 | I59: 3400 | J59: =H59*I59 -> 10200 | K59: 3 | L59: 3000 | M59: =K59*L59 -> 9000 | N59: 3 | O59: 2900 | P59: =N59*O59 -> 8700 | Q59: 6 | R59: 190 | S59: =Q59*R59 -> 1140 | T59: 6 | U59: 190 | V59: =T59*U59 -> 1140 | W59: 6 | X59: 190 | Y59: =W59*X59 -> 1140 | Z59: 30 | AA59: 6 | AB59: =Z59*AA59 -> 180 | AC59: =H59+K59+N59+Q59+T59+W59+Z59 -> 57 | AD59: =J59+M59+P59+S59+V59+Y59+AB59 -> 31500
A60: 40 | B60: Всекубанский турнир по футболу среди детских дворовых команд на Кубок Губернатора Краснодарского края I этап II этап III этап IV этап | C60: КГ | D60: 10-15 лет | E60: 15.06.2026 01.07.2026 15.07.2026 20.07.2026 | F60: 29.06.2026 12.07.2026 31.07.2026 03.08.2026 | G60: муниципальные образования, городских и сельских поселениях Кранодарского края | H60: 3 | I60: 7300 | J60: =H60*I60 -> 21900 | K60: 3 | L60: 6650 | M60: =K60*L60 -> 19950 | N60: 3 | O60: 6050 | P60: =N60*O60 -> 18150 | Q60: 11 | R60: 190 | S60: =Q60*R60 -> 2090 | T60: 11 | U60: 190 | V60: =T60*U60 -> 2090 | W60: 11 | X60: 190 | Y60: =W60*X60 -> 2090 | Z60: 693 | AA60: 6 | AB60: =Z60*AA60 -> 4158 | AC60: =H60+K60+N60+Q60+T60+W60+Z60 -> 735 | AD60: =J60+M60+P60+S60+V60+Y60+AB60 -> 70428
A61: 41 | B61: Краевой фестиваль по плаванию "Я-Пловец" II этап | C61: КС | D61: мальчики, девочки 8 лет, девушки, юноши 10-11 лет, девушки, юноши 11-13 лет | E61: 18.05.2026 | F61: 19.05.2026 | G61: г. Краснодар | Q61: 8 | R61: 190 | S61: =Q61*R61 -> 1520 | T61: 8 | U61: 190 | V61: =T61*U61 -> 1520 | W61: 8 | X61: 190 | Y61: =W61*X61 -> 1520 | Z61: 24 | AA61: 6 | AB61: =Z61*AA61 -> 144 | AC61: =H61+K61+N61+Q61+T61+W61+Z61 -> 48 | AD61: =J61+M61+P61+S61+V61+Y61+AB61 -> 4704 | AF61: 54
A62: 42 | B62: Краевой фестиваль по плаванию "Я-Пловец" III этап | C62: КС | D62: мальчики, девочки 8 лет, девушки, юноши 10-11 лет, девушки, юноши 11-13 лет | E62: 17.09.2026 | F62: 18.09.2026 | G62: г. Краснодар | Q62: 8 | R62: 190 | S62: =Q62*R62 -> 1520 | T62: 8 | U62: 190 | V62: =T62*U62 -> 1520 | W62: 8 | X62: 190 | Y62: =W62*X62 -> 1520 | Z62: 24 | AA62: 6 | AB62: =Z62*AA62 -> 144 | AC62: =H62+K62+N62+Q62+T62+W62+Z62 -> 48 | AD62: =J62+M62+P62+S62+V62+Y62+AB62 -> 4704 | AF62: 54
A63: 43 | B63: Краевой фестиваль по плаванию "Я-Пловец" IV этап | C63: КС | D63: мальчики, девочки 8 лет, девушки, юноши 10-11 лет, девушки, юноши 11-13 лет | E63: 10.11.2026 | F63: 11.11.2026 | G63: г. Краснодар | Q63: 8 | R63: 190 | S63: =Q63*R63 -> 1520 | T63: 8 | U63: 190 | V63: =T63*U63 -> 1520 | W63: 8 | X63: 190 | Y63: =W63*X63 -> 1520 | Z63: 24 | AA63: 6 | AB63: =Z63*AA63 -> 144 | AC63: =H63+K63+N63+Q63+T63+W63+Z63 -> 48 | AD63: =J63+M63+P63+S63+V63+Y63+AB63 -> 4704 | AF63: 54
A64: 44 | B64: Личное первенство Краснодарского края среди ветеранов (рывок мужчины и женщины) | C64: ПК | D64: мужчины, женщины | E64: 46101 | F64: 46102 | G64: ст.Анастасиевская, Славянский район | Q64: 18 | R64: 190 | S64: =Q64*R64 -> 3420 | T64: 18 | U64: 190 | V64: =T64*U64 -> 3420 | W64: 18 | X64: 190 | Y64: =W64*X64 -> 3420 | Z64: 54 | AA64: 6 | AB64: =Z64*AA64 -> 324 | AC64: =H64+K64+N64+Q64+T64+W64+Z64 -> 108 | AD64: =J64+M64+P64+S64+V64+Y64+AB64 -> 10584 | AF64: положение 27.01.2026
A65: 45 | B65: Краевой предновогодний гиревой марафон и полумарафон среди юношей и девушек, мужчин и женщин | C65: КС | D65: мальчики и девочки (10-12 лет), юноши, девушки 14-16 лет, 17-18 лет, юниоры и юниорки 19-23 года, мужчины (19-39 лет, женщины 19-35 лет), ветераны мужчины ( 40 лет и старше), женщины (35 лет и старше) | E65: 46375 | F65: 46376 | G65: ст-ца Анастасиевская (Славянский район) | Q65: 12 | R65: 190 | S65: =Q65*R65 -> 2280 | T65: 12 | U65: 190 | V65: =T65*U65 -> 2280 | W65: 12 | X65: 190 | Y65: =W65*X65 -> 2280 | Z65: 36 | AA65: 6 | AB65: =Z65*AA65 -> 216 | AC65: =H65+K65+N65+Q65+T65+W65+Z65 -> 72 | AD65: =J65+M65+P65+S65+V65+Y65+AB65 -> 7056
A66: 1 | B66: Личное первенство Краснодарского края среди ветеранов по гиревому спорту (классический толчок) (мужчины, женщины) | C66: ПК | D66: мужчины, женщины | E66: 46059 | F66: 46060 | G66: ст.Ленинградская | Q66: 32 | R66: 190 | S66: =Q66*R66 -> 6080 | T66: 32 | U66: 190 | V66: =T66*U66 -> 6080 | W66: 32 | X66: 190 | Y66: =W66*X66 -> 6080 | Z66: 96 | AA66: 6 | AB66: =Z66*AA66 -> 576 | AE66: =H66+K66+N66+Q66+T66+W66+Z66 -> 192 | AF66: =J66+M66+P66+S66+V66+Y66+AB66 -> 18816 | AH66: положение 30.01.2026
A67: 2 | B67: Личное первенство Краснодарского края среди ветеранов по гиревому спорту в толчке ДЦ | C67: ПК | D67: мужчины, женщины | E67: 46052 | F67: 46053 | G67: ст.Анастасиевская, Славянский район | Q67: 32 | R67: 190 | S67: =Q67*R67 -> 6080 | T67: 32 | U67: 190 | V67: =T67*U67 -> 6080 | W67: 32 | X67: 190 | Y67: =W67*X67 -> 6080 | Z67: 96 | AA67: 6 | AB67: =Z67*AA67 -> 576 | AE67: =H67+K67+N67+Q67+T67+W67+Z67 -> 192 | AF67: =J67+M67+P67+S67+V67+Y67+AB67 -> 18816 | AH67: положение 27.01.2026
A68: 1 | B68: Кубок Краснодарского края по волейболу среди мужских и женских команд ветеранов памяти Н.П. Дьяченко | C68: КС | D68: мужчины 40 лет и старше, женщины 35 лет и старше | E68: октябрь | F68: октябрь | G68: п. Ольгинка (Туапсинский район) | H68: 6 | I68: 3400 | J68: =H68*I68 -> 20400 | K68: 6 | L68: 3000 | M68: =K68*L68 -> 18000 | N68: 6 | O68: 2900 | P68: =N68*O68 -> 17400 | Q68: 60 | R68: 190 | S68: =Q68*R68 -> 11400 | T68: 60 | U68: 190 | V68: =T68*U68 -> 11400 | W68: 60 | X68: 190 | Y68: =W68*X68 -> 11400 | Z68: 18 | AA68: 6 | AB68: =Z68*AA68 -> 108 | AE68: =H68+K68+N68+Q68+T68+W68+Z68 -> 216 | AF68: =J68+M68+P68+S68+V68+Y68+AB68 -> 90108
A69: 2 | B69: Краевой фестиваль женского спорта «Красота. Грация. Идеал.» | C69: КС | D69: согласно положению | E69: октябрь | F69: октябрь | G69: г. Геленджик | H69: 1 | I69: 3400 | J69: =H69*I69 -> 3400 | K69: 1 | L69: 3000 | M69: =K69*L69 -> 3000 | N69: 1 | O69: 2900 | P69: =N69*O69 -> 2900 | Q69: 30 | R69: 190 | S69: =Q69*R69 -> 5700 | T69: 30 | U69: 190 | V69: =T69*U69 -> 5700 | W69: 30 | X69: 190 | Y69: =W69*X69 -> 5700 | Z69: 97 | AA69: 6 | AB69: =Z69*AA69 -> 582 | AE69: =H69+K69+N69+Q69+T69+W69+Z69 -> 190 | AF69: =J69+M69+P69+S69+V69+Y69+AB69 -> 26982
A70: ГОСУДАРСТВЕННАЯ ПРОГРАММА КРАСНОДАРСКОГО КРАЯ
B71: "ДОСТУПНАЯ СРЕДА"
A72: 46 | B72: Краевой фестиваль шахмат среди инвалидов по зрению программа | C72: КС | D72: 14 лет и старше | E72: по назначению | F72: согласно положению | G72: согласно положению | Q72: 2 | R72: 190 | S72: =Q72*R72 -> 380 | T72: 2 | U72: 190 | V72: =T72*U72 -> 380 | W72: 2 | X72: 190 | Y72: =W72*X72 -> 380 | Z72: 6 | AA72: 6 | AB72: =Z72*AA72 -> 36 | AC72: =H72+K72+N72+Q72+T72+W72+Z72 -> 12 | AD72: =J72+M72+P72+S72+V72+Y72+AB72 -> 1176
A73: 47 | B73: Краевой фестиваль шашек среди инвалидов по зрению | C73: КС | D73: мужчины, женщины от 18 и старше | E73: по назначению | F73: согласно положению | G73: согласно положению | Q73: 4 | R73: 190 | S73: =Q73*R73 -> 760 | T73: 4 | U73: 190 | V73: =T73*U73 -> 760 | W73: 4 | X73: 190 | Y73: =W73*X73 -> 760 | Z73: 12 | AA73: 6 | AB73: =Z73*AA73 -> 72 | AC73: =H73+K73+N73+Q73+T73+W73+Z73 -> 24 | AD73: =J73+M73+P73+S73+V73+Y73+AB73 -> 2352
A74: 48 | B74: Краевой фестиваль по шоудауну среди инвалидов по зрению | C74: КС | D74: 14 лет и старше | E74: по назначению | F74: согласно положению | G74: согласно положению | Q74: 2 | R74: 190 | S74: =Q74*R74 -> 380 | T74: 2 | U74: 190 | V74: =T74*U74 -> 380 | W74: 2 | X74: 190 | Y74: =W74*X74 -> 380 | Z74: 6 | AA74: 6 | AB74: =Z74*AA74 -> 36 | AC74: =H74+K74+N74+Q74+T74+W74+Z74 -> 12 | AD74: =J74+M74+P74+S74+V74+Y74+AB74 -> 1176
A75: 49 | B75: Краевой спортивный фестиваль среди инвалидов с нарушением слуха | C75: КС | D75: мужчины, женщины от 18 и старше | E75: по назначению | F75: по назначению | G75: по назначению | H75: 1 | I75: 3400 | J75: =H75*I75 -> 3400 | K75: 1 | L75: 3000 | M75: =K75*L75 -> 3000 | N75: 1 | O75: 2900 | P75: =N75*O75 -> 2900 | Q75: 34 | R75: 190 | S75: =Q75*R75 -> 6460 | T75: 34 | U75: 190 | V75: =T75*U75 -> 6460 | W75: 34 | X75: 190 | Y75: =W75*X75 -> 6460 | Z75: 120 | AA75: 6 | AB75: =H75+K75+N75+Q75+T75+W75+Z75 -> 225 | AC75: =H75+K75+N75+Q75+T75+W75+Z75 -> 225 | AD75: =J75+M75+P75+S75+V75+Y75 -> 28680
A76: 50 | B76: Краевой фестиваль среди инвалидов с нарушением слуха № 2 | C76: КС | D76: 12-17 лет | E76: по назначению | F76: по назначению | G76: по назначению | H76: 1 | I76: 3400 | J76: =H76*I76 -> 3400 | K76: 1 | L76: 3000 | M76: =K76*L76 -> 3000 | N76: 1 | O76: 2900 | P76: =N76*O76 -> 2900 | Q76: 15 | R76: 190 | S76: =Q76*R76 -> 2850 | T76: 15 | U76: 190 | V76: =T76*U76 -> 2850 | W76: 15 | X76: 190 | Y76: =W76*X76 -> 2850 | Z76: 186 | AA76: 6 | AB76: 186 | AC76: =H76+K76+N76+Q76+T76+W76+Z76 -> 234 | AD76: =J76+M76+P76+S76+V76+Y76 -> 17850
A77: 51 | B77: Краевые спортивные соревнования для детей-инвалидов с поражением опорно-двигательного аппарата | C77: КС | D77: до 18 лет | E77: по назначению | F77: по назначению | G77: по назначению | Q77: 18 | R77: 190 | S77: =Q77*R77 -> 3420 | T77: 18 | U77: 190 | V77: =T77*U77 -> 3420 | W77: 18 | X77: 190 | Y77: =W77*X77 -> 3420 | Z77: 54 | AA77: 6 | AB77: =Z77*AA77 -> 324 | AC77: =H77+K77+N77+Q77+T77+W77+Z77 -> 108 | AD77: =J77+M77+P77+S77+V77+Y77+AB77 -> 10584
A78: 52 | B78: Краевой спортивный конкурс среди инвалидов по зрению "Современная мозайка" | C78: КС | D78: 18 лет и старше | E78: по назначению | F78: по назначению | G78: по назначению | H78: 1 | I78: 3400 | J78: =H78*I78 -> 3400 | K78: 1 | L78: 3000 | M78: =K78*L78 -> 3000 | N78: 1 | O78: 2900 | P78: =N78*O78 -> 2900 | Q78: 21 | R78: 190 | S78: =Q78*R78 -> 3990 | T78: 21 | U78: 190 | V78: =T78*U78 -> 3990 | W78: 21 | X78: 190 | Y78: =W78*X78 -> 3990 | Z78: 75 | AA78: 6 | AB78: 75 | AC78: =H78+K78+N78+Q78+T78+W78+Z78 -> 141 | AD78: =J78+M78+P78+S78+V78+Y78+AB78 -> 21345
A79: 53 | B79: Краевой фестиваль для детей -инвалидов и их сверстников, не имеющих инвалидности, в возрасте от 12 до 16 лет | C79: КС | D79: от 12-16 лет | E79: по назначению | F79: по назначению | G79: по назначению | H79: 1 | I79: 3400 | J79: =H79*I79 -> 3400 | K79: 1 | L79: 3000 | M79: =K79*L79 -> 3000 | N79: 1 | O79: 2900 | P79: =N79*O79 -> 2900 | Q79: 20 | R79: 190 | S79: =Q79*R79 -> 3800 | T79: 20 | U79: 190 | V79: =T79*U79 -> 3800 | W79: 20 | X79: 190 | Y79: =W79*X79 -> 3800 | Z79: 51 | AA79: 6 | AB79: =H79+K79+N79+Q79+T79+W79+Z79 -> 114 | AC79: =H79+K79+N79+Q79+T79+W79+Z79 -> 114 | AD79: =J79+M79+P79+S79+V79+Y79+AB79 -> 20814
A80: 54 | B80: Спартакиада инвалидов Кубани | C80: КС | D80: 12-60 лет | E80: по назначению | F80: по назначению | G80: по назначению | H80: 8 | I80: 3400 | J80: =H80*I80 -> 27200 | K80: 8 | L80: 3000 | M80: =K80*L80 -> 24000 | N80: 8 | O80: 2900 | P80: =N80*O80 -> 23200 | Q80: 102 | R80: 190 | S80: =Q80*R80 -> 19380 | T80: 102 | U80: 190 | V80: =T80*U80 -> 19380 | W80: 102 | X80: 190 | Y80: =W80*X80 -> 19380 | Z80: 330 | AA80: 6 | AB80: =Z80*AA80 -> 1980 | AC80: =H80+K80+N80+Q80+T80+W80+Z80 -> 660 | AD80: =J80+M80+P80+S80+V80+Y80+AB80 -> 134520
A81: 55 | B81: Первенство Краснодарского края | C81: ПК | D81: 12 лет 13-15 лет 16-18 лет | E81: 46082 | F81: 46082 | G81: по назначению | H81: 1 | I81: 3400 | J81: =H81*I81 -> 3400 | K81: 1 | L81: 3000 | M81: =K81*L81 -> 3000 | N81: 2 | O81: 2900 | P81: =N81*O81 -> 5800 | Q81: 24 | R81: 190 | S81: =Q81*R81 -> 4560 | T81: 24 | U81: 190 | V81: =T81*U81 -> 4560 | W81: 48 | X81: 190 | Y81: =W81*X81 -> 9120 | Z81: 96 | AA81: 6 | AB81: =Z81*AA81 -> 576 | AC81: =H81+K81+N81+Q81+T81+W81+Z81 -> 196 | AD81: =J81+M81+P81+S81++V81+Y81+AB81 -> 31016
A82: 56 | B82: Чемпионат Краснодарского края | C82: ЧК | D82: 19 лет и старше | E82: по назначению | F82: по назначению | G82: по назначению | H82: 1 | I82: 4100 | J82: =H82*I82 -> 4100 | K82: 1 | L82: 3350 | M82: =K82*L82 -> 3350 | N82: 2 | O82: 3000 | P82: =N82*O82 -> 6000 | Q82: 8 | R82: 190 | S82: =Q82*R82 -> 1520 | T82: 8 | U82: 190 | V82: =T82*U82 -> 1520 | W82: 16 | X82: 190 | Y82: =W82*X82 -> 3040 | Z82: 32 | AA82: 6 | AB82: =Z82*AA82 -> 192 | AC82: =H82+K82+N82+Q82+T82+W82+Z82 -> 68 | AD82: =J82+M82+P82+S82++V82+Y82+AB82 -> 19722
A83: 57 | B83: Первенство Краснодарского края | C83: ПК | D83: 12 лет 13-15 лет 16-18 лет 19 лет и старше | E83: по назначению | F83: по назначению | G83: по назначению | H83: 1 | I83: 3400 | J83: =H83*I83 -> 3400 | K83: 1 | L83: 3000 | M83: =K83*L83 -> 3000 | N83: 2 | O83: 2900 | P83: =N83*O83 -> 5800 | Q83: 32 | R83: 190 | S83: =Q83*R83 -> 6080 | T83: 32 | U83: 190 | V83: =T83*U83 -> 6080 | W83: 64 | X83: 190 | Y83: =W83*X83 -> 12160 | Z83: 96 | AA83: 6 | AB83: =Z83*AA83 -> 576 | AC83: =H83+K83+N83+Q83+T83+W83+Z83 -> 228 | AD83: =J83+M83+P83+S83++V83+Y83+AB83 -> 37096
B84: ДИНАМО
A85: 58 | B85: 68-я Спартакиада Краснодарской краевой организации Общества «Динамо» | C85: КС | D85: 21-50 лет | E85: по назначению | F85: по назначению | G85: МО Краснодарского края | H85: 27 | I85: 3400 | J85: =H85*I85 -> 91800 | K85: 27 | L85: 3000 | M85: =K85*L85 -> 81000 | N85: 27 | O85: 2900 | P85: =N85*O85 -> 78300 | Q85: 151 | R85: 190 | S85: =Q85*R85 -> 28690 | T85: 151 | U85: 190 | V85: =T85*U85 -> 28690 | W85: 151 | X85: 190 | Y85: =W85*X85 -> 28690 | AC85: =H85+K85+N85+Q85+T85+W85+Z85 -> 534 | AD85: =J85+M85+P85+S85+V85+Y85+AB85 -> 337170 | AE85: =SUM(AD85:AD88) -> 874770
A86: 59 | B86: Спартакиада Краснодарской краевой организации Общества «Динамо» совместно с Новороссийской городской организацией Общества "Динамо" | C86: КС | D86: 21-50 лет | E86: по назначению | F86: по назначению | G86: МО Краснодарского края | H86: 24 | I86: 3400 | J86: =H86*I86 -> 81600 | K86: 24 | L86: 3000 | M86: =K86*L86 -> 72000 | N86: 24 | O86: 2900 | P86: =N86*O86 -> 69600 | Q86: 92 | R86: 190 | S86: =Q86*R86 -> 17480 | T86: 92 | U86: 190 | V86: =T86*U86 -> 17480 | W86: 92 | X86: 190 | Y86: =W86*X86 -> 17480 | AC86: =H86+K86+N86+Q86+T86+W86+Z86 -> 348 | AD86: =J86+M86+P86+S86+V86+Y86+AB86 -> 275640
A87: 60 | B87: VIII Спартакиада Краснодарской краевой организации Общества «Динамо» среди ветеранов-пенсионеров органов безопасности и правопорядка | C87: КС | D87: 45+ | E87: по назначению | F87: по назначению | G87: МО Краснодарского края | H87: 9 | I87: 3400 | J87: =H87*I87 -> 30600 | K87: 9 | L87: 3000 | M87: =K87*L87 -> 27000 | N87: 9 | O87: 2900 | P87: =N87*O87 -> 26100 | Q87: 40 | R87: 190 | S87: =Q87*R87 -> 7600 | T87: 40 | U87: 190 | V87: =T87*U87 -> 7600 | W87: 40 | X87: 190 | Y87: =W87*X87 -> 7600 | AC87: =H87+K87+N87+Q87+T87+W87+Z87 -> 147 | AD87: =J87+M87+P87+S87+V87+Y87+AB87 -> 106500
A88: 61 | B88: Спартакиада Главного управления по Краснодарскому краю Федеральной службы войск национальной гвардии Российской Федерации и Краснодарской краевой организации Общества "Динамо" в 2026 году | C88: КС | D88: 21-50 лет | E88: февраль | F88: декабрь | G88: МО Краснодарского края | H88: 11 | I88: 3400 | J88: =H88*I88 -> 37400 | K88: 11 | L88: 3000 | M88: =K88*L88 -> 33000 | N88: 11 | O88: 2900 | P88: =N88*O88 -> 31900 | Q88: 90 | R88: 190 | S88: =Q88*R88 -> 17100 | T88: 90 | U88: 190 | V88: =T88*U88 -> 17100 | W88: 90 | X88: 190 | Y88: =W88*X88 -> 17100 | Z88: 310 | AA88: 6 | AB88: =Z88*AA88 -> 1860 | AC88: =H88+K88+N88+Q88+T88+W88+Z88 -> 613 | AD88: =J88+M88+P88+S88+V88+Y88+AB88 -> 155460
A89: СПОРТИВНЫЕ СОРЕВНОВАНИЯ ПО ВИДАМ СПОРТА
A90: АРМРЕСТЛИНГ
A91: 62 | B91: Первенство Краснодарского края | C91: ПК | D91: юноши, девушки (14- 15 лет), юниоры, юниорки (16-18 лет), юниоры, юниорки (19-21 год), мужчины, женщины | E91: 46332 | F91: 46334 | G91: Красноармейский район, ст-ца Старонижестеблиевская | H91: 1 | I91: 3400 | J91: =H91*I91 -> 3400 | K91: 1 | L91: 3000 | M91: =K91*L91 -> 3000 | N91: 1 | O91: 2900 | P91: =N91*O91 -> 2900 | Q91: 44 | R91: 190 | S91: =Q91*R91 -> 8360 | T91: 44 | U91: 190 | V91: =T91*U91 -> 8360 | W91: 44 | X91: 190 | Y91: =W91*X91 -> 8360 | Z91: 145 | AA91: 6 | AB91: =Z91*AA91 -> 870 | AC91: =H91+K91+N91+Q91+T91+W91+Z91 -> 280 | AD91: =J91+M91+P91+S91++V91+Y91+AB91 -> 35250
A92: 63 | B92: Чемпионат Краснодарского края | C92: ЧК | D92: мужчины, женщины | E92: 46346 | F92: 46348 | G92: Красноармейский район, ст-ца Старонижестеблиевская | H92: 1 | I92: 4100 | J92: =H92*I92 -> 4100 | K92: 1 | L92: 3350 | M92: =K92*L92 -> 3350 | N92: 1 | O92: 3000 | P92: =N92*O92 -> 3000 | Q92: 19 | R92: 190 | S92: =Q92*R92 -> 3610 | T92: 19 | U92: 190 | V92: =T92*U92 -> 3610 | W92: 19 | X92: 190 | Y92: =W92*X92 -> 3610 | Z92: 70 | AA92: 6 | AB92: =Z92*AA92 -> 420 | AC92: =H92+K92+N92+Q92+T92+W92+Z92 -> 130 | AD92: =J92+M92+P92+S92++V92+Y92+AB92 -> 21700
B93: АЛЬПИНИЗМ
A94: 3 | B94: Чемпионат Краснодарского края по альпинизму | C94: ЧК | D94: мужчины и женщины | E94: 46284 | F94: 46285 | G94: г. Сочи, пгт. Красная поляна | Q94: 2 | R94: 190 | S94: =Q94*R94 -> 380 | T94: 2 | U94: 190 | V94: =T94*U94 -> 380 | W94: 2 | X94: 190 | Y94: =W94*X94 -> 380 | Z94: 6 | AA94: 6 | AB94: =Z94*AA94 -> 36 | AE94: =H94+K94+N94+Q94+T94+W94+Z94 -> 12 | AF94: =J94+M94+P94+S94+V94+Y94+AB94 -> 1176
A95: 4 | B95: Чемпионат Краснодарского края по альпинизму | C95: ЧК | D95: мужчины и женщины | E95: 46291 | F95: 46300 | G95: г. Сочи, пгт. Красная поляна | Q95: 2 | R95: 190 | S95: =Q95*R95 -> 380 | T95: 2 | U95: 190 | V95: =T95*U95 -> 380 | W95: 2 | X95: 190 | Y95: =W95*X95 -> 380 | Z95: 6 | AA95: 6 | AB95: =Z95*AA95 -> 36 | AE95: =H95+K95+N95+Q95+T95+W95+Z95 -> 12 | AF95: =J95+M95+P95+S95+V95+Y95+AB95 -> 1176
B96: АВИАМОДЕЛЬНЫЙ СПОРТ
A97: 64 | B97: Кубок Краснодарского края в классе моделей F2B-моделей -пилотажные модели | C97: КК | D97: юниоры, юниорки (14 лет и старше) | E97: 46147 | F97: 46180 | G97: с. Красногвардейское, Республика Адыгея | H97: 1 | I97: 3300 | J97: =H97*I97 -> 3300 | K97: 1 | L97: 2850 | M97: =K97*L97 -> 2850 | N97: 1 | O97: 2750 | P97: =N97*O97 -> 2750 | Q97: 2 | R97: 190 | S97: =Q97*R97 -> 380 | T97: 2 | U97: 190 | V97: =T97*U97 -> 380 | W97: 2 | X97: 190 | Y97: =W97*X97 -> 380 | Z97: 6 | AA97: 6 | AB97: =Z97*AA97 -> 36 | AC97: =Q97+T97+W97+Z97 -> 12 | AD97: =S97+V97+Y97+AB97 -> 1176 | AF97: положение 29.12.2026
A98: 65 | B98: Чемпионат Краснодарского края по авиамодельному спорту в классе моделей F2D-модели "воздушного боя" | C98: ЧК | D98: юниоры, юниорки (14 лет и старше) | E98: 46136 | F98: 46139 | G98: Красносельское городское поселение, Гулькевичского района | H98: 1 | I98: 3300 | J98: =H98*I98 -> 3300 | K98: 1 | L98: 2850 | M98: =K98*L98 -> 2850 | N98: 1 | O98: 2750 | P98: =N98*O98 -> 2750 | Q98: 4 | R98: 190 | S98: =Q98*R98 -> 760 | T98: 4 | U98: 190 | V98: =T98*U98 -> 760 | W98: 4 | X98: 190 | Y98: =W98*X98 -> 760 | Z98: 12 | AA98: 6 | AB98: =Z98*AA98 -> 72 | AC98: =Q98+T98+W98+Z98 -> 24 | AD98: =S98+V98+Y98+AB98 -> 2352 | AF98: положение 29.12.2026
A99: 66 | B99: Первенство Краснодарского края по авиамодельному спорту в классе моделей F2D-модели "воздушного боя" | C99: ПК | D99: юниоры, юниорки (10-18 лет) | E99: 46135 | F99: 46137 | G99: Красносельское городское поселение, Гулькевичского района | H99: 1 | I99: 3300 | J99: =H99*I99 -> 3300 | K99: 1 | L99: 2850 | M99: =K99*L99 -> 2850 | N99: 1 | O99: 2750 | P99: =N99*O99 -> 2750 | Q99: 4 | R99: 190 | S99: =Q99*R99 -> 760 | T99: 4 | U99: 190 | V99: =T99*U99 -> 760 | W99: 4 | X99: 190 | Y99: =W99*X99 -> 760 | Z99: 12 | AA99: 6 | AB99: =Z99*AA99 -> 72 | AC99: =Q99+T99+W99+Z99 -> 24 | AD99: =S99+V99+Y99+AB99 -> 2352 | AF99: положение 29.12.2026
B100: АКРОБАТИЧЕСКИЙ РОК-Н-РОЛЛ
A101: 67 | B101: Краевые соревнования, посвященные Международному женскому дню | C101: КС | D101: мужчины и женщины, юниоры и юниорки до 18 лет, юноши и девушки до 16 лет, до 15 лет, мальчики и девочки до 12 лет | E101: 46087 | F101: 46088 | G101: г. Краснодар | Q101: 105 | R101: 190 | S101: =Q101*R101 -> 19950 | T101: 88 | U101: 190 | V101: =T101*U101 -> 16720 | W101: 88 | X101: 190 | Y101: =W101*X101 -> 16720 | Z101: 281 | AA101: 6 | AB101: =Z101*AA101 -> 1686 | AC101: =H101+K101+N101+Q101+T101+W101+Z101 -> 562 | AD101: =J101+M101+P101+S101+V101+Y101+AB101 -> 55076 | AF101: 281
...

Sheet Приложение 2
AC1: УТВЕРЖДАЮ
AC2: Руководитель государственного бюджетного учреждения Краснодарского края "Центр развития спорта"
AC3: _______________ В.П. Колпаков
AC4: "____" __________ 20__ г.
H5: Приложение 2
G6: УТВЕРЖДАЮ Руководитель ГБУ КК "Центр развития спорта" ________________ В.П. Колпаков "_____" ____________ 20____ г. согласно приказу
A11: Календарный план официальных физкультурных и спортивных мероприятий государственного бюджетного учреждения Краснодарского края "Центр развития спорта" на 2026 год в части обеспечения наградной атрибутикой за счет субсидий на финансовое обеспечение выполнения государственного задания на оказание государственных услуг (выполнение работ) прошлых лет.
A14: № п/п | B14: Ответственный за проведение мероприятия | C14: Вид спорта | D14: Наименование мероприятия | E14: Вид соревнований | F14: Возраст | G14: Дата проведения (начало мероприятия) | H14: Дата проведения (конец мероприятия) | I14: Место проведения | J14: Количество кубков | S14: Количество медалей | AB14: Грамоты | AE14: Услуги по изготовлению и поставке | AG14: Всего по виду спорта
J15: 1 место Кол-во, шт. | K15: Стоимость 1 шт. | L15: Итого | M15: 2 место Кол-во, шт. | N15: Стоимость 1 шт. | O15: Итого | P15: 3 место Кол-во, шт. | Q15: Стоимость 1 шт. | R15: Итого | S15: 1 место Кол-во, шт. | T15: Стоимость 1 шт. | U15: Итого | V15: 2 место Кол-во, шт. | W15: Стоимость 1 шт. | X15: Итого | Y15: 3 место Количество, шт. | Z15: Стоимость 1 | AA15: Итого | AB15: Кол-во, шт. | AC15: Стоимость 1 шт. | AD15: Итого | AE15: Кол-во ед наградного материала | AF15: Сумма
D16: ФИЗКУЛЬТУРНЫЕ МЕРОПРИЯТИЯ СРЕДИ РАЗЛИЧНЫХ ВОЗРАСТНЫХ ГРУПП НАСЕЛЕНИЯ И ИНВАЛИДОВ
D17: ФИЗКУЛЬТУРНЫЕ МЕРОПРИЯТИЯ
D20: ГОТОВ К ТРУДУ И ОБОРОНЕ
D70: КОНЬКОБЕЖНЫЙ СПОРТ
D72: КИОКУШИН
D75: КИКБОКСИНГ
A78: КОМПЬЮТЕРНЫЙ СПОРТ
D81: КЕРЛИНГ
D83: ЛАПТА
D86: ЛЕГКАЯ АТЛЕТИКА
D93: НАСТОЛЬНЫЙ ТЕННИС
D96: ПРЫЖКИ НА БАТУТЕ
AH98: положение 18.12.2025
AH99: положение 18.12.2025
D101: ПРЫЖКИ В ВОДУ
D103: ПОДВОДНЫЙ СПОРТ
D106: ПУЛЕВАЯ СТРЕЛЬБА
D109: ПОЛИАТЛОН
D110: ПЛАВАНИЕ
A115: РЕГБИ
D117: РУКОПАШНЫЙ БОЙ
A119: РАДИОСПОРТ
D126: СНОУБОРД
D127: СЁРФИНГ
D130: СПОРТИВНОЕ ПРОГРАММИРОВАНИЕ
D132: СПОРТИВНАЯ АКРОБАТИКА
D135: СПОРТИВНЫЙ ТУРИЗМ
D144: СИНХРОННОЕ ПЛАВАНИЕ
D147: СПОРТИВНАЯ ГИМНАСТИКА
A155: САМБО
D157: СТЕНДОВАЯ СТРЕЛЬБА
A160: СПОРТ ГЛУХИХ
D165: СПОРТИВНАЯ БОРЬБА (ГРЕКО-РИМСКАЯ БОРЬБА)
D167: СПОРТИВНАЯ БОРЬБА (ВОЛЬНАЯ БОРЬБА)
D181: ТАНЦЕВАЛЬНЫЙ СПОРТ
D188: ТАВРЕЛИ
D190: ТХЭКВОНДО (ВТФ)
AH191: положение 17.12.2025
AH193: положение 24.12.2025
AH194: положение 24.12.2025
D195: ТРИАТЛОН
D199: ТЯЖЕЛАЯ АТЛЕТИКА
D205: ФИДЖИТАЛ СПОРТ
D207: ФИГУРНОЕ КАТАНИЕ НА КОНЬКАХ
D213: ФЕХТОВАНИЕ
D215: ФУТБОЛ
D217: ХОККЕЙ НА ТРАВЕ
D222: ХОККЕЙ
A232: ХУДОЖЕСТВЕННАЯ ГИМНАСТИКА
D237: ШАХМАТЫ
D242: ШАШКИ
D244: КОМПЛЕКСНОЕ МЕРОПРИЯТИЕ
A245: 146 | D245: XIII летняя Спартакиада учащихся (юношеская) Кубани 2026 года (по видам спорта) | E245: КС | F245: согласно положению | G245: по назначению | H245: по назначению | I245: по назначению | J245: 3 | K245: 3400 | L245: =J245*K245 -> 10200 | M245: 3 | N245: 3000 | O245: =M245*N245 -> 9000 | P245: 3 | Q245: 2900 | R245: =P245*Q245 -> 8700 | S245: 57 | T245: 190 | U245: =S245*T245 -> 10830 | V245: 57 | W245: 190 | X245: 3230 | Y245: 101 | Z245: 190 | AA245: 6460 | AB245: 237 | AC245: 6 | AD245: 444 | AE245: =R245+U245+X245 -> 22760 | AF245: =L245+O245+R245+U245+X245+AA245+AD245 -> 48864
D246: ИТОГО | AF246: 3124430
A247: Заместитель руководителя | I247: Р.Ю.Александров
A248: Начальник отдела по взаимодействию с физкультурно-спортивными организациями
I249: Э.С.Гильгенберг

Sheet Приложение 3
AC1: УТВЕРЖДАЮ
AC2: Руководитель государственного бюджетного учреждения Краснодарского края "Центр развития спорта"
AC3: _______________ В.П. Колпаков
AC4: "____" __________ 20__ г.
H5: Приложение 3 | AC5: УТВЕРЖДАЮ
G6: УТВЕРЖДАЮ Руководитель ГБУ КК "Центр развития спорта" ________________ В.П. Колпаков "_____" ____________ 20____ г. согласно приказу № _____ от "____" ______ 20____ г. | AC6: руководитель ГБУ КК "Центр развития спорта"
AC7: _________________ В.П. Колпаков
A11: Календарный план официальных физкультурных и спортивных мероприятий государственного бюджетного учреждения Краснодарского края "Центр развития спорта" на 2026 год в части обеспечения наградной атрибутикой за счет субсидий на финансовое обеспечение выполнения государственного задания на оказание государственных услуг (выполнение работ), дополнительно.
A14: № п/п | B14: Ответственный за проведение мероприятия | C14: Вид спорта | D14: Наименование мероприятия | E14: Вид соревнований | F14: Возраст | G14: Дата проведения (начало мероприятия) | H14: Дата проведения (конец мероприятия) | I14: Место проведения | J14: Количество кубков | S14: Количество медалей | AB14: Грамоты | AE14: Услуги по изготовлению и поставке | AG14: Всего по виду спорта
J15: 1 место Кол-во, шт. | K15: Стоимость 1 шт. | L15: Итого | M15: 2 место Кол-во, шт. | N15: Стоимость 1 шт. | O15: Итого | P15: 3 место Кол-во, шт. | Q15: Стоимость 1 шт. | R15: Итого | S15: 1 место Кол-во, шт. | T15: Стоимость 1 шт. | U15: Итого | V15: 2 место Кол-во, шт. | W15: Стоимость 1 шт. | X15: Итого | Y15: 3 место Количество, шт. | Z15: Стоимость 1 | AA15: Итого | AB15: Кол-во, шт. | AC15: Стоимость 1 шт. | AD15: Итого | AE15: Кол-во ед наградного материала | AF15: Сумма
D16: ФИЗКУЛЬТУРНЫЕ МЕРОПРИЯТИЯ СРЕДИ РАЗЛИЧНЫХ ВОЗРАСТНЫХ ГРУПП НАСЕЛЕНИЯ И ИНВАЛИДОВ
D17: ФИЗКУЛЬТУРНЫЕ МЕРОПРИЯТИЯ
A20: АЛЬПИНИЗМ
D23: БОУЛИНГ
A26: ГАНДБОЛ
D29: КИОКУШИН
A30: КИКБОКСИНГ
D77: УШУ
D79: ФЕХТОВАНИЕ
D82: ИТОГО | AF82: 1766622
A83: Заместитель руководителя | I83: Р.Ю.Александров
A84: Начальник отдела по взаимодействию с физкультурно-спортивными организациями
I85: Э.С.Гильгенберг

Sheet ДИНАМО 
A3: Краснодарская краевая организация Общества «Динамо»
D5: № п/п | E5: Учреждение/ Федерация | F5: Вид спорта | G5: Наименование мероприятия (полное) с учетом вида спорта | H5: Возраст спортсменов в соответствии с ЕВСК | I5: Дата проведения (начало мероприятия) | J5: Дата проведения (конец мероприятия) | K5: Место проведения | L5: Кол-во кубков (командный зачет) | O5: Кол-во медалей | R5: Кол-во грамот | S5: Количество кубков | AB5: Количество медалей | AK5: Грамоты | AN5: Услуги по изготовлению и поставке
L6: 1 | M6: 2 | N6: 3 | O6: 1 | P6: 2 | Q6: 3 | S6: 1 место Кол-во, шт. | T6: Стоимость 1 шт. | U6: Итого | V6: 2 место Кол-во, шт. | W6: Стоимость 1 шт. | X6: Итого | Y6: 3 место Кол-во, шт. | Z6: Стоимость 1 шт. | AA6: Итого | AB6: 1 место Кол-во, шт. | AC6: Стоимость 1 шт. | AD6: Итого | AE6: 2 место Кол-во, шт. | AF6: Стоимость 1 шт. | AG6: Итого | AH6: 3 место Количество, шт. | AI6: Стоимость 1 | AJ6: Итого | AK6: Кол-во, шт. | AL6: Стоимость 1 шт. | AM6: Итого | AN6: Кол-во ед наградного материала | AO6: Сумма
D7: 1 | E7: Краснодарская краевая организация Общества «Динамо» | F7: Стрельба из боевого ручного стрелкового оружия | G7: 68-я Спартакиада Краснодарской краевой организации Общества «Динамо» | H7: 21-50 лет | I7: по назначению | J7: по назначению | K7: г.Краснодар | L7: 3 | M7: 3 | N7: 3 | O7: 13 | P7: 13 | Q7: 13 | R7: - | S7: 3 | T7: 3400 | U7: =S7*T7 -> 10200 | V7: 3 | W7: 3000 | X7: =V7*W7 -> 9000 | Y7: 3 | Z7: 2900 | AA7: =Y7*Z7 -> 8700 | AB7: 13 | AC7: 190 | AD7: =AB7*AC7 -> 2470 | AE7: 13 | AF7: 190 | AG7: =AE7*AF7 -> 2470 | AH7: 13 | AI7: 190 | AJ7: =AH7*AI7 -> 2470 | AN7: =S7+V7+Y7+AB7+AE7+AH7+AK7 -> 48 | AO7: =U7+X7+AA7+AD7+AG7+AJ7+AM7 -> 35310
F8: Плавание | G8: 68-я Спартакиада Краснодарской краевой организации Общества «Динамо» | H8: 21- 50 лет | I8: по назначению | J8: по назначению | K8: г.Краснодар | L8: 3 | M8: 3 | N8: 3 | O8: 12 | P8: 12 | Q8: 12 | R8: - | S8: 3 | T8: 3400 | U8: =S8*T8 -> 10200 | V8: 3 | W8: 3000 | X8: =V8*W8 -> 9000 | Y8: 3 | Z8: 2900 | AA8: =Y8*Z8 -> 8700 | AB8: 12 | AC8: 190 | AD8: =AB8*AC8 -> 2280 | AE8: 12 | AF8: 190 | AG8: =AE8*AF8 -> 2280 | AH8: 12 | AI8: 190 | AJ8: =AH8*AI8 -> 2280 | AN8: =S8+V8+Y8+AB8+AE8+AH8+AK8 -> 45 | AO8: =U8+X8+AA8+AD8+AG8+AJ8+AM8 -> 34740
F9: Мини-футбол | G9: 68-я Спартакиада Краснодарской краевой организации Общества «Динамо» | H9: 21-50 лет | I9: по назначению | J9: по назначению | K9: г.Краснодар | L9: 3 | M9: 3 | N9: 3 | O9: 36 | P9: 36 | Q9: 36 | R9: - | S9: 3 | T9: 3400 | U9: =S9*T9 -> 10200 | V9: 3 | W9: 3000 | X9: =V9*W9 -> 9000 | Y9: 3 | Z9: 2900 | AA9: =Y9*Z9 -> 8700 | AB9: 36 | AC9: 190 | AD9: =AB9*AC9 -> 6840 | AE9: 36 | AF9: 190 | AG9: =AE9*AF9 -> 6840 | AH9: 36 | AI9: 190 | AJ9: =AH9*AI9 -> 6840 | AN9: =S9+V9+Y9+AB9+AE9+AH9+AK9 -> 117 | AO9: =U9+X9+AA9+AD9+AG9+AJ9+AM9 -> 48420
F10: Легкоатлетическая эстафета 4х400 метров | G10: 68-я Спартакиада Краснодарской краевой организации Общества «Динамо» | H10: 21-50 лет | I10: по назначению | J10: по назначению | K10: г.Краснодар | L10: 3 | M10: 3 | N10: 3 | O10: 12 | P10: 12 | Q10: 12 | R10: - | S10: 3 | T10: 3400 | U10: =S10*T10 -> 10200 | V10: 3 | W10: 3000 | X10: =V10*W10 -> 9000 | Y10: 3 | Z10: 2900 | AA10: =Y10*Z10 -> 8700 | AB10: 12 | AC10: 190 | AD10: =AB10*AC10 -> 2280 | AE10: 12 | AF10: 190 | AG10: =AE10*AF10 -> 2280 | AH10: 12 | AI10: 190 | AJ10: =AH10*AI10 -> 2280 | AN10: =S10+V10+Y10+AB10+AE10+AH10+AK10 -> 45 | AO10: =U10+X10+AA10+AD10+AG10+AJ10+AM10 -> 34740
F11: Легкая атлетика кросс | G11: 68-я Спартакиада Краснодарской краевой организации Общества «Динамо» | H11: 21-50 лет | I11: по назначению | J11: по назначению | K11: г.Краснодар | L11: 3 | M11: 3 | N11: 3 | O11: 13 | P11: 13 | Q11: 13 | R11: - | S11: 3 | T11: 3400 | U11: =S11*T11 -> 10200 | V11: 3 | W11: 3000 | X11: =V11*W11 -> 9000 | Y11: 3 | Z11: 2900 | AA11: =Y11*Z11 -> 8700 | AB11: 13 | AC11: 190 | AD11: =AB11*AC11 -> 2470 | AE11: 13 | AF11: 190 | AG11: =AE11*AF11 -> 2470 | AH11: 13 | AI11: 190 | AJ11: =AH11*AI11 -> 2470 | AN11: =S11+V11+Y11+AB11+AE11+AH11+AK11 -> 48 | AO11: =U11+X11+AA11+AD11+AG11+AJ11+AM11 -> 35310
F12: Волейбол | G12: 68-я Спартакиада Краснодарской краевой организации Общества «Динамо» | H12: 21-50 лет | I12: по назначению | J12: по назначению | K12: г.Краснодар | L12: 3 | M12: 3 | N12: 3 | O12: 36 | P12: 36 | Q12: 36 | R12: - | S12: 3 | T12: 3400 | U12: =S12*T12 -> 10200 | V12: 3 | W12: 3000 | X12: =V12*W12 -> 9000 | Y12: 3 | Z12: 2900 | AA12: =Y12*Z12 -> 8700 | AB12: 36 | AC12: 190 | AD12: =AB12*AC12 -> 6840 | AE12: 36 | AF12: 190 | AG12: =AE12*AF12 -> 6840 | AH12: 36 | AI12: 190 | AJ12: =AH12*AI12 -> 6840 | AN12: =S12+V12+Y12+AB12+AE12+AH12+AK12 -> 117 | AO12: =U12+X12+AA12+AD12+AG12+AJ12+AM12 -> 48420
F13: Служебный биатлон | G13: 68-я Спартакиада Краснодарской краевой организации Общества «Динамо» | H13: 21-50 лет | I13: по назначению | J13: по назначению | K13: г.Краснодар | L13: 3 | M13: 3 | N13: 3 | O13: 16 | P13: 16 | Q13: 16 | R13: - | S13: 3 | T13: 3400 | U13: =S13*T13 -> 10200 | V13: 3 | W13: 3000 | X13: =V13*W13 -> 9000 | Y13: 3 | Z13: 2900 | AA13: =Y13*Z13 -> 8700 | AB13: 16 | AC13: 190 | AD13: =AB13*AC13 -> 3040 | AE13: 16 | AF13: 190 | AG13: =AE13*AF13 -> 3040 | AH13: 16 | AI13: 190 | AJ13: =AH13*AI13 -> 3040 | AN13: =S13+V13+Y13+AB13+AE13+AH13+AK13 -> 57 | AO13: =U13+X13+AA13+AD13+AG13+AJ13+AM13 -> 37020
F14: Полоса препятствий | G14: 68-я Спартакиада Краснодарской краевой организации Общества «Динамо» | H14: 21-50 лет | I14: по назначению | J14: по назначению | K14: г.Краснодар | L14: 3 | M14: 3 | N14: 3 | O14: 13 | P14: 13 | Q14: 13 | R14: - | S14: 3 | T14: 3400 | U14: =S14*T14 -> 10200 | V14: 3 | W14: 3000 | X14: =V14*W14 -> 9000 | Y14: 3 | Z14: 2900 | AA14: =Y14*Z14 -> 8700 | AB14: 13 | AC14: 190 | AD14: =AB14*AC14 -> 2470 | AE14: 13 | AF14: 190 | AG14: =AE14*AF14 -> 2470 | AH14: 13 | AI14: 190 | AJ14: =AH14*AI14 -> 2470 | AN14: =S14+V14+Y14+AB14+AE14+AH14+AK14 -> 48 | AO14: =U14+X14+AA14+AD14+AG14+AJ14+AM14 -> 35310
F15: Общекомандное первенство | G15: 68-я Спартакиада Краснодарской краевой организации Общества «Динамо» | H15: 21-50 лет | I15: по назначению | J15: по назначению | K15: г.Краснодар | L15: 3 | M15: 3 | N15: 3 | O15: 13 | P15: 13 | Q15: 13 | R15: - | S15: 3 | T15: 3400 | U15: =S15*T15 -> 10200 | V15: 3 | W15: 3000 | X15: =V15*W15 -> 9000 | Y15: 3 | Z15: 2900 | AA15: =Y15*Z15 -> 8700
K16: ИТОГО | S16: 27 | V16: 27 | Y16: 27 | AB16: =SUM(AB7:AB14) -> 151 | AE16: =SUM(AE7:AE14) -> 151 | AH16: =SUM(AH7:AH14) -> 151
F17: Стрельба из боевого ручного стрелкового оружия | G17: Спартакиада Краснодарской краевой организации Общества «Динамо» совместно с Новороссийской городской организацией Общества "Динамо" | H17: 21-50 лет | I17: по назначению | J17: по назначению | K17: г.Новороссийск | L17: 2 | M17: 2 | N17: 2 | O17: 7 | P17: 7 | Q17: 7 | R17: - | S17: 2 | T17: 3400 | U17: =S17*T17 -> 6800 | V17: 2 | W17: 3000 | X17: =V17*W17 -> 6000 | Y17: 2 | Z17: 2900 | AA17: =Y17*Z17 -> 5800 | AB17: 7 | AC17: 190 | AD17: =AB17*AC17 -> 1330 | AE17: 7 | AF17: 190 | AG17: =AE17*AF17 -> 1330 | AH17: 7 | AI17: 190 | AJ17: =AH17*AI17 -> 1330 | AN17: =S17+V17+Y17+AB17+AE17+AH17+AK17 -> 27 | AO17: =U17+X17+AA17+AD17+AG17+AJ17+AM17 -> 22590
F18: Плавание | G18: Спартакиада Краснодарской краевой организации Общества «Динамо» совместно с Новороссийской городской организацией Общества "Динамо" | H18: 21-50 лет | I18: по назначению | J18: по назначению | K18: г.Новороссийск | L18: 2 | M18: 2 | N18: 2 | O18: 9 | P18: 9 | Q18: 9 | R18: - | S18: 2 | T18: 3400 | U18: =S18*T18 -> 6800 | V18: 2 | W18: 3000 | X18: =V18*W18 -> 6000 | Y18: 2 | Z18: 2900 | AA18: =Y18*Z18 -> 5800 | AB18: 9 | AC18: 190 | AD18: =AB18*AC18 -> 1710 | AE18: 9 | AF18: 190 | AG18: =AE18*AF18 -> 1710 | AH18: 9 | AI18: 190 | AJ18: =AH18*AI18 -> 1710 | AN18: =S18+V18+Y18+AB18+AE18+AH18+AK18 -> 33 | AO18: =U18+X18+AA18+AD18+AG18+AJ18+AM18 -> 23730
F19: Армспорт | G19: Спартакиада Краснодарской краевой организации Общества «Динамо» совместно с Новороссийской городской организацией Общества "Динамо" | H19: 21-50 лет | I19: по назначению | J19: по назначению | K19: г.Новороссийск | L19: 2 | M19: 2 | N19: 2 | O19: 9 | P19: 9 | Q19: 9 | R19: - | S19: 2 | T19: 3400 | U19: =S19*T19 -> 6800 | V19: 2 | W19: 3000 | X19: =V19*W19 -> 6000 | Y19: 2 | Z19: 2900 | AA19: =Y19*Z19 -> 5800 | AB19: 9 | AC19: 190 | AD19: =AB19*AC19 -> 1710 | AE19: 9 | AF19: 190 | AG19: =AE19*AF19 -> 1710 | AH19: 9 | AI19: 190 | AJ19: =AH19*AI19 -> 1710 | AN19: =S19+V19+Y19+AB19+AE19+AH19+AK19 -> 33 | AO19: =U19+X19+AA19+AD19+AG19+AJ19+AM19 -> 23730
F20: Гиревой спорт | G20: Спартакиада Краснодарской краевой организации Общества «Динамо» совместно с Новороссийской городской организацией Общества "Динамо" | H20: 21-50 лет | I20: по назначению | J20: по назначению | K20: г.Новороссийск | L20: 2 | M20: 2 | N20: 2 | O20: 9 | P20: 9 | Q20: 9 | R20: - | S20: 2 | T20: 3400 | U20: =S20*T20 -> 6800 | V20: 2 | W20: 3000 | X20: =V20*W20 -> 6000 | Y20: 2 | Z20: 2900 | AA20: =Y20*Z20 -> 5800 | AB20: 9 | AC20: 190 | AD20: =AB20*AC20 -> 1710 | AE20: 9 | AF20: 190 | AG20: =AE20*AF20 -> 1710 | AH20: 9 | AI20: 190 | AJ20: =AH20*AI20 -> 1710 | AN20: =S20+V20+Y20+AB20+AE20+AH20+AK20 -> 33 | AO20: =U20+X20+AA20+AD20+AG20+AJ20+AM20 -> 23730
F21: Легкоатлетическая эстафета 4х400 метров, бег 1500 и 3000 метров | G21: Спартакиада Краснодарской краевой организации Общества «Динамо» совместно с Новороссийской городской организацией Общества "Динамо" | H21: 21-50 лет | I21: по назначению | J21: по назначению | K21: г.Новороссийск | L21: 2 | M21: 2 | N21: 2 | O21: 10 | P21: 10 | Q21: 10 | R21: - | S21: 2 | T21: 3400 | U21: =S21*T21 -> 6800 | V21: 2 | W21: 3000 | X21: =V21*W21 -> 6000 | Y21: 2 | Z21: 2900 | AA21: =Y21*Z21 -> 5800 | AB21: 10 | AC21: 190 | AD21: =AB21*AC21 -> 1900 | AE21: 10 | AF21: 190 | AG21: =AE21*AF21 -> 1900 | AH21: 10 | AI21: 190 | AJ21: =AH21*AI21 -> 1900 | AN21: =S21+V21+Y21+AB21+AE21+AH21+AK21 -> 36 | AO21: =U21+X21+AA21+AD21+AG21+AJ21+AM21 -> 24300
F22: Мини-футбол | G22: Спартакиада Краснодарской краевой организации Общества «Динамо» совместно с Новороссийской городской организацией Общества "Динамо" | H22: 21-50 лет | I22: по назначению | J22: по назначению | K22: г.Новороссийск | L22: 2 | M22: 2 | N22: 2 | O22: 20 | P22: 20 | Q22: 20 | R22: - | S22: 2 | T22: 3400 | U22: =S22*T22 -> 6800 | V22: 2 | W22: 3000 | X22: =V22*W22 -> 6000 | Y22: 2 | Z22: 2900 | AA22: =Y22*Z22 -> 5800 | AB22: 20 | AC22: 190 | AD22: =AB22*AC22 -> 3800 | AE22: 20 | AF22: 190 | AG22: =AE22*AF22 -> 3800 | AH22: 20 | AI22: 190 | AJ22: =AH22*AI22 -> 3800 | AN22: =S22+V22+Y22+AB22+AE22+AH22+AK22 -> 66 | AO22: =U22+X22+AA22+AD22+AG22+AJ22+AM22 -> 30000
F23: Пляжный волейбол | G23: Спартакиада Краснодарской краевой организации Общества «Динамо» совместно с Новороссийской городской организацией Общества "Динамо" | H23: 21-50 лет | I23: по назначению | J23: по назначению | K23: г.Новороссийск | L23: 2 | M23: 2 | N23: 2 | O23: 4 | P23: 4 | Q23: 4 | R23: - | S23: 2 | T23: 3400 | U23: =S23*T23 -> 6800 | V23: 2 | W23: 3000 | X23: =V23*W23 -> 6000 | Y23: 2 | Z23: 2900 | AA23: =Y23*Z23 -> 5800 | AB23: 4 | AC23: 190 | AD23: =AB23*AC23 -> 760 | AE23: 4 | AF23: 190 | AG23: =AE23*AF23 -> 760 | AH23: 4 | AI23: 190 | AJ23: =AH23*AI23 -> 760 | AN23: =S23+V23+Y23+AB23+AE23+AH23+AK23 -> 18 | AO23: =U23+X23+AA23+AD23+AG23+AJ23+AM23 -> 20880
F24: Шахматы | G24: Спартакиада Краснодарской краевой организации Общества «Динамо» совместно с Новороссийской городской организацией Общества "Динамо" | H24: 21-50 лет | I24: по назначению | J24: по назначению | K24: г.Новороссийск | L24: 2 | M24: 2 | N24: 2 | O24: 4 | P24: 4 | Q24: 4 | R24: - | S24: 2 | T24: 3400 | U24: =S24*T24 -> 6800 | V24: 2 | W24: 3000 | X24: =V24*W24 -> 6000 | Y24: 2 | Z24: 2900 | AA24: =Y24*Z24 -> 5800 | AB24: 4 | AC24: 190 | AD24: =AB24*AC24 -> 760 | AE24: 4 | AF24: 190 | AG24: =AE24*AF24 -> 760 | AH24: 4 | AI24: 190 | AJ24: =AH24*AI24 -> 760 | AN24: =S24+V24+Y24+AB24+AE24+AH24+AK24 -> 18 | AO24: =U24+X24+AA24+AD24+AG24+AJ24+AM24 -> 20880
F25: Настольный теннис | G25: Спартакиада Краснодарской краевой организации Общества «Динамо» совместно с Новороссийской городской организацией Общества "Динамо" | H25: 21-50 лет | I25: по назначению | J25: по назначению | K25: г.Новороссийск | L25: 2 | M25: 2 | N25: 2 | O25: 5 | P25: 5 | Q25: 5 | R25: - | S25: 2 | T25: 3400 | U25: =S25*T25 -> 6800 | V25: 2 | W25: 3000 | X25: =V25*W25 -> 6000 | Y25: 2 | Z25: 2900 | AA25: =Y25*Z25 -> 5800 | AB25: 5 | AC25: 190 | AD25: =AB25*AC25 -> 950 | AE25: 5 | AF25: 190 | AG25: =AE25*AF25 -> 950 | AH25: 5 | AI25: 190 | AJ25: =AH25*AI25 -> 950 | AN25: =S25+V25+Y25+AB25+AE25+AH25+AK25 -> 21 | AO25: =U25+X25+AA25+AD25+AG25+AJ25+AM25 -> 21450
F26: Перетягивание каната | G26: Спартакиада Краснодарской краевой организации Общества «Динамо» совместно с Новороссийской городской организацией Общества "Динамо" | H26: 21-50 лет | I26: по назначению | J26: по назначению | K26: г.Новороссийск | L26: 2 | M26: 2 | N26: 2 | O26: 10 | P26: 10 | Q26: 10 | R26: - | S26: 2 | T26: 3400 | U26: =S26*T26 -> 6800 | V26: 2 | W26: 3000 | X26: =V26*W26 -> 6000 | Y26: 2 | Z26: 2900 | AA26: =Y26*Z26 -> 5800 | AB26: 10 | AC26: 190 | AD26: =AB26*AC26 -> 1900 | AE26: 10 | AF26: 190 | AG26: =AE26*AF26 -> 1900 | AH26: 10 | AI26: 190 | AJ26: =AH26*AI26 -> 1900 | AN26: =S26+V26+Y26+AB26+AE26+AH26+AK26 -> 36 | AO26: =U26+X26+AA26+AD26+AG26+AJ26+AM26 -> 24300
F27: Стрельба из пневматической винтовки | G27: Спартакиада Краснодарской краевой организации Общества «Динамо» совместно с Новороссийской городской организацией Общества "Динамо" | H27: 21-50 лет | I27: по назначению | J27: по назначению | K27: г.Новороссийск | L27: 2 | M27: 2 | N27: 2 | O27: 5 | P27: 5 | Q27: 5 | R27: - | S27: 2 | T27: 3400 | U27: =S27*T27 -> 6800 | V27: 2 | W27: 3000 | X27: =V27*W27 -> 6000 | Y27: 2 | Z27: 2900 | AA27: =Y27*Z27 -> 5800 | AB27: 5 | AC27: 190 | AD27: =AB27*AC27 -> 950 | AE27: 5 | AF27: 190 | AG27: =AE27*AF27 -> 950 | AH27: 5 | AI27: 190 | AJ27: =AH27*AI27 -> 950 | AN27: =S27+V27+Y27+AB27+AE27+AH27+AK27 -> 21 | AO27: =U27+X27+AA27+AD27+AG27+AJ27+AM27 -> 21450
F28: Общекомандное первенство | G28: Спартакиада Краснодарской краевой организации Общества «Динамо» совместно с Новороссийской городской организацией Общества "Динамо" | H28: 21-50 лет | I28: по назначению | J28: по назначению | K28: г.Новороссийск | L28: 2 | M28: 2 | N28: 2 | O28: 5 | P28: 5 | Q28: 5 | R28: - | S28: 2 | T28: 3400 | U28: =S28*T28 -> 6800 | V28: 2 | W28: 3000 | X28: =V28*W28 -> 6000 | Y28: 2 | Z28: 2900 | AA28: =Y28*Z28 -> 5800
K29: ИТОГО | S29: 24 | V29: 24 | Y29: 24 | AB29: =SUM(AB17:AB27) -> 92 | AE29: 92 | AH29: 92
F30: Стрельба из пневматического пистолета | G30: 8-я Спартакиада Краснодарской краевой организации Общества «Динамо» среди ветеранов-пенсионеров органов безопасности и правопорядка | H30: 45+ | I30: март | J30: март | K30: г. Краснодар | L30: 1 | M30: 1 | N30: 1 | O30: 5 | P30: 5 | Q30: 5 | R30: - | S30: 1 | T30: 3400 | U30: =S30*T30 -> 3400 | V30: 1 | W30: 3000 | X30: =V30*W30 -> 3000 | Y30: 1 | Z30: 2900 | AA30: =Y30*Z30 -> 2900 | AB30: 5 | AC30: 190 | AD30: =AB30*AC30 -> 950 | AE30: 5 | AF30: 190 | AG30: =AE30*AF30 -> 950 | AH30: 5 | AI30: 190 | AJ30: =AH30*AI30 -> 950 | AN30: =S30+V30+Y30+AB30+AE30+AH30+AK30 -> 18 | AO30: =U30+X30+AA30+AD30+AG30+AJ30+AM30 -> 12150
F31: Стрельба из пневматической винтовки | G31: 8-я Спартакиада Краснодарской краевой организации Общества «Динамо» среди ветеранов-пенсионеров органов безопасности и правопорядка | H31: 45+ | I31: март | J31: март | K31: г. Краснодар | L31: 1 | M31: 1 | N31: 1 | O31: 5 | P31: 5 | Q31: 5 | R31: - | S31: 1 | T31: 3400 | U31: =S31*T31 -> 3400 | V31: 1 | W31: 3000 | X31: =V31*W31 -> 3000 | Y31: 1 | Z31: 2900 | AA31: =Y31*Z31 -> 2900 | AB31: 5 | AC31: 190 | AD31: =AB31*AC31 -> 950 | AE31: 5 | AF31: 190 | AG31: =AE31*AF31 -> 950 | AH31: 5 | AI31: 190 | AJ31: =AH31*AI31 -> 950 | AN31: =S31+V31+Y31+AB31+AE31+AH31+AK31 -> 18 | AO31: =U31+X31+AA31+AD31+AG31+AJ31+AM31 -> 12150
F32: Плавание | G32: 8-я Спартакиада Краснодарской краевой организации Общества «Динамо» среди ветеранов-пенсионеров органов безопасности и правопорядка | H32: 45+ | I32: май | J32: май | K32: г. Краснодар | L32: 1 | M32: 1 | N32: 1 | O32: 5 | P32: 5 | Q32: 5 | R32: - | S32: 1 | T32: 3400 | U32: =S32*T32 -> 3400 | V32: 1 | W32: 3000 | X32: =V32*W32 -> 3000 | Y32: 1 | Z32: 2900 | AA32: =Y32*Z32 -> 2900 | AB32: 5 | AC32: 190 | AD32: =AB32*AC32 -> 950 | AE32: 5 | AF32: 190 | AG32: =AE32*AF32 -> 950 | AH32: 5 | AI32: 190 | AJ32: =AH32*AI32 -> 950 | AN32: =S32+V32+Y32+AB32+AE32+AH32+AK32 -> 18 | AO32: =U32+X32+AA32+AD32+AG32+AJ32+AM32 -> 12150
F33: Шахматы (быстрые) | G33: 8-я Спартакиада Краснодарской краевой организации Общества «Динамо» среди ветеранов-пенсионеров органов безопасности и правопорядка | H33: 45+ | I33: сентябрь | J33: сентябрь | K33: г. Краснодар | L33: 1 | M33: 1 | N33: 1 | O33: 4 | P33: 4 | Q33: 4 | R33: - | S33: 1 | T33: 3400 | U33: =S33*T33 -> 3400 | V33: 1 | W33: 3000 | X33: =V33*W33 -> 3000 | Y33: 1 | Z33: 2900 | AA33: =Y33*Z33 -> 2900 | AB33: 4 | AC33: 190 | AD33: =AB33*AC33 -> 760 | AE33: 4 | AF33: 190 | AG33: =AE33*AF33 -> 760 | AH33: 4 | AI33: 190 | AJ33: =AH33*AI33 -> 760 | AN33: =S33+V33+Y33+AB33+AE33+AH33+AK33 -> 15 | AO33: =U33+X33+AA33+AD33+AG33+AJ33+AM33 -> 11580
F34: Настольный теннис | G34: 8-я Спартакиада Краснодарской краевой организации Общества «Динамо» среди ветеранов-пенсионеров органов безопасности и правопорядка | H34: 45+ | I34: октябрь | J34: октябрь | K34: г. Краснодар | L34: 1 | M34: 1 | N34: 1 | O34: 3 | P34: 3 | Q34: 3 | R34: - | S34: 1 | T34: 3400 | U34: =S34*T34 -> 3400 | V34: 1 | W34: 3000 | X34: =V34*W34 -> 3000 | Y34: 1 | Z34: 2900 | AA34: =Y34*Z34 -> 2900 | AB34: 3 | AC34: 190 | AD34: =AB34*AC34 -> 570 | AE34: 3 | AF34: 190 | AG34: =AE34*AF34 -> 570 | AH34: 3 | AI34: 190 | AJ34: =AH34*AI34 -> 570 | AN34: =S34+V34+Y34+AB34+AE34+AH34+AK34 -> 12 | AO34: =U34+X34+AA34+AD34+AG34+AJ34+AM34 -> 11010
F35: Шашки | G35: 8-я Спартакиада Краснодарской краевой организации Общества «Динамо» среди ветеранов-пенсионеров органов безопасности и правопорядка | H35: 45+ | I35: июнь | J35: июнь | K35: г. Краснодар | L35: 1 | M35: 1 | N35: 1 | O35: 4 | P35: 4 | Q35: 4 | R35: - | S35: 1 | T35: 3400 | U35: =S35*T35 -> 3400 | V35: 1 | W35: 3000 | X35: =V35*W35 -> 3000 | Y35: 1 | Z35: 2900 | AA35: =Y35*Z35 -> 2900 | AB35: 4 | AC35: 190 | AD35: =AB35*AC35 -> 760 | AE35: 4 | AF35: 190 | AG35: =AE35*AF35 -> 760 | AH35: 4 | AI35: 190 | AJ35: =AH35*AI35 -> 760 | AN35: =S35+V35+Y35+AB35+AE35+AH35+AK35 -> 15 | AO35: =U35+X35+AA35+AD35+AG35+AJ35+AM35 -> 11580
F36: Дартс | G36: 8-я Спартакиада Краснодарской краевой организации Общества «Динамо» среди ветеранов-пенсионеров органов безопасности и правопорядка | H36: 45+ | I36: февраль | J36: февраль | K36: г. Краснодар | L36: 1 | M36: 1 | N36: 1 | O36: 5 | P36: 5 | Q36: 5 | R36: - | S36: 1 | T36: 3400 | U36: =S36*T36 -> 3400 | V36: 1 | W36: 3000 | X36: =V36*W36 -> 3000 | Y36: 1 | Z36: 2900 | AA36: =Y36*Z36 -> 2900 | AB36: 5 | AC36: 190 | AD36: =AB36*AC36 -> 950 | AE36: 5 | AF36: 190 | AG36: =AE36*AF36 -> 950 | AH36: 5 | AI36: 190 | AJ36: =AH36*AI36 -> 950 | AN36: =S36+V36+Y36+AB36+AE36+AH36+AK36 -> 18 | AO36: =U36+X36+AA36+AD36+AG36+AJ36+AM36 -> 12150
F37: Рукопашный бой | G37: 8-я Спартакиада Краснодарской краевой организации Общества «Динамо» среди ветеранов-пенсионеров органов безопасности и правопорядка | H37: Дети 12-15 лет | I37: Декабрь | J37: Декабрь | K37: г. Краснодар | L37: 1 | M37: 1 | N37: 1 | O37: 9 | P37: 9 | Q37: 9 | R37: - | S37: 1 | T37: 3400 | U37: =S37*T37 -> 3400 | V37: 1 | W37: 3000 | X37: =V37*W37 -> 3000 | Y37: 1 | Z37: 2900 | AA37: =Y37*Z37 -> 2900 | AB37: 9 | AC37: 190 | AD37: =AB37*AC37 -> 1710 | AE37: 9 | AF37: 190 | AG37: =AE37*AF37 -> 1710 | AH37: 9 | AI37: 190 | AJ37: =AH37*AI37 -> 1710 | AN37: =S37+V37+Y37+AB37+AE37+AH37+AK37 -> 30 | AO37: =U37+X37+AA37+AD37+AG37+AJ37+AM37 -> 14430
F38: Общекомандное первенство | G38: Спартакиада Краснодарской краевой организации Общества «Динамо» совместно с Новороссийской городской организацией Общества "Динамо" | H38: 21-50 лет | I38: по назначению | J38: по назначению | K38: г.Новороссийск | L38: 2 | M38: 2 | N38: 2 | O38: 5 | P38: 5 | Q38: 5 | R38: - | S38: 1 | T38: 3400 | U38: =S38*T38 -> 3400 | V38: 1 | W38: 3000 | X38: =V38*W38 -> 3000 | Y38: 1 | Z38: 2900 | AA38: =Y38*Z38 -> 2900
K39: ИТОГО | S39: 9 | V39: 9 | Y39: 9 | AB39: =SUM(AB30:AB37) -> 40 | AE39: =SUM(AE30:AE37) -> 40 | AH39: =SUM(AH30:AH37) -> 40
F40: Дзюдо | G40: Спартакиада Главного управления ФС ВНГ России по Краснодарскому краю | H40: 21-50 лет | I40: 46048 | J40: 46049 | K40: г. Краснодар | L40: 1 | M40: 1 | N40: 1 | O40: 9 | P40: 9 | Q40: 9 | R40: 30 | S40: 1 | T40: 3400 | U40: =S40*T40 -> 3400 | V40: 1 | W40: 3000 | X40: =V40*W40 -> 3000 | Y40: 1 | Z40: 2900 | AA40: =Y40*Z40 -> 2900 | AB40: 9 | AC40: 190 | AD40: =AB40*AC40 -> 1710 | AE40: 9 | AF40: 190 | AG40: =AE40*AF40 -> 1710 | AH40: 9 | AI40: 190 | AJ40: =AH40*AI40 -> 1710 | AK40: 30 | AL40: 6 | AM40: =AK40*AL40 -> 180 | AN40: =S40+V40+Y40+AB40+AE40+AH40+AK40 -> 60 | AO40: =U40+X40+AA40+AD40+AG40+AJ40+AM40 -> 14610
H41: 21-50 лет
F42: Стрельба из боевого ручного стрелкового | G42: Спартакиада Главного управления ФС ВНГ России по Краснодарскому краю | H42: 21-50 лет | I42: 46091 | J42: 46094 | K42: г. Краснодар | L42: 1 | M42: 1 | N42: 1 | O42: 7 | P42: 7 | Q42: 7 | R42: 26 | S42: 1 | T42: 3400 | U42: =S42*T42 -> 3400 | V42: 1 | W42: 3000 | X42: =V42*W42 -> 3000 | Y42: 1 | Z42: 2900 | AA42: =Y42*Z42 -> 2900 | AB42: 7 | AC42: 190 | AD42: =AB42*AC42 -> 1330 | AE42: 7 | AF42: 190 | AG42: =AE42*AF42 -> 1330 | AH42: 7 | AI42: 190 | AJ42: =AH42*AI42 -> 1330 | AK42: 26 | AL42: 6 | AM42: =AK42*AL42 -> 156 | AN42: =S42+V42+Y42+AB42+AE42+AH42+AK42 -> 50 | AO42: =U42+X42+AA42+AD42+AG42+AJ42+AM42 -> 13446
F43: служебно-боевая стрельта | G43: Спартакиада Главного управления ФС ВНГ России по Краснодарскому краю | H43: 21-50 лет | I43: 46091 | J43: 46094 | K43: г. Краснодар
F44: Служебный биатлон | G44: Спартакиада Главного управления ФС ВНГ России по Краснодарскому краю | H44: 21-50 лет | I44: 46139 | J44: 46141 | K44: г. Краснодар | L44: 1 | M44: 1 | N44: 1 | O44: 6 | P44: 6 | Q44: 6 | R44: 24 | S44: 1 | T44: 3400 | U44: =S44*T44 -> 3400 | V44: 1 | W44: 3000 | X44: =V44*W44 -> 3000 | Y44: 1 | Z44: 2900 | AA44: =Y44*Z44 -> 2900 | AB44: 6 | AC44: 190 | AD44: =AB44*AC44 -> 1140 | AE44: 6 | AF44: 190 | AG44: =AE44*AF44 -> 1140 | AH44: 6 | AI44: 190 | AJ44: =AH44*AI44 -> 1140 | AK44: 24 | AL44: 6 | AM44: =AK44*AL44 -> 144 | AN44: =S44+V44+Y44+AB44+AE44+AH44+AK44 -> 45 | AO44: =U44+X44+AA44+AD44+AG44+AJ44+AM44 -> 12864
F45: Легкая атлетика (кросс) | G45: Спартакиада Главного управления ФС ВНГ России по Краснодарскому краю | H45: 21-50 лет | I45: 46139 | J45: 46141 | K45: г. Краснодар | L45: 1 | M45: 1 | N45: 1 | O45: 10 | P45: 10 | Q45: 10 | R45: 33 | S45: 1 | T45: 3400 | U45: =S45*T45 -> 3400 | V45: 1 | W45: 3000 | X45: =V45*W45 -> 3000 | Y45: 1 | Z45: 2900 | AA45: =Y45*Z45 -> 2900 | AB45: 10 | AC45: 190 | AD45: =AB45*AC45 -> 1900 | AE45: 10 | AF45: 190 | AG45: =AE45*AF45 -> 1900 | AH45: 10 | AI45: 190 | AJ45: =AH45*AI45 -> 1900 | AK45: 33 | AL45: 6 | AM45: =AK45*AL45 -> 198 | AN45: =S45+V45+Y45+AB45+AE45+AH45+AK45 -> 66 | AO45: =U45+X45+AA45+AD45+AG45+AJ45+AM45 -> 15198
H46: 21-50 лет | I46: по назначению | J46: по назначению
F47: Мини-футбол | G47: Спартакиада Главного управления ФС ВНГ России по Краснодарскому краю | H47: 21-50 лет | I47: 46217 | J47: 46220 | K47: г. Краснодар | L47: 1 | M47: 1 | N47: 1 | O47: 7 | P47: 7 | Q47: 7 | R47: 24 | S47: 1 | T47: 3400 | U47: =S47*T47 -> 3400 | V47: 1 | W47: 3000 | X47: =V47*W47 -> 3000 | Y47: 1 | Z47: 2900 | AA47: =Y47*Z47 -> 2900 | AB47: 7 | AC47: 190 | AD47: =AB47*AC47 -> 1330 | AE47: 7 | AF47: 190 | AG47: =AE47*AF47 -> 1330 | AH47: 7 | AI47: 190 | AJ47: =AH47*AI47 -> 1330 | AK47: 24 | AL47: 6 | AM47: =AK47*AL47 -> 144 | AN47: =S47+V47+Y47+AB47+AE47+AH47+AK47 -> 48 | AO47: =U47+X47+AA47+AD47+AG47+AJ47+AM47 -> 13434
F48: военно многоборье-спортивное многоборье | G48: Спартакиада Главного управления ФС ВНГ России по Краснодарскому краю | H48: 21-50 лет | I48: 46231 | J48: 46233 | K48: г. Краснодар
A49: выдано | F49: Самбо и боевое самбо | G49: Спартакиада Главного управления ФС ВНГ России по Краснодарскому краю | H49: 21-50 лет | I49: 46224 | J49: 46226 | K49: г. Краснодар | L49: 1 | M49: 1 | N49: 1 | O49: 10 | P49: 10 | Q49: 10 | R49: 36
S50: 1 | T50: 3400 | U50: =S50*T50 -> 3400 | V50: 1 | W50: 3000 | X50: =V50*W50 -> 3000 | Y50: 1 | Z50: 2900 | AA50: =Y50*Z50 -> 2900 | AB50: 10 | AC50: 190 | AD50: =AB50*AC50 -> 1900 | AE50: 10 | AF50: 190 | AG50: =AE50*AF50 -> 1900 | AH50: 10 | AI50: 190 | AJ50: =AH50*AI50 -> 1900 | AK50: 36 | AL50: 6 | AM50: =AK50*AL50 -> 216 | AN50: =S50+V50+Y50+AB50+AE50+AH50+AK50 -> 69 | AO50: =U50+X50+AA50+AD50+AG50+AJ50+AM50 -> 15216
A51: выдано | F51: Плавание | G51: Спартакиада Главного управления ФС ВНГ России по Краснодарскому краю | H51: 21-50 лет | I51: 46231 | J51: 46233 | K51: г. Краснодар | L51: 1 | M51: 1 | N51: 1 | O51: 12 | P51: 12 | Q51: 12 | R51: 38
S52: 1 | T52: 3400 | U52: =S52*T52 -> 3400 | V52: 1 | W52: 3000 | X52: =V52*W52 -> 3000 | Y52: 1 | Z52: 2900 | AA52: =Y52*Z52 -> 2900 | AB52: 12 | AC52: 190 | AD52: =AB52*AC52 -> 2280 | AE52: 12 | AF52: 190 | AG52: =AE52*AF52 -> 2280 | AH52: 12 | AI52: 190 | AJ52: =AH52*AI52 -> 2280 | AK52: 38 | AL52: 6 | AM52: =AK52*AL52 -> 228 | AN52: =S52+V52+Y52+AB52+AE52+AH52+AK52 -> 77 | AO52: =U52+X52+AA52+AD52+AG52+AJ52+AM52 -> 16368
A53: выдано | F53: Рукопашный бой | G53: Спартакиада Главного управления ФС ВНГ России по Краснодарскому краю | H53: 21-50 лет | I53: 46343 | J53: 46344 | K53: г. Краснодар | L53: 1 | M53: 1 | N53: 1 | O53: 8 | P53: 8 | Q53: 8 | R53: 27
S54: 1 | T54: 3400 | U54: =S54*T54 -> 3400 | V54: 1 | W54: 3000 | X54: =V54*W54 -> 3000 | Y54: 1 | Z54: 2900 | AA54: =Y54*Z54 -> 2900 | AB54: 8 | AC54: 190 | AD54: =AB54*AC54 -> 1520 | AE54: 8 | AF54: 190 | AG54: =AE54*AF54 -> 1520 | AH54: 8 | AI54: 190 | AJ54: =AH54*AI54 -> 1520 | AK54: 27 | AL54: 6 | AM54: =AK54*AL54 -> 162 | AN54: =S54+V54+Y54+AB54+AE54+AH54+AK54 -> 54 | AO54: =U54+X54+AA54+AD54+AG54+AJ54+AM54 -> 14022
A55: выдано | F55: Шахматы | G55: Спартакиада Главного управления ФС ВНГ России по Краснодарскому краю | H55: 21-50 лет | I55: 46048 | J55: 46049 | K55: г. Краснодар | L55: 1 | M55: 1 | N55: 1 | O55: 1 | P55: 1 | Q55: 1 | R55: 6 | S55: 1 | V55: 1 | Y55: 1 | AB55: 0 | AE55: 0 | AH55: 0 | AK55: 6
S56: 1 | T56: 3400 | U56: =S56*T56 -> 3400 | V56: 1 | W56: 3000 | X56: =V56*W56 -> 3000 | Y56: 1 | Z56: 2900 | AA56: =Y56*Z56 -> 2900 | AB56: 1 | AC56: 190 | AD56: =AB56*AC56 -> 190 | AE56: 1 | AF56: 190 | AG56: =AE56*AF56 -> 190 | AH56: 1 | AI56: 190 | AJ56: =AH56*AI56 -> 190 | AK56: 6 | AL56: 6 | AM56: =AK56*AL56 -> 36 | AN56: =S56+V56+Y56+AB56+AE56+AH56+AK56 -> 12 | AO56: =U56+X56+AA56+AD56+AG56+AJ56+AM56 -> 9906
A57: выдано | F57: Бокс | G57: Спартакиада Главного управления ФС ВНГ России по Краснодарскому краю | H57: 21-50 лет | I57: 46104 | J57: 46106 | K57: г. Краснодар | L57: 1 | M57: 1 | N57: 1 | O57: 12 | P57: 12 | Q57: 12 | R57: 39
S58: 1 | T58: 3400 | U58: =S58*T58 -> 3400 | V58: 1 | W58: 3000 | X58: =V58*W58 -> 3000 | Y58: 1 | Z58: 2900 | AA58: =Y58*Z58 -> 2900 | AB58: 12 | AC58: 190 | AD58: =AB58*AC58 -> 2280 | AE58: 12 | AF58: 190 | AG58: =AE58*AF58 -> 2280 | AH58: 12 | AI58: 190 | AJ58: =AH58*AI58 -> 2280 | AK58: 39 | AL58: 6 | AM58: =AK58*AL58 -> 234 | AN58: =S58+V58+Y58+AB58+AE58+AH58+AK58 -> 78 | AO58: =U58+X58+AA58+AD58+AG58+AJ58+AM58 -> 16374
A59: выдано | F59: Комплексное единоборство | G59: Спартакиада Главного управления ФС ВНГ России по Краснодарскому краю | H59: 21-50 лет | I59: 46225 | J59: по назначению | K59: г. Краснодар | L59: 1 | M59: 1 | N59: 1 | O59: 8 | P59: 8 | Q59: 8 | R59: 27
S60: 1 | T60: 3400 | U60: =S60*T60 -> 3400 | V60: 1 | W60: 3000 | X60: =V60*W60 -> 3000 | Y60: 1 | Z60: 2900 | AA60: =Y60*Z60 -> 2900 | AB60: 8 | AC60: 190 | AD60: =AB60*AC60 -> 1520 | AE60: 8 | AF60: 190 | AG60: =AE60*AF60 -> 1520 | AH60: 8 | AI60: 190 | AJ60: =AH60*AI60 -> 1520 | AK60: 27 | AL60: 6 | AM60: =AK60*AL60 -> 162 | AN60: =S60+V60+Y60+AB60+AE60+AH60+AK60 -> 54 | AO60: =U60+X60+AA60+AD60+AG60+AJ60+AM60 -> 14022
K61: ИТОГО | S61: =SUM(S40:S60) -> 12 | V61: =SUM(V40:V60) -> 12 | Y61: =SUM(Y40:Y60) -> 12 | AB61: =SUM(AB40:AB60) -> 90 | AE61: =SUM(AE40:AE60) -> 90 | AH61: =SUM(AH40:AH60) -> 90 | AK61: =SUM(AK40:AK60) -> 316

Sheet Спартакиада юнош.
D1: XIII летняя Спартакиада учащихся (юношеская) Кубани 2026 года (по видам спорта)
B2: Вид спорта | C2: Месяц | D2: Дата проведения (начало мероприятия) | E2: Дата проведения (конец мероприятия) | F2: Место проведения | G2: Количество кубков | P2: Количество медалей | Y2: Грамоты | AD2: Дата согласования положения
G3: Кол-во, шт. | H3: Стоимость 1 шт. | I3: Итого | J3: Кол-во, шт. | K3: Стоимость 1 шт. | L3: Итого | M3: Кол-во, шт. | N3: Стоимость 1 шт. | O3: Итого | P3: Кол-во, шт. | Q3: Стоимость 1 шт. | R3: Итого | S3: Кол-во, шт. | T3: Стоимость 1 шт. | U3: Итого | V3: Количество, шт. | W3: Стоимость 1 | X3: Итого | Y3: Кол-во, шт. | Z3: Стоимость 1 шт. | AA3: Итого
A4: 1 | B4: Бадминтон | D4: 46093 | E4: 46096 | F4: г.Гулькевичи | G4: 1 | H4: 3400 | I4: =G4*H4 -> 3400 | J4: 1 | K4: 3000 | L4: =J4*K4 -> 3000 | M4: 1 | N4: 2900 | O4: =M4*N4 -> 2900 | P4: 8 | Q4: 190 | R4: =P4*Q4 -> 1520 | S4: 8 | T4: 190 | U4: =S4*T4 -> 1520 | V4: 16 | W4: 190 | X4: =V4*W4 -> 3040 | Y4: 35 | Z4: 6 | AA4: =Y4*Z4 -> 210 | AB4: =G4+J4+M4+P4+S4+V4+Y4 -> 70 | AC4: =I4+L4+O4+R4+U4+X4+234 -> 15614 | AD4: 46002
A5: 2 | B5: Баскетбол (юноши) | D5: 46103 | E5: 46109 | F5: г. Краснодар | G5: 1 | H5: 3400 | I5: =G5*H5 -> 3400 | J5: 1 | K5: 3000 | L5: =J5*K5 -> 3000 | M5: 1 | N5: 2900 | O5: =M5*N5 -> 2900 | P5: 14 | Q5: 190 | R5: =P5*Q5 -> 2660 | S5: 14 | T5: 190 | U5: =S5*T5 -> 2660 | V5: 14 | W5: 190 | X5: =V5*W5 -> 2660 | Y5: 45 | Z5: 6 | AA5: =Y5*Z5 -> 270 | AB5: =G5+J5+M5+P5+S5+V5+Y5 -> 90 | AC5: =I5+L5+O5+R5+U5+X5+234 -> 17514 | AD5: 46002
A6: 3 | B6: Баскетбол (девушки) | D6: 46096 | E6: 46102 | F6: г. Краснодар | G6: 1 | H6: 3400 | I6: =G6*H6 -> 3400 | J6: 1 | K6: 3000 | L6: =J6*K6 -> 3000 | M6: 1 | N6: 2900 | O6: =M6*N6 -> 2900 | P6: 14 | Q6: 190 | R6: =P6*Q6 -> 2660 | S6: 14 | T6: 190 | U6: =S6*T6 -> 2660 | V6: 14 | W6: 190 | X6: =V6*W6 -> 2660 | Y6: 45 | Z6: 6 | AA6: =Y6*Z6 -> 270 | AB6: =G6+J6+M6+P6+S6+V6+Y6 -> 90 | AC6: =I6+L6+O6+R6+U6+X6+234 -> 17514 | AD6: 46002
A7: 4 | B7: Велосипедный спорт (Маунтибайк) | D7: 46092 | E7: 46096 | F7: г.Геленджик, с.Архипо-Осиповка | G7: 1 | H7: 3400 | I7: =G7*H7 -> 3400 | J7: 1 | K7: 3000 | L7: =J7*K7 -> 3000 | M7: 1 | N7: 2900 | O7: =M7*N7 -> 2900 | P7: 6 | Q7: 190 | R7: =P7*Q7 -> 1140 | S7: 6 | T7: 190 | U7: =S7*T7 -> 1140 | V7: 6 | W7: 190 | X7: =V7*W7 -> 1140 | Y7: 21 | Z7: 6 | AA7: =Y7*Z7 -> 126 | AB7: =G7+J7+M7+P7+S7+V7+Y7 -> 42 | AC7: =I7+L7+O7+R7+U7+X7+234 -> 12954 | AD7: 46002
A8: 5 | B8: Велосипедный спорт (дисциплина шоссе) | D8: 46156 | E8: 46160 | F8: ст-ца Брюховецкая | G8: 1 | H8: 3400 | I8: 3400 | J8: 1 | K8: 3000 | L8: 3000 | M8: 1 | N8: 2900 | O8: 2900 | P8: 4 | Q8: 190 | R8: 1140 | S8: 4 | T8: 190 | U8: 1140 | V8: 4 | W8: 190 | X8: 1140 | Y8: 15 | Z8: 6 | AA8: 126 | AB8: 42 | AC8: 12954 | AD8: 46002
A9: 6 | B9: Велосипедный спорт (BMX) | D9: 46156 | E9: 46160 | F9: ст-ца Брюховецкая | G9: 1 | H9: 3400 | I9: 3400 | J9: 1 | K9: 3000 | L9: 3000 | M9: 1 | N9: 2900 | O9: 2900 | P9: 4 | Q9: 190 | R9: 1140 | S9: 4 | T9: 190 | U9: 1140 | V9: 4 | W9: 190 | X9: 1140 | Y9: 15 | Z9: 6 | AA9: 126 | AB9: 42 | AC9: 12954 | AD9: 46002
A10: 7 | B10: Волейбол (девушки) | D10: 46112 | E10: 46117 | F10: Курганинский район, г.Курганинск | G10: 1 | H10: 3400 | I10: =G10*H10 -> 3400 | J10: 1 | K10: 3000 | L10: =J10*K10 -> 3000 | M10: 1 | N10: 2900 | O10: =M10*N10 -> 2900 | P10: 14 | Q10: 190 | R10: =P10*Q10 -> 2660 | S10: 14 | T10: 190 | U10: =S10*T10 -> 2660 | V10: 14 | W10: 190 | X10: =V10*W10 -> 2660 | Y10: 45 | Z10: 6 | AA10: =Y10*Z10 -> 270 | AB10: =G10+J10+M10+P10+S10+V10+Y10 -> 90 | AC10: =I10+L10+O10+R10+U10+X10+234 -> 17514 | AD10: 46002
A11: 8 | B11: Волейбол (юноши) | D11: 46112 | E11: 46117 | F11: Северский район, пгт.Ильский | G11: 1 | H11: 3400 | I11: =G11*H11 -> 3400 | J11: 1 | K11: 3000 | L11: =J11*K11 -> 3000 | M11: 1 | N11: 2900 | O11: =M11*N11 -> 2900 | P11: 14 | Q11: 190 | R11: =P11*Q11 -> 2660 | S11: 14 | T11: 190 | U11: =S11*T11 -> 2660 | V11: 14 | W11: 190 | X11: =V11*W11 -> 2660 | Y11: 45 | Z11: 6 | AA11: =Y11*Z11 -> 270 | AB11: =G11+J11+M11+P11+S11+V11+Y11 -> 90 | AC11: =I11+L11+O11+R11+U11+X11+234 -> 17514 | AD11: 46002
A12: 9 | B12: Волейбол пляжный | D12: 46146 | E12: 46149 | F12: г.Краснодар | G12: 1 | H12: 3400 | I12: =G12*H12 -> 3400 | J12: 1 | K12: 3000 | L12: =J12*K12 -> 3000 | M12: 1 | N12: 2900 | O12: =M12*N12 -> 2900 | P12: 3 | Q12: 190 | R12: =P12*Q12 -> 570 | S12: 3 | T12: 190 | U12: =S12*T12 -> 570 | V12: 3 | W12: 190 | X12: =V12*W12 -> 570 | Y12: 9 | Z12: 6 | AA12: =Y12*Z12 -> 54 | AB12: =G12+J12+M12+P12+S12+V12+Y12 -> 21 | AC12: =I12+L12+O12+R12+U12+X12+234 -> 11244 | AD12: 46002
A13: 10 | B13: Волейбол пляжный | D13: 46146 | E13: 46149 | F13: г.Краснодар | G13: 1 | H13: 3400 | I13: =G13*H13 -> 3400 | J13: 1 | K13: 3000 | L13: =J13*K13 -> 3000 | M13: 1 | N13: 2900 | O13: =M13*N13 -> 2900 | P13: 3 | Q13: 190 | R13: =P13*Q13 -> 570 | S13: 3 | T13: 190 | U13: =S13*T13 -> 570 | V13: 3 | W13: 190 | X13: =V13*W13 -> 570 | Y13: 9 | Z13: 6 | AA13: =Y13*Z13 -> 54 | AB13: =G13+J13+M13+P13+S13+V13+Y13 -> 21 | AC13: =I13+L13+O13+R13+U13+X13+234 -> 11244 | AD13: 46002
A14: 11 | B14: Гандбол (юноши) | D14: 46048 | E14: 46053 | F14: Павловский район, ст-ца Павловская | G14: 1 | H14: 3400 | I14: =G14*H14 -> 3400 | J14: 1 | K14: 3000 | L14: =J14*K14 -> 3000 | M14: 1 | N14: 2900 | O14: =M14*N14 -> 2900 | P14: 18 | Q14: 190 | R14: =P14*Q14 -> 3420 | S14: 18 | T14: 190 | U14: =S14*T14 -> 3420 | V14: 18 | W14: 190 | X14: =V14*W14 -> 3420 | Y14: 57 | Z14: 6 | AA14: =Y14*Z14 -> 342 | AB14: =G14+J14+M14+P14+S14+V14+Y14 -> 114 | AC14: =I14+L14+O14+R14+U14+X14+234 -> 19794 | AD14: 46002
A15: 12 | B15: Гандбол (девушки) | D15: 46055 | E15: 46060 | F15: Павловский район, ст-ца Павловская | G15: 1 | H15: 3400 | I15: =G15*H15 -> 3400 | J15: 1 | K15: 3000 | L15: =J15*K15 -> 3000 | M15: 1 | N15: 2900 | O15: =M15*N15 -> 2900 | P15: 18 | Q15: 190 | R15: =P15*Q15 -> 3420 | S15: 18 | T15: 190 | U15: =S15*T15 -> 3420 | V15: 18 | W15: 190 | X15: =V15*W15 -> 3420 | Y15: 57 | Z15: 6 | AA15: =Y15*Z15 -> 342 | AB15: =G15+J15+M15+P15+S15+V15+Y15 -> 114 | AC15: =I15+L15+O15+R15+U15+X15+234 -> 19794 | AD15: 46002
A16: 13 | B16: Гребной спорт | C16: пк | D16: 46154 | E16: 46156 | F16: г. Краснодар | G16: 1 | H16: 3400 | I16: =G16*H16 -> 3400 | J16: 1 | K16: 3000 | L16: =J16*K16 -> 3000 | M16: 1 | N16: 2900 | O16: =M16*N16 -> 2900 | P16: 44 | Q16: 190 | R16: =P16*Q16 -> 8360 | S16: 44 | T16: 190 | U16: =S16*T16 -> 8360 | V16: 44 | W16: 190 | X16: =V16*W16 -> 8360 | Y16: 135 | Z16: 6 | AA16: =Y16*Z16 -> 810 | AB16: =G16+J16+M16+P16+S16+V16+Y16 -> 270 | AC16: =I16+L16+O16+R16+U16+X16+234 -> 34614 | AD16: 46002
A17: 14 | B17: ЛАПТА (девушки) | D17: 46200 | E17: 46201 | F17: Кущевский район, ст-ца Кущевская | G17: 1 | H17: 3400 | I17: =G17*H17 -> 3400 | J17: 1 | K17: 3000 | L17: =J17*K17 -> 3000 | M17: 1 | N17: 2900 | O17: =M17*N17 -> 2900 | P17: 8 | Q17: 190 | R17: =P17*Q17 -> 1520 | S17: 8 | T17: 190 | U17: =S17*T17 -> 1520 | V17: 8 | W17: 190 | X17: =V17*W17 -> 1520 | Y17: 24 | Z17: 6 | AA17: =Y17*Z17 -> 144 | AB17: =G17+J17+M17+P17+S17+V17+Y17 -> 51 | AC17: =I17+L17+O17+R17+U17+X17+234 -> 14094 | AD17: 46002 | AG17: нет в потребности
A18: 15 | B18: ЛАПТА (юноши) | D18: 46200 | E18: 46201 | F18: Кущевский район, ст-ца Кущевская | G18: 1 | H18: 3400 | I18: =G18*H18 -> 3400 | J18: 1 | K18: 3000 | L18: =J18*K18 -> 3000 | M18: 1 | N18: 2900 | O18: =M18*N18 -> 2900 | P18: 8 | Q18: 190 | R18: =P18*Q18 -> 1520 | S18: 8 | T18: 190 | U18: =S18*T18 -> 1520 | V18: 8 | W18: 190 | X18: =V18*W18 -> 1520 | Y18: 24 | Z18: 6 | AA18: =Y18*Z18 -> 144 | AB18: =G18+J18+M18+P18+S18+V18+Y18 -> 51 | AC18: =I18+L18+O18+R18+U18+X18+234 -> 14094 | AD18: 46002 | AF18: нет в потребности
A19: 16 | B19: Дзюдо (юниоры) | D19: 46126 | E19: 46128 | F19: г. Армавир | G19: 1 | H19: 3400 | I19: =G19*H19 -> 3400 | J19: 1 | K19: 3000 | L19: =J19*K19 -> 3000 | M19: 1 | N19: 2900 | O19: =M19*N19 -> 2900 | P19: 9 | Q19: 190 | R19: =P19*Q19 -> 1710 | S19: 9 | T19: 190 | U19: =S19*T19 -> 1710 | V19: 18 | W19: 190 | X19: =V19*W19 -> 3420 | Y19: 39 | Z19: 6 | AA19: =Y19*Z19 -> 234 | AB19: =G19+J19+M19+P19+S19+V19+Y19 -> 78 | AC19: =I19+L19+O19+R19+U19+X19+234 -> 16374
A20: 17 | B20: Дзюдо (юниорки) | D20: 46126 | E20: 46128 | F20: г. Армавир | G20: 1 | H20: 3400 | I20: =G20*H20 -> 3400 | J20: 1 | K20: 3000 | L20: =J20*K20 -> 3000 | M20: 1 | N20: 2900 | O20: =M20*N20 -> 2900 | P20: 8 | Q20: 190 | R20: =P20*Q20 -> 1520 | S20: 8 | T20: 190 | U20: =S20*T20 -> 1520 | V20: 16 | W20: 190 | X20: =V20*W20 -> 3040 | Y20: 35 | Z20: 6 | AA20: =Y20*Z20 -> 210 | AB20: =G20+J20+M20+P20+S20+V20+Y20+35 -> 105 | AC20: =I20+L20+O20+R20+U20+X20+210 -> 15590
A21: 18 | B21: Легкая атлетика | D21: 46171 | E21: 46173 | F21: г. Краснодар | G21: 1 | H21: 3400 | I21: =G21*H21 -> 3400 | J21: 1 | K21: 3000 | L21: =J21*K21 -> 3000 | M21: 1 | N21: 2900 | O21: =M21*N21 -> 2900 | P21: 40 | Q21: 190 | R21: =P21*Q21 -> 7600 | S21: 40 | T21: 190 | U21: =S21*T21 -> 7600 | V21: 40 | W21: 190 | X21: =V21*W21 -> 7600 | Y21: 123 | Z21: 6 | AA21: =Y21*Z21 -> 738 | AB21: =G21+J21+M21+P21+S21+V21+Y21 -> 246 | AC21: =I21+L21+O21+R21+U21+X21+234 -> 32334 | AD21: 46002
A22: 19 | B22: Теннис (юноши) | D22: 46110 | E22: 46117 | F22: г.Кореновск | G22: 1 | H22: 3400 | I22: =G22*H22 -> 3400 | J22: 1 | K22: 3000 | L22: =J22*K22 -> 3000 | M22: 1 | N22: 2900 | O22: =M22*N22 -> 2900 | P22: 3 | Q22: 190 | R22: =P22*Q22 -> 570 | S22: 3 | T22: 190 | U22: =S22*T22 -> 570 | V22: 3 | W22: 190 | X22: =V22*W22 -> 570 | Y22: 12 | Z22: 6 | AA22: =Y22*Z22 -> 72 | AB22: =G22+J22+M22+P22+S22+V22+Y22 -> 24 | AC22: =I22+L22+O22+R22+U22+X22+234 -> 11244 | AD22: 46002 | AE22: 46002 | AF22: 46002
A23: 20 | B23: Теннис (девушки) | D23: 46110 | E23: 46117 | F23: г.Кореновск | G23: 1 | H23: 3400 | I23: =G23*H23 -> 3400 | J23: 1 | K23: 3000 | L23: =J23*K23 -> 3000 | M23: 1 | N23: 2900 | O23: =M23*N23 -> 2900 | P23: 3 | Q23: 190 | R23: =P23*Q23 -> 570 | S23: 3 | T23: 190 | U23: =S23*T23 -> 570 | V23: 3 | W23: 190 | X23: =V23*W23 -> 570 | Y23: 12 | Z23: 6 | AA23: =Y23*Z23 -> 72 | AB23: =G23+J23+M23+P23+S23+V23+Y23 -> 24 | AC23: =I23+L23+O23+R23+U23+X23+234 -> 11244 | AD23: 46002 | AE23: 46002 | AF23: 46002
A24: 21 | B24: Прыжки на батуте | D24: 46132 | E24: 46135 | F24: г. Краснодар | G24: 1 | H24: 3400 | I24: =G24*H24 -> 3400 | J24: 1 | K24: 3000 | L24: =J24*K24 -> 3000 | M24: 1 | N24: 2900 | O24: =M24*N24 -> 2900 | P24: 10 | Q24: 190 | R24: =P24*Q24 -> 1900 | S24: 10 | T24: 190 | U24: =S24*T24 -> 1900 | V24: 10 | W24: 190 | X24: =V24*W24 -> 1900 | Y24: 30 | Z24: 6 | AA24: =Y24*Z24 -> 180 | AB24: =G24+J24+M24+P24+S24+V24+Y24 -> 63 | AC24: =I24+L24+O24+R24+U24+X24+234 -> 15234 | AD24: 46002 | AE24: 46002 | AF24: 46002
A25: 22 | B25: Пулевая стрельба | D25: 46182 | E25: 46185 | F25: г. Краснодар | G25: 1 | H25: 3400 | I25: =G25*H25 -> 3400 | J25: 1 | K25: 3000 | L25: =J25*K25 -> 3000 | M25: 1 | N25: 2900 | O25: =M25*N25 -> 2900 | P25: 8 | Q25: 190 | R25: =P25*Q25 -> 1520 | S25: 8 | T25: 190 | U25: =S25*T25 -> 1520 | V25: 12 | W25: 190 | X25: =V25*W25 -> 2280 | Y25: 31 | Z25: 6 | AA25: =Y25*Z25 -> 186 | AB25: =G25+J25+M25+P25+S25+V25+Y25 -> 62 | AC25: =I25+L25+O25+R25+U25+X25+AA25 -> 14806 | AD25: 46002 | AE25: 46002 | AF25: 46002
A26: 23 | B26: Регби-7 (юноши, девушки) | D26: 46116 | E26: 46117 | F26: Красноармейский район, ст-ца Старожестеблиевская | G26: 2 | H26: 3400 | I26: =G26*H26 -> 6800 | J26: 2 | K26: 3000 | L26: =J26*K26 -> 6000 | M26: 2 | N26: 2900 | O26: =M26*N26 -> 5800 | P26: 30 | Q26: 190 | R26: =P26*Q26 -> 5700 | S26: 30 | T26: 190 | U26: =S26*T26 -> 5700 | V26: 30 | W26: 190 | X26: =V26*W26 -> 5700 | Y26: 96 | Z26: 6 | AA26: =Y26*Z26 -> 576 | AB26: =G26+J26+M26+P26+S26+V26+Y26 -> 192 | AC26: =I26+L26+O26+R26+U26+X26+288 -> 35988 | AD26: 46002
A27: 24 | B27: Водное поло (юноши) | D27: 46174 | E27: 46179 | F27: г. Краснодар | G27: 1 | H27: 3400 | I27: =G27*H27 -> 3400 | J27: 1 | K27: 3000 | L27: =J27*K27 -> 3000 | M27: 1 | N27: 2900 | O27: =M27*N27 -> 2900 | P27: 18 | Q27: 190 | R27: =P27*Q27 -> 3420 | S27: 18 | T27: 190 | U27: =S27*T27 -> 3420 | V27: 18 | W27: 190 | X27: =V27*W27 -> 3420 | Y27: 57 | Z27: 6 | AA27: =Y27*Z27 -> 342 | AB27: =G27+J27+M27+P27+S27+V27+Y27+35 -> 149 | AC27: =I27+L27+O27+R27+U27+X27+210 -> 19770 | AD27: 46002
A28: 25 | B28: Спортивная борьба (греко-римская борьба (юноши) | D28: 46087 | E28: 46089 | F28: г. Краснодар | G28: 1 | H28: 3400 | I28: =G28*H28 -> 3400 | J28: 1 | K28: 3000 | L28: =J28*K28 -> 3000 | M28: 1 | N28: 2900 | O28: =M28*N28 -> 2900 | P28: 15 | Q28: 190 | R28: =P28*Q28 -> 2850 | S28: 15 | T28: 190 | U28: =S28*T28 -> 2850 | V28: 30 | W28: 190 | X28: =V28*W28 -> 5700 | Y28: 60 | Z28: 6 | AA28: =Y28*Z28 -> 360 | AB28: =G28+J28+M28+P28+S28+V28+Y28+35 -> 158 | AC28: =I28+L28+O28+R28+U28+X28+210 -> 20910 | AD28: 46002
A29: 26 | B29: Спортивная борьба (вольная борьба (юноши) | D29: 46101 | E29: 46103 | F29: г.Горячий Ключ | G29: 1 | H29: 3400 | I29: =G29*H29 -> 3400 | J29: 1 | K29: 3000 | L29: =J29*K29 -> 3000 | M29: 1 | N29: 2900 | O29: =M29*N29 -> 2900 | P29: 11 | Q29: 190 | R29: =P29*Q29 -> 2090 | S29: 11 | T29: 190 | U29: =S29*T29 -> 2090 | V29: 22 | W29: 190 | X29: =V29*W29 -> 4180 | Y29: 58 | Z29: 6 | AA29: =Y29*Z29 -> 348 | AB29: =G29+J29+M29+P29+S29+V29+Y29+35 -> 140 | AC29: =I29+L29+O29+R29+U29+X29+210 -> 17870 | AD29: 46002
A30: 27 | B30: Спортивная борьба (вольная борьба (девушки) | D30: 46101 | E30: 46103 | F30: г.Горячий Ключ | G30: 1 | H30: 3400 | I30: =G30*H30 -> 3400 | J30: 1 | K30: 3000 | L30: =J30*K30 -> 3000 | M30: 1 | N30: 2900 | O30: =M30*N30 -> 2900 | P30: 11 | Q30: 190 | R30: =P30*Q30 -> 2090 | S30: 11 | T30: 190 | U30: =S30*T30 -> 2090 | V30: 22 | W30: 190 | X30: =V30*W30 -> 4180 | Y30: 58 | Z30: 6 | AA30: =Y30*Z30 -> 348 | AB30: =G30+J30+M30+P30+S30+V30+Y30+35 -> 140 | AC30: =I30+L30+O30+R30+U30+X30+210 -> 17870 | AD30: 46002
A31: 28 | B31: Спортивная гимнастика | D31: 46119 | E31: 46123 | F31: г. Краснодар | G31: 1 | H31: 3400 | I31: =G31*H31 -> 3400 | J31: 1 | K31: 3000 | L31: =J31*K31 -> 3000 | M31: 1 | N31: 2900 | O31: =M31*N31 -> 2900 | P31: 20 | Q31: 190 | R31: =P31*Q31 -> 3800 | S31: 20 | T31: 190 | U31: =S31*T31 -> 3800 | V31: 20 | W31: 190 | X31: =V31*W31 -> 3800 | Y31: 63 | Z31: 6 | AA31: =Y31*Z31 -> 378 | AB31: =G31+J31+M31+P31+S31+V31+Y31 -> 126 | AC31: =I31+L31+O31+R31+U31+X31+234 -> 20934 | AD31: 46002
A32: 29 | B32: Пулевая стрельба | D32: 46182 | E32: 46185 | F32: г. Краснодар | G32: 1 | H32: 3400 | I32: =G32*H32 -> 3400 | J32: 1 | K32: 3000 | L32: =J32*K32 -> 3000 | M32: 1 | N32: 2900 | O32: =M32*N32 -> 2900 | P32: 8 | Q32: 190 | R32: =P32*Q32 -> 1520 | S32: 8 | T32: 190 | U32: =S32*T32 -> 1520 | V32: 12 | W32: 190 | X32: =V32*W32 -> 2280 | Y32: 31 | Z32: 6 | AA32: =Y32*Z32 -> 186 | AB32: =G32+J32+M32+P32+S32+V32+Y32 -> 62 | AC32: =I32+L32+O32+R32+U32+X32+234 -> 14854 | AD32: 46002 | AH32: нет в потребности
A33: 30 | B33: Стрельба из лука | D33: 46217 | E33: 46221 | F33: г. Сочи | G33: 1 | H33: 3400 | I33: =G33*H33 -> 3400 | J33: 1 | K33: 3000 | L33: =J33*K33 -> 3000 | M33: 1 | N33: 2900 | O33: =M33*N33 -> 2900 | P33: 20 | Q33: 190 | R33: =P33*Q33 -> 3800 | S33: 20 | T33: 190 | U33: =S33*T33 -> 3800 | V33: 20 | W33: 190 | X33: =V33*W33 -> 3800 | Y33: 33 | Z33: 6 | AA33: =Y33*Z33 -> 198 | AB33: =G33+J33+M33+P33+S33+V33+Y33 -> 96 | AC33: =I33+L33+O33+R33+U33+X33+234 -> 20934 | AD33: 46002
A34: 31 | B34: Триатлон | D34: 46196 | E34: 46199 | F34: Курганинский район, г.Курганинск | G34: 1 | H34: 3400 | I34: =G34*H34 -> 3400 | J34: 1 | K34: 3000 | L34: =J34*K34 -> 3000 | M34: 1 | N34: 2900 | O34: =M34*N34 -> 2900 | P34: 6 | Q34: 190 | R34: =P34*Q34 -> 1140 | S34: 6 | T34: 190 | U34: =S34*T34 -> 1140 | V34: 6 | W34: 190 | X34: =V34*W34 -> 1140 | Y34: 21 | Z34: 6 | AA34: =Y34*Z34 -> 126 | AB34: =G34+J34+M34+P34+S34+V34+Y34 -> 42 | AC34: =I34+L34+O34+R34+U34+X34+234 -> 12954 | AD34: 46002 | AG34: в потребности без кубков
A35: 32 | B35: Тяжелая атлетика (юниоры, юниорки) | D35: 46099 | E35: 46103 | F35: г. Краснодар | G35: 1 | H35: 3400 | I35: =G35*H35 -> 3400 | J35: 1 | K35: 3000 | L35: =J35*K35 -> 3000 | M35: 1 | N35: 2900 | O35: =M35*N35 -> 2900 | P35: 20 | Q35: 190 | R35: =P35*Q35 -> 3800 | S35: 20 | T35: 190 | U35: =S35*T35 -> 3800 | V35: 20 | W35: 190 | X35: =V35*W35 -> 3800 | Y35: 63 | Z35: 6 | AA35: =Y35*Z35 -> 378 | AB35: =G35+J35+M35+P35+S35+V35+Y35 -> 126 | AC35: =I35+L35+O35+R35+U35+X35+AA35 -> 21078 | AD35: 46002
A36: 33 | B36: Футбол (юноши) | D36: 46191 | E36: 46194 | F36: г. Краснодар | P36: 19 | Q36: 190 | R36: =P36*Q36 -> 3610 | S36: 19 | T36: 190 | U36: =S36*T36 -> 3610 | V36: 19 | W36: 190 | X36: =V36*W36 -> 3610 | Y36: 57 | Z36: 6 | AA36: =Y36*Z36 -> 342 | AB36: =G36+J36+M36+P36+S36+V36+6 -> 63 | AC36: =I36+L36+O36+R36+U36+X36+510 -> 11340 | AD36: 46002
A37: 34 | B37: Футбол (девушки) | D37: 46082 | E37: 46173 | F37: г. Краснодар | P37: 19 | Q37: 190 | R37: =P37*Q37 -> 3610 | S37: 19 | T37: 190 | U37: =S37*T37 -> 3610 | V37: 19 | W37: 190 | X37: =V37*W37 -> 3610 | Y37: 57 | Z37: 6 | AA37: =Y37*Z37 -> 342 | AB37: =G37+J37+M37+P37+S37+V37+6 -> 63 | AC37: =I37+L37+O37+R37+U37+X37+510 -> 11340 | AD37: 46002
A38: 35 | B38: Фехтование | D38: 46161 | E38: 46164 | F38: г. Краснодар | G38: 1 | H38: 3400 | I38: =G38*H38 -> 3400 | J38: 1 | K38: 3000 | L38: =J38*K38 -> 3000 | M38: 1 | N38: 2900 | O38: =M38*N38 -> 2900 | P38: 6 | Q38: 190 | R38: =P38*Q38 -> 1140 | S38: 6 | T38: 190 | U38: =S38*T38 -> 1140 | V38: 6 | W38: 190 | X38: =V38*W38 -> 1140 | Y38: 18 | Z38: 6 | AA38: =Y38*Z38 -> 108 | AB38: =G38+J38+M38+P38+S38+V38+Y38 -> 39 | AC38: =I38+L38+O38+R38+U38+X38+AA38 -> 12828 | AD38: 46002 | AE38: 46002 | AF38: 46002
A39: 36 | B39: Художественная гимнастика | D39: 46135 | E39: 46139 | F39: по назначанию | G39: 1 | H39: 3400 | I39: =G39*H39 -> 3400 | J39: 1 | K39: 3000 | L39: =J39*K39 -> 3000 | M39: 1 | N39: 2900 | O39: =M39*N39 -> 2900 | P39: 17 | Q39: 190 | R39: =P39*Q39 -> 3230 | S39: 17 | T39: 190 | U39: =S39*T39 -> 3230 | V39: 17 | W39: 190 | X39: =V39*W39 -> 3230 | Y39: 54 | Z39: 6 | AA39: =Y39*Z39 -> 324 | AB39: =G39+J39+M39+P39+S39+V39+Y39 -> 108 | AC39: =I39+L39+O39+R39+U39+X39+186 -> 19176 | AD39: 46002 | AE39: 46002 | AF39: 46002
A40: 37 | B40: Хоккей на траве (юноши) | D40: 46103 | E40: 46107 | F40: г.Крымск | G40: 1 | H40: 3400 | I40: =G40*H40 -> 3400 | J40: 1 | K40: 3000 | L40: =J40*K40 -> 3000 | M40: 1 | N40: 2900 | O40: =M40*N40 -> 2900 | P40: 19 | Q40: 190 | R40: =P40*Q40 -> 3610 | S40: 19 | T40: 190 | U40: =S40*T40 -> 3610 | V40: 19 | W40: 190 | X40: =V40*W40 -> 3610 | Y40: 60 | Z40: 6 | AA40: =Y40*Z40 -> 360 | AB40: 60 | AC40: =I40+L40+O40+R40+U40+X40+186 -> 20316 | AD40: 46002 | AE40: 46002 | AF40: 46002
A41: 38 | B41: Хоккей на траве (девушки) | D41: 46108 | E41: 46112 | F41: г.Крымск | G41: 1 | H41: 3400 | I41: =G41*H41 -> 3400 | J41: 1 | K41: 3000 | L41: =J41*K41 -> 3000 | M41: 1 | N41: 2900 | O41: =M41*N41 -> 2900 | P41: 19 | Q41: 190 | R41: =P41*Q41 -> 3610 | S41: 19 | T41: 190 | U41: =S41*T41 -> 3610 | V41: 19 | W41: 190 | X41: =V41*W41 -> 3610 | Y41: 60 | Z41: 6 | AA41: =Y41*Z41 -> 360 | AB41: 60 | AC41: =I41+L41+O41+R41+U41+X41+186 -> 20316 | AD41: 46002 | AE41: 46002 | AF41: 46002
A42: 39 | B42: Шахматы | D42: 46120 | E42: 46125 | F42: г.Краснодар | G42: 1 | H42: 3400 | I42: =G42*H42 -> 3400 | J42: 1 | K42: 3000 | L42: =J42*K42 -> 3000 | M42: 1 | N42: 2900 | O42: =M42*N42 -> 2900 | P42: 4 | Q42: 190 | R42: =P42*Q42 -> 760 | S42: 4 | T42: 190 | U42: =S42*T42 -> 760 | V42: 4 | W42: 190 | X42: =V42*W42 -> 760 | Y42: 15 | Z42: 6 | AA42: =Y42*Z42 -> 90 | AB42: =G42+J42+M42+P42+S42+V42+Y42 -> 30 | AC42: =I42+L42+O42+R42+U42+X42 -> 11580 | AD42: 46002 | AE42: 46002 | AF42: 46002
A43: 40 | B43: Настольльный теннис | D43: 46161 | E43: 46166 | F43: г.Славянск-на-Кубани | G43: 4 | H43: 3400 | I43: =G43*H43 -> 13600 | J43: 4 | K43: 3000 | L43: =J43*K43 -> 12000 | M43: 4 | N43: 2900 | O43: =M43*N43 -> 11600 | P43: 8 | Q43: 190 | R43: =P43*Q43 -> 1520 | S43: 8 | T43: 190 | U43: =S43*T43 -> 1520 | V43: 8 | W43: 190 | X43: =V43*W43 -> 1520 | Y43: 42 | Z43: 6 | AA43: =Y43*Z43 -> 252 | AB43: =G43+J43+M43+P43+S43+V43+Y43 -> 78 | AC43: =I43+L43+O43+R43+U43+X43 -> 41760 | AD43: 46002 | AE43: 46002 | AF43: 46002
A44: 41 | B44: Гребля на байдарках и каноэ | D44: 46190 | E44: 46192 | F44: г. Краснодар | G44: 1 | H44: 3400 | I44: =G44*H44 -> 3400 | J44: 1 | K44: 3000 | L44: =J44*K44 -> 3000 | M44: 1 | N44: 2900 | O44: =M44*N44 -> 2900 | P44: 30 | Q44: 190 | R44: =P44*Q44 -> 5700 | S44: 30 | T44: 190 | U44: =S44*T44 -> 5700 | V44: 30 | W44: 190 | X44: =V44*W44 -> 5700 | Y44: 93 | Z44: 6 | AA44: =Y44*Z44 -> 558 | AB44: =G44+J44+M44+P44+S44+V44+Y44 -> 186 | AC44: =I44+L44+O44+R44+U44+X44 -> 26400 | AD44: 46002 | AE44: 46002 | AF44: 46002
A45: 42 | B45: Плавание | D45: 46084 | E45: 46087 | F45: г. Краснодар | G45: 1 | H45: 3400 | I45: =G45*H45 -> 3400 | J45: 1 | K45: 3000 | L45: =J45*K45 -> 3000 | M45: 1 | N45: 2900 | O45: =M45*N45 -> 2900 | P45: 32 | Q45: 190 | R45: =P45*Q45 -> 6080 | S45: 32 | T45: 190 | U45: =S45*T45 -> 6080 | V45: 32 | W45: 190 | X45: =V45*W45 -> 6080 | Y45: 99 | Z45: 6 | AA45: =Y45*Z45 -> 594 | AB45: =G45+J45+M45+P45+S45+V45+Y45 -> 198 | AC45: =I45+L45+O45+R45+U45+X45 -> 27540 | AD45: 46002 | AE45: 46002 | AF45: 46002
A46: 43 | B46: Спортивное ориентирование | D46: 46122 | E46: 46125 | F46: ст-ца Выселки | G46: 1 | H46: 3400 | I46: =G46*H46 -> 3400 | J46: 1 | K46: 3000 | L46: =J46*K46 -> 3000 | M46: 1 | N46: 2900 | O46: =M46*N46 -> 2900 | P46: 4 | Q46: 190 | R46: =P46*Q46 -> 760 | S46: 4 | T46: 190 | U46: =S46*T46 -> 760 | V46: 4 | W46: 190 | X46: =V46*W46 -> 760 | Y46: 15 | Z46: 6 | AA46: =Y46*Z46 -> 90 | AB46: =G46+J46+M46+P46+S46+V46+Y46 -> 30 | AC46: =I46+L46+O46+R46+U46+X46 -> 11580 | AD46: 46002 | AE46: 46002 | AF46: 46002 | AH46: нет в потребности
A47: 44 | B47: Тхэквондо ВТФ | D47: 46121 | E47: 46123 | F47: Тихорецкий район, ст-ца Архангелькая | G47: 1 | H47: 3400 | I47: =G47*H47 -> 3400 | J47: 1 | K47: 3000 | L47: =J47*K47 -> 3000 | M47: 1 | N47: 2900 | O47: =M47*N47 -> 2900 | P47: 28 | Q47: 190 | R47: =P47*Q47 -> 5320 | S47: 28 | T47: 190 | U47: =S47*T47 -> 5320 | V47: 56 | W47: 190 | X47: =V47*W47 -> 10640 | Y47: 112 | Z47: 6 | AA47: =Y47*Z47 -> 672 | AB47: =G47+J47+M47+P47+S47+V47+Y47 -> 227 | AC47: =I47+L47+O47+R47+U47+X47 -> 30580 | AD47: 46002 | AE47: 46002 | AF47: 46002 | AH47: нет в потребности
A48: 45 | B48: Инвалиды Кубани | D48: по назначению | E48: по назначению | F48: по назначанию | G48: 8 | H48: 3400 | I48: =G48*H48 -> 27200 | J48: 8 | K48: 3000 | L48: =J48*K48 -> 24000 | M48: 8 | N48: 2900 | O48: =M48*N48 -> 23200 | P48: 102 | Q48: 190 | R48: =P48*Q48 -> 19380 | S48: 102 | T48: 190 | U48: =S48*T48 -> 19380 | V48: 102 | W48: 190 | X48: =V48*W48 -> 19380 | Y48: 330 | Z48: 6 | AA48: =Y48*Z48 -> 1980 | AB48: =G48+J48+M48+P48+S48+V48+Y48 -> 660 | AC48: =I48+L48+O48+R48+U48+X48+1980 -> 134520 | AG48: нет положения
A49: 46 | B49: Самбо (юноши) | D49: 46041 | E49: 46043 | F49: г. Армавир | G49: 1 | H49: 3400 | I49: =G49*H49 -> 3400 | J49: 1 | K49: 3000 | L49: =J49*K49 -> 3000 | M49: 1 | N49: 2900 | O49: =M49*N49 -> 2900 | P49: 9 | Q49: 190 | R49: =P49*Q49 -> 1710 | S49: 9 | T49: 190 | U49: =S49*T49 -> 1710 | V49: 18 | W49: 190 | X49: =V49*W49 -> 3420 | Y49: 39 | Z49: 6 | AA49: =Y49*Z49 -> 234 | AB49: =G49+J49+M49+P49+S49+V49+Y49 -> 78 | AC49: =I49+L49+O49+R49+U49+X49+234 -> 16374 | AD49: 46002
A50: 47 | B50: Самбо (девушки) | D50: 46041 | E50: 46043 | F50: г. Армавир | G50: 1 | H50: 3400 | I50: =G50*H50 -> 3400 | J50: 1 | K50: 3000 | L50: =J50*K50 -> 3000 | M50: 1 | N50: 2900 | O50: =M50*N50 -> 2900 | P50: 9 | Q50: 190 | R50: =P50*Q50 -> 1710 | S50: 9 | T50: 190 | U50: =S50*T50 -> 1710 | V50: 18 | W50: 190 | X50: =V50*W50 -> 3420 | Y50: 39 | Z50: 6 | AA50: =Y50*Z50 -> 234 | AB50: =G50+J50+M50+P50+S50+V50+Y50+35 -> 113 | AC50: =I50+L50+O50+R50+U50+X50+210 -> 16350 | AD50: 46002
A51: 48 | B51: Спортивная акробатика | D51: 46036 | E51: 46039 | F51: г. Краснодар | G51: 1 | H51: 3400 | I51: =G51*H51 -> 3400 | J51: 1 | K51: 3000 | L51: =J51*K51 -> 3000 | M51: 1 | N51: 2900 | O51: =M51*N51 -> 2900 | P51: 13 | Q51: 190 | R51: =P51*Q51 -> 2470 | S51: 13 | T51: 190 | U51: =S51*T51 -> 2470 | V51: 13 | W51: 190 | X51: =V51*W51 -> 2470 | Y51: 52 | Z51: 6 | AA51: =Y51*Z51 -> 312 | AB51: =G51+J51+M51+P51+S51+V51+Y51+35 -> 129 | AC51: =I51+L51+O51+R51+U51+X51+210 -> 16920 | AD51: 46002 | AL51: в потребности нет
A52: 49 | B52: Бокс | D52: 46062 | E52: 46070 | F52: г.Крымск | H52: 3400 | I52: =G52*H52 -> 0 | K52: 3000 | L52: =J52*K52 -> 0 | N52: 2900 | O52: =M52*N52 -> 0 | P52: 26 | Q52: 190 | R52: =P52*Q52 -> 4940 | S52: 26 | T52: 190 | U52: =S52*T52 -> 4940 | V52: 52 | W52: 190 | X52: =V52*W52 -> 9880 | Y52: 107 | Z52: 6 | AA52: =Y52*Z52 -> 642 | AB52: =G52+J52+M52+P52+S52+V52+Y52 -> 211 | AC52: =I52+L52+O52+R52+U52+X52+234 -> 19994 | AD52: 11.12.2025 в положении нет кубков
B53: ИТОГО | G53: 57 | I53: =G53*H48 -> 193800 | J53: 57 | L53: =J53*K48 -> 171000 | M53: 57 | O53: =M53*N48 -> 165300 | P53: 784 | R53: =P53*Q48 -> 148960 | S53: 784 | U53: =S53*T48 -> 148960 | V53: 926 | X53: =V53*W48 -> 175940 | Y53: 2652 | AA53: =Y53*Z48 -> 15912 | AC53: =I53+L53+O53+R53+U53+X53+AA53 -> 1019872

Sheet ЦРС СПОРТ ОТДЕЛ
A1: Информация о потребности в наградном материале на 2026 год
A3: № п/п | B3: Наименование мероприятия | C3: Возраст спортсменов | D3: Дата проведения (начало мероприятия) | E3: Дата проведения (конец мероприятия) | F3: Место проведения | G3: Количество кубков | J3: Количество медалей | M3: Грамоты
G4: 1 место | H4: 2 место | I4: 3 место | J4: 1 место | K4: 2 место | L4: 3 место | M4: Количество, шт.
A5: 1 | B5: XXXV Универсиада Кубани среди высших учебных заведений | C5: 17-25 лет | D5: январь | E5: май | F5: г. Краснодар | G5: 20 | H5: 20 | I5: 20 | J5: 286 | K5: 286 | L5: 412 | M5: 1128
B6: 3-5 февраля | C6: 17-19 февраля | D6: 24-27 февраля | E6: 03-05 марта | F6: 17-18 марта | G6: 07-09 апреля | H6: 21-23 апреля | I6: 09-12 мая
A7: 2 | B7: XVII спартакиада среди сборных команд органов исполнительной власти и структурных подразделений администрации Краснодарского края | C7: 18 лет и старше | D7: январь | E7: декабрь | G7: 19 | H7: 19 | I7: 19 | J7: 140 | K7: 140 | L7: 140 | M7: 492
A8: 3 | B8: XXXIII Сельские спортивные игры Кубани | C8: 18 лет и старше | D8: январь | E8: июнь | G8: 20 | H8: 20 | I8: 20 | J8: 140 | K8: 140 | L8: 140 | M8: 500
A9: 4 | B9: Спартакиада трудящихся Краснодарского края | C9: 25 лет и старше | D9: август | E9: декабрь | G9: 44 | H9: 44 | I9: 44 | J9: 280 | K9: 280 | L9: 280 | M9: 972
A10: 5 | B10: Весенний забег «Парковые тропы» | C10: 4года и сташе | D10: март | E10: март | J10: 54 | K10: 54 | L10: 54 | M10: 162
A11: 6 | B11: Краевые семейные спортивные игры «Стартуем вместе» | C11: 12 лет и старше | D11: май | E11: май | G11: 2 | H11: 2 | I11: 2 | J11: 26 | K11: 26 | L11: 26 | M11: 36
A12: 7 | B12: Всекубанская эстафета «Спортсмены Кубани – в ознаменование Победы в Великой Отечественной войне 1941-1945 годов» | C12: 4года и сташе | D12: июнь | E12: июнь | J12: 118 | K12: 118 | L12: 118 | M12: 354
A13: 8 | B13: Спартакиада пенсионеров Краснодарского края 2026 года | C13: 55 и старше | D13: май | E13: май | G13: 1 | H13: 1 | I13: 1 | J13: 16 | K13: 16 | L13: 16 | M13: 51
A14: 9 | B14: Краевые соревнования среди ветеранов физической культуры и спорта Кубани, посвящённые Всероссийскому Дню физкультурника | C14: 35 лет и старше | D14: июль | E14: август | J14: 24 | K14: 24 | L14: 24 | M14: 72
A15: 10 | B15: Краевой день бега «Кросс Нации» в рамках Всероссийского дня бега «Кросс Нации» | C15: 4года и сташе | D15: сентябрь | E15: сентябрь | J15: 118 | K15: 118 | L15: 118 | M15: 354
A16: 11 | B16: Краевые соревнования по городошному спорту среди ветеранов физической культуры и спорта Кубани | C16: 35 лет и старше | D16: октябрь | E16: октябрь | J16: 6 | K16: 6 | L16: 6 | M16: 18
A17: 12 | B17: Краевой фестиваль женского спорта «Красота. Грация. Идеал.» | C17: 25 лет и старше | D17: октябрь | E17: октябрь | G17: 1 | H17: 1 | I17: 1 | J17: 30 | K17: 30 | L17: 30 | M17: 97
A18: 13 | B18: Ночной забег «Кубанская миля» | C18: 8 лет и сташе | D18: декабрь | E18: декабрь | J18: 54 | K18: 54 | L18: 54 | M18: 162
B19: ИТОГО | G19: =SUM(G5:G18) -> 107 | H19: =SUM(H5:H18) -> 107 | I19: =SUM(I5:I18) -> 107 | J19: =SUM(J5:J18) -> 1292 | K19: =SUM(K5:K18) -> 1292 | L19: =SUM(L5:L18) -> 1418 | M19: =SUM(M5:M18) -> 4398
B20: За счет средств субсидии на иные цели
A21: № п/п | B21: Наименование мероприятия | C21: Возраст спортсменов | D21: Дата проведения (начало мероприятия) | E21: Дата проведения (конец мероприятия) | F21: Место проведения | G21: Количество кубков | J21: Количество медалей | M21: Грамоты | O21: 2026
G22: 1 место | H22: 2 место | I22: 3 место | J22: 1 место | K22: 2 место | L22: 3 место | M22: Количество, шт.
A23: 1 | B23: Краевые спортивные игры «Спорт против наркотиков» | C23: 12-15 лет | D23: апрель | E23: июнь | F23: МО Краснодарского кря | J23: 160 | K23: 160 | L23: 160 | M23: 486
A24: 2 | B24: государственная программа Краснодарского края «Доступная среда» | G24: =SUM(G25:G33) -> 12 | H24: =SUM(H25:H33) -> 12 | I24: =SUM(I25:I33) -> 12 | J24: =SUM(J25:J33) -> 218 | K24: =SUM(K25:K33) -> 218 | L24: =SUM(L25:L33) -> 218 | M24: =SUM(M25:M33) -> 840
A25: 2.1 | B25: Краевой фестиваль шахмат среди инвалидов по зрению | C25: 14 лет и старше | D25: по назначению | E25: по назначению | F25: по назначению | J25: 2 | K25: 2 | L25: 2 | M25: 6
A26: 2.2 | B26: Краевой фестиваль шашек среди инвалидов по зрению | C26: 14 лет и старше | D26: по назначению | E26: по назначению | F26: по назначению | J26: 4 | K26: 4 | L26: 4 | M26: 12
A27: 2.3 | B27: Спартакиада инвалидов Кубани | C27: 12-60 лет | D27: по назначению | E27: по назначению | F27: по назначению | G27: 8 | H27: 8 | I27: 8 | J27: 102 | K27: 102 | L27: 102 | M27: 330
A28: 2.4 | B28: Краевой спортивный конкурс среди инвалидов по зрению «Современная мозаика» | C28: 18 лет и старше | D28: по назначению | E28: по назначению | F28: по назначению | G28: 1 | H28: 1 | I28: 1 | J28: 21 | K28: 21 | L28: 21 | M28: 75
A29: 2.5 | B29: Краевой фестиваль по шоудауну среди инвалидов по зрению | C29: 14 лет и старше | D29: по назначению | E29: по назначению | F29: по назначению | J29: 2 | K29: 2 | L29: 2 | M29: 6
A30: 2.6 | B30: Спортивный фестиваль для детей-инвалидов и их сверстников, не имеющих инвалидности, в возрасте от 12 до 16 лет | C30: 12-16 лет | D30: по назначению | E30: по назначению | F30: по назначению | G30: 1 | H30: 1 | I30: 1 | J30: 20 | K30: 20 | L30: 20 | M30: 51
A31: 2.7 | B31: Краевые спортивные соревнования для детей-инвалидов с поражением опорно-двигательного аппарата | C31: до 18 лет | D31: по назначению | E31: по назначению | F31: по назначению | J31: 18 | K31: 18 | L31: 18 | M31: 54
A32: 2.8 | B32: Краевой спортивный фестиваль среди инвалидов с нарушением слуха № 2 | C32: 12-17 лет | D32: по назначению | E32: по назначению | F32: по назначению | G32: 1 | H32: 1 | I32: 1 | J32: 15 | K32: 15 | L32: 15 | M32: 186
A33: 2.9 | B33: Краевой спортивный фестиваль среди инвалидов с нарушением слуха | C33: 18 лет и старше | D33: по назначению | E33: по назначению | F33: по назначению | G33: 1 | H33: 1 | I33: 1 | J33: 34 | K33: 34 | L33: 34 | M33: 120
A34: 3 | B34: Всекубанский турнир по футболу среди детских дворовых команд на Кубок Губернатора Краснодарского края | C34: 10-15 лет | D34: июнь | E34: август | F34: МО Краснодарского кря | G34: 3 | H34: 3 | I34: 3 | J34: 30 | K34: 30 | L34: 30 | M34: 693
B35: ИТОГО ПО СУБСИДИЯМ | G35: =G23+G24+G34 -> 15 | H35: =H23+H24+H34 -> 15 | I35: =I23+I24+I34 -> 15 | J35: =J24+J23+J34 -> 408 | K35: =K23+K24+K34 -> 408 | L35: =L23+L24+L34 -> 408 | M35: =M23+M24+M34 -> 2019

Sheet СМЕТА на 2026 год
A2: СМЕТА
G3: расходов на обеспечение наградной атрибутикой
D4: Источник финансирования | F4: за счет субсидий на финансовое обеспечение выполнения государственного задания на оказание государственных услуг (выполнение работ) в 2026 году
F5: работа "Реализация календарных планов официальных физкультурных и спортивных мероприятий"
A7: № п/п | B7: Ответственный за проведение мероприятия | C7: Вид спорта | D7: Наименование мероприятия | E7: Вид соревнований | F7: Возраст | G7: Дата проведения (начало мероприятия) | H7: Дата проведения (конец мероприятия) | I7: Место проведения | J7: Количество кубков | S7: Количество медалей | AB7: Грамоты | AF7: 27 | AG7: Всего по виду спорта
J8: 1 место Кол-во, шт. | K8: Стоимость 1 шт. | L8: Итого | M8: 2 место Кол-во, шт. | N8: Стоимость 1 шт. | O8: Итого | P8: 3 место Кол-во, шт. | Q8: Стоимость 1 шт. | R8: Итого | S8: 1 место Кол-во, шт. | T8: Стоимость 1 шт. | U8: Итого | V8: 2 место Кол-во, шт. | W8: Стоимость 1 шт. | X8: Итого | Y8: 3 место Количество, шт. | Z8: Стоимость 1 | AA8: Итого | AB8: Кол-во, шт. | AC8: Стоимость 1 шт. | AD8: Итого | AF8: Сумма
A9: 4 | B9: Физкультурное мероприятие "Всекубанский казачий слет "Готов к труду и обороне" | C9: КС | D9: от 20 до 49 лет | E9: 46305 | F9: 46305 | G9: Краснодарский край | H9: 1 | I9: 3400 | J9: =H9*I9 -> 3400 | K9: 1 | L9: 3000 | M9: =K9*L9 -> 3000 | N9: 1 | O9: 2900 | P9: =N9*O9 -> 2900 | Q9: 4 | R9: 190 | S9: =Q9*R9 -> 760 | T9: 4 | U9: 190 | V9: =T9*U9 -> 760 | W9: 4 | X9: 190 | Y9: =W9*X9 -> 760 | Z9: 15 | AA9: 6 | AB9: =Z9*AA9 -> 90 | AC9: =H9+K9+N9+Q9+T9+W9+Z9 -> 30 | AD9: =J9+M9+P9+S9+V9+Y9+AB9 -> 11670
A10: 5 | B10: Краевой фестиваль чемпионов Всероссийского физкультурно-спортивного комплекса "Готов к труду и обороне" | C10: КС | D10: от 18 до 49 | E10: 46291 | F10: 46291 | G10: Краснодарский край | H10: 1 | I10: 3400 | J10: =H10*I10 -> 3400 | K10: 1 | L10: 3000 | M10: =K10*L10 -> 3000 | N10: 1 | O10: 2900 | P10: =N10*O10 -> 2900 | Q10: 5 | R10: 190 | S10: =Q10*R10 -> 950 | T10: 5 | U10: 190 | V10: =T10*U10 -> 950 | W10: 5 | X10: 190 | Y10: =W10*X10 -> 950 | Z10: 15 | AA10: 6 | AB10: =Z10*AA10 -> 90 | AC10: =H10+K10+N10+Q10+T10+W10+Z10 -> 33 | AD10: =J10+M10+P10+S10+V10+Y10+AB10 -> 12240
A11: 6 | B11: Краевой день бега "Кросс Нации" в рамках Всероссийского дня бега "Кросс Нации" | C11: КС | D11: согласно положению | E11: сентябрь | F11: сентябрь | G11: согласно положению | Q11: 118 | R11: 190 | S11: =Q11*R11 -> 22420 | T11: 118 | U11: 190 | V11: =T11*U11 -> 22420 | W11: 118 | X11: 190 | Y11: =W11*X11 -> 22420 | Z11: 354 | AA11: 6 | AB11: =Z11*AA11 -> 2124 | AC11: =H11+K11+N11+Q11+T11+W11+Z11 -> 708 | AD11: =J11+M11+P11+S11+V11+Y11+AB11 -> 69384
A12: 7 | B12: Краевые соревнования по городошному спорту среди ветеранов физической культуры и спорта Кубани | C12: КС | D12: 35 лет и старше | E12: октябрь | F12: октябрь | G12: согласно положению | Q12: 6 | R12: 190 | S12: =Q12*R12 -> 1140 | T12: 6 | U12: 190 | V12: =T12*U12 -> 1140 | W12: 6 | X12: 190 | Y12: =W12*X12 -> 1140 | Z12: 18 | AA12: 6 | AB12: =Z12*AA12 -> 108 | AC12: =H12+K12+N12+Q12+T12+W12+Z12 -> 36 | AD12: =J12+M12+P12+S12+V12+Y12+AB12 -> 3528
A13: 8 | B13: Всекубанская эстафета «Спортсмены Кубани – в ознаменование Победы в Великой Отечественной войне 1941-1945 годов» | C13: КС | D13: согласно положению | E13: июнь | F13: июнь | G13: согласно положению | Q13: 118 | R13: 190 | S13: =Q13*R13 -> 22420 | T13: 118 | U13: 190 | V13: =T13*U13 -> 22420 | W13: 118 | X13: 190 | Y13: =W13*X13 -> 22420 | Z13: 354 | AA13: 6 | AB13: =Z13*AA13 -> 2124 | AC13: =H13+K13+N13+Q13+T13+W13+Z13 -> 708 | AD13: =J13+M13+P13+S13+V13+Y13+AB13 -> 69384
B14: ФИЗКУЛЬТУРНЫЕ МЕРОПРИЯТИЯ
A15: 9 | B15: XXXV Универсиада Кубани среди высших учебных заведений (по видам спорта) | C15: КС | D15: юноши, девушки 1999 - 2006 г.р. | E15: январь | F15: май | G15: г. Краснодар | H15: 11 | I15: 3400 | J15: =H15*I15 -> 37400 | K15: 11 | L15: 3000 | M15: =K15*L15 -> 33000 | N15: 11 | O15: 2900 | P15: =N15*O15 -> 31900 | Q15: 159 | R15: 190 | S15: =Q15*R15 -> 30210 | T15: 159 | U15: 190 | V15: =T15*U15 -> 30210 | W15: 257 | X15: 190 | Y15: =W15*X15 -> 48830 | Z15: 610 | AA15: 6 | AB15: =Z15*AA15 -> 3660 | AC15: =H15+K15+N15+Q15+T15+W15+Z15 -> 1218 | AD15: =J15+M15+P15+S15+V15+Y15+AB15 -> 215210
A16: 10 | B16: XVII Спартакиада среди сборных команд органов исполнительной власти и структурных подразделений администрации Краснодарского края (по видам спорта) | C16: КС | D16: 18 лет и старше | E16: февраль | F16: декабрь | G16: г. Краснодар | H16: 21 | I16: 3400 | J16: =H16*I16 -> 71400 | K16: 21 | L16: 3000 | M16: =K16*L16 -> 63000 | N16: 21 | O16: 2900 | P16: =N16*O16 -> 60900 | Q16: 149 | R16: 190 | S16: =Q16*R16 -> 28310 | T16: 149 | U16: 190 | V16: =T16*U16 -> 28310 | W16: 149 | X16: 190 | Y16: =W16*X16 -> 28310 | Z16: 522 | AA16: 6 | AB16: =Z16*AA16 -> 3132 | AC16: =H16+K16+N16+Q16+T16+W16+Z16 -> 1032 | AD16: =J16+M16+P16+S16+V16+Y16+AB16 -> 283362
A17: 11 | B17: XXXIII Сельские спортивные игры Кубани | C17: КС | D17: мужчины, женщины 18 лет и старше | E17: 46037 | F17: 46203 | G17: муниципальные образования Краснодарского края | H17: 20 | I17: 3400 | J17: =H17*I17 -> 68000 | K17: 20 | L17: 3000 | M17: =K17*L17 -> 60000 | N17: 20 | O17: 2900 | P17: =N17*O17 -> 58000 | Q17: 116 | R17: 190 | S17: =Q17*R17 -> 22040 | T17: 116 | U17: 190 | V17: =T17*U17 -> 22040 | W17: 116 | X17: 190 | Y17: =W17*X17 -> 22040 | Z17: 408 | AA17: 6 | AB17: =Z17*AA17 -> 2448 | AC17: 500 | AD17: =J17+M17+P17+S17+V17+Y17+AB17 -> 254568
A18: 12 | B18: Турнир Краснодарского края по волейболу среди команд ветеранов в честь Дня Защитника Отечества | C18: КС | D18: мужчины 40 лет и старше, женщины 35 лет и старше | E18: 46065 | F18: 46068 | G18: п. Ольгинка (Туапсинский район) | H18: 6 | I18: 3400 | J18: =H18*I18 -> 20400 | K18: 6 | L18: 3000 | M18: =K18*L18 -> 18000 | N18: 6 | O18: 2900 | P18: =N18*O18 -> 17400 | Q18: 60 | R18: 190 | S18: =Q18*R18 -> 11400 | T18: 60 | U18: 190 | V18: =T18*U18 -> 11400 | W18: 60 | X18: 190 | Y18: =W18*X18 -> 11400 | Z18: 18 | AA18: 6 | AB18: =Z18*AA18 -> 108 | AC18: =H18+K18+N18+Q18+T18+W18+Z18 -> 216 | AD18: =J18+M18+P18+S18+V18+Y18+AB18 -> 90108 | AF18: 18
A19: 13 | B19: Краевой турнир по волейболу среди среди сильнейших команд ветеранов | C19: КС | D19: мужчины 40 лет и старше, женщины 35 лет и старше | E19: февраль | F19: февраль | G19: п. Ольгинка (Туапсинский район) | H19: 6 | I19: 3400 | J19: =H19*I19 -> 20400 | K19: 6 | L19: 3000 | M19: =K19*L19 -> 18000 | N19: 6 | O19: 2900 | P19: =N19*O19 -> 17400 | Q19: 60 | R19: 190 | S19: =Q19*R19 -> 11400 | T19: 60 | U19: 190 | V19: =T19*U19 -> 11400 | W19: 60 | X19: 190 | Y19: =W19*X19 -> 11400 | Z19: 20 | AA19: 6 | AB19: =Z19*AA19 -> 120 | AC19: =H19+K19+N19+Q19+T19+W19+Z19 -> 218 | AD19: =J19+M19+P19+S19+V19+Y19+AB19 -> 90120 | AF19: 18
A20: 14 | B20: Краевые соревнования по настольному теннису среди ветеранов физической культуры и спорта Кубани памяти МС МК ЗТР Г.М. Стрельникова | C20: КС | D20: мужчины 40-70+ лет, женщины 40-55+ лет | E20: март | F20: март | G20: согласно положению | Q20: 8 | R20: 190 | S20: =Q20*R20 -> 1520 | T20: 8 | U20: 190 | V20: =T20*U20 -> 1520 | W20: 16 | X20: 190 | Y20: =W20*X20 -> 3040 | Z20: 32 | AA20: 6 | AB20: =Z20*AA20 -> 192 | AC20: =H20+K20+N20+Q20+T20+W20+Z20 -> 64 | AD20: =J20+M20+P20+S20+V20+Y20+AB20 -> 6272 | AF20: 32
A21: 15 | B21: Краевой турнир по футболу среди смешанных детских команд (девочки и мальчики до 12 лет) I этап (региональный) | C21: КС | D21: девочки и мальчики до 12 лет | E21: 46113 | F21: 46142 | G21: г. Краснодар | H21: 1 | I21: 3400 | J21: =H21*I21 -> 3400 | K21: 1 | L21: 3000 | M21: =K21*L21 -> 3000 | N21: 1 | O21: 2900 | P21: =N21*O21 -> 2900 | Q21: 13 | R21: 190 | S21: =Q21*R21 -> 2470 | T21: 13 | U21: 190 | V21: =T21*U21 -> 2470 | W21: 13 | X21: 190 | Y21: =W21*X21 -> 2470 | Z21: 48 | AA21: 6 | AB21: =Z21*AA21 -> 288 | AC21: =H21+K21+N21+Q21+T21+W21+Z21 -> 90 | AD21: =J21+M21+P21+S21+V21+Y21+AB21 -> 16998 | AF21: 47
A22: 16 | B22: Краевой турнир по футболу "Кожаный мяч - Лига юных футболистов" II этап (региональный) | C22: КТ | D22: девочки и мальчики до 12, до 14 лет и до 16 лет, мальчики до 18 лет | E22: 46119 | F22: 46203 | G22: города и районы Краснодарского края, г. Краснодар | H22: 10 | I22: 3400 | J22: =H22*I22 -> 34000 | K22: 10 | L22: 3000 | M22: =K22*L22 -> 30000 | N22: 10 | O22: 2900 | P22: =N22*O22 -> 29000 | Q22: 143 | R22: 190 | S22: =Q22*R22 -> 27170 | T22: 143 | U22: 190 | V22: =T22*U22 -> 27170 | W22: 143 | X22: 190 | Y22: =W22*X22 -> 27170 | Z22: 520 | AA22: 6 | AB22: =Z22*AA22 -> 3120 | AC22: =H22+K22+N22+Q22+T22+W22+AA22 -> 465 | AD22: =J22+M22+P22+S22+V22+Y22+AB22 -> 177630 | AF22: 519
A23: 17 | B23: Краевой турнир по футболу "Кожаный мяч - детям" I этап (региональный) | C23: КТ | D23: мальчики до 10 лет | E23: 46266 | F23: 46295 | G23: г. Краснодар | H23: 1 | I23: 3400 | J23: =H23*I23 -> 3400 | K23: 1 | L23: 3000 | M23: =K23*L23 -> 3000 | N23: 1 | O23: 2900 | P23: =N23*O23 -> 2900 | Q23: 11 | R23: 190 | S23: =Q23*R23 -> 2090 | T23: 11 | U23: 190 | V23: =T23*U23 -> 2090 | W23: 11 | X23: 190 | Y23: =W23*X23 -> 2090 | Z23: 42 | AA23: 6 | AB23: =Z23*AA23 -> 252 | AC23: =H23+K23+N23+Q23+T23+W23+AA23 -> 42 | AD23: =J23+M23+P23+S23+V23+Y23+AB23 -> 15822 | AF23: 519
A24: 18 | B24: Физкультурное мероприятие по футболу среди мальчиков до 10 лет. Предварительный этап Финальный этап. | C24: КТ | D24: мальчики до 10 лет 2017г.р. | E24: 24.04.2026 23.05.2026 | F24: 17.05.2026 27.05.2026 | G24: п. Новомихайловский Туапсинский р-н | H24: 1 | I24: 3400 | J24: =H24*I24 -> 3400 | K24: 1 | L24: 3000 | M24: =K24*L24 -> 3000 | N24: 1 | O24: 2900 | P24: =N24*O24 -> 2900 | Q24: 15 | R24: 190 | S24: =Q24*R24 -> 2850 | T24: 15 | U24: 190 | V24: =T24*U24 -> 2850 | W24: 15 | X24: 190 | Y24: =W24*X24 -> 2850 | Z24: 53 | AA24: 6 | AB24: =Z24*AA24 -> 318 | AC24: =H24+K24+N24+Q24+T24+W24+Z24 -> 101 | AD24: =J24+M24+P24+S24+V24+Y24+AB24 -> 18168
A25: 19 | B25: Краевой турнир по футболу среди смешанных детских команд (девочки и мальчики до 10 лет) I этап (региональный) | C25: КС | D25: девочки и мальчики до 10 лет | E25: 46113 | F25: 46142 | G25: г. Краснодар | H25: 1 | I25: 3400 | J25: =H25*I25 -> 3400 | K25: 1 | L25: 3000 | M25: =K25*L25 -> 3000 | N25: 1 | O25: 2900 | P25: =N25*O25 -> 2900 | Q25: 11 | R25: 190 | S25: =Q25*R25 -> 2090 | T25: 11 | U25: 190 | V25: =T25*U25 -> 2090 | W25: 11 | X25: 190 | Y25: =W25*X25 -> 2090 | Z25: 42 | AA25: 6 | AB25: =Z25*AA25 -> 252 | AC25: =H25+K25+N25+Q25+T25+W25+Z25 -> 78 | AD25: =J25+M25+P25+S25+V25+Y25+AB25 -> 15822 | AF25: 41
A26: 20 | B26: Краевые семейные спортивные игры «Стартуем вместе» I этап, II этап | C26: КС | D26: согласно положению | E26: февраль | F26: июнь | G26: муниципальные образования Краснодарского края, г. Славянск-на -Кубани | H26: 2 | I26: 3400 | J26: =H26*I26 -> 6800 | K26: 2 | L26: 3000 | M26: =K26*L26 -> 6000 | N26: 2 | O26: 2900 | P26: =N26*O26 -> 5800 | Q26: 26 | R26: 190 | S26: =Q26*R26 -> 4940 | T26: 26 | U26: 190 | V26: =T26*U26 -> 4940 | W26: 26 | X26: 190 | Y26: =W26*X26 -> 4940 | Z26: 36 | AA26: 6 | AB26: =Z26*AA26 -> 216 | AC26: =H26+K26+N26+Q26+T26+W26+Z26 -> 120 | AD26: =J26+M26+P26+S26+V26+Y26+AB26 -> 33636
A27: 21 | B27: Спартакиада пенсионеров Краснодарского края 2026 года | C27: КС | D27: мужчины (60 лет и старше), женщины (55 лет и старше) | E27: май | F27: май | G27: г. Краснодар | H27: 1 | I27: 3400 | J27: =H27*I27 -> 3400 | K27: 1 | L27: 3000 | M27: =K27*L27 -> 3000 | N27: 1 | O27: 2900 | P27: =N27*O27 -> 2900 | Q27: 16 | R27: 190 | S27: =Q27*R27 -> 3040 | T27: 16 | U27: 190 | V27: =T27*U27 -> 3040 | W27: 16 | X27: 190 | Y27: =W27*X27 -> 3040 | Z27: 51 | AA27: 6 | AB27: =Z27*AA27 -> 306 | AC27: =H27+K27+N27+Q27+T27+W27+Z27 -> 102 | AD27: =J27+M27+P27+S27+V27+Y27+AB27 -> 18726
A28: 22 | B28: Первенство по волейболу среди мужских и женских команд ветеранов памяти В.П. Белянского | C28: ПК | D28: мужчины 40 лет и старше, женщины 35 лет и старше | E28: июнь | F28: июнь | G28: с. Ольгинка (Туапсинский район) | H28: 6 | I28: 3400 | J28: =H28*I28 -> 20400 | K28: 6 | L28: 3000 | M28: =K28*L28 -> 18000 | N28: 6 | O28: 2900 | P28: =N28*O28 -> 17400 | Q28: 60 | R28: 190 | S28: =Q28*R28 -> 11400 | T28: 60 | U28: 190 | V28: =T28*U28 -> 11400 | W28: 60 | X28: 190 | Y28: =W28*X28 -> 11400 | Z28: 20 | AA28: 6 | AB28: =Z28*AA28 -> 120 | AC28: =H28+K28+N28+Q28+T28+W28+Z28 -> 218 | AD28: =J28+M28+P28+S28+V28+Y28+AB28 -> 90120
A29: 23 | B29: Краевые соревнования среди ветеранов физической культуры и спорта Кубани, посвящённые Всероссийскому Дню физкультурника | C29: КС | D29: согласно положению | E29: июль | F29: июль | G29: согласно положению | Q29: 24 | R29: 190 | S29: =Q29*R29 -> 4560 | T29: 24 | U29: 190 | V29: =T29*U29 -> 4560 | W29: 24 | X29: 190 | Y29: =W29*X29 -> 4560 | Z29: 72 | AA29: 6 | AB29: =Z29*AA29 -> 432 | AC29: =H29+K29+N29+Q29+T29+W29+Z29 -> 144 | AD29: =J29+M29+P29+S29+V29+Y29+AB29 -> 14112
A30: 24 | B30: Весенний забег "Парковые тропы" | C30: ПК | D30: мальчики, девочки (4-15 лет), мужчины, женщины (16-61+) | E30: 46095 | F30: 46095 | G30: г. Краснодар | Q30: 42 | R30: 190 | S30: =Q30*R30 -> 7980 | T30: 42 | U30: 190 | V30: =T30*U30 -> 7980 | W30: 42 | X30: 190 | Y30: =W30*X30 -> 7980 | AA30: 6 | AB30: =Z30*AA30 -> 0 | AC30: =H30+K30+N30+Q30+T30+W30+Z30 -> 126 | AD30: =J30+M30+P30+S30+V30+Y30+AB30 -> 23940
A31: 25 | B31: Ночной забег- "Кубанская миля" | C31: КС | D31: 8 лет и старше | E31: декабрь | F31: декабрь | G31: по положению | Q31: 54 | R31: 190 | S31: =Q31*R31 -> 10260 | T31: 54 | U31: 190 | V31: =T31*U31 -> 10260 | W31: 54 | X31: 190 | Y31: =W31*X31 -> 10260 | Z31: 162 | AA31: 190 | AB31: =Z31*AA31 -> 30780 | AC31: =H31+K31+N31+Q31+T31+W31+Z31 -> 324 | AD31: =J31+M31+P31+S31+V31+Y31+AB31 -> 61560
A32: 26 | B32: Краевые соревнования среди школьников по самбо в рамках Всероссийской школьной лиги самбо на Кубок Губернатора Краснодарского края | C32: КГ | D32: 12-14 лет | E32: сентябрь | F32: ноябрь | G32: Краснодарский край | H32: 5 | I32: 7300 | J32: =H32*I32 -> 36500 | K32: 5 | L32: 6650 | M32: =K32*L32 -> 33250 | N32: 5 | O32: 6050 | P32: =N32*O32 -> 30250 | Q32: 72 | R32: 190 | S32: =Q32*R32 -> 13680 | T32: 72 | U32: 190 | V32: =T32*U32 -> 13680 | W32: 122 | X32: 190 | Y32: =W32*X32 -> 23180 | Z32: 695 | AA32: 6 | AB32: =Z32*AA32 -> 4170 | AC32: =H32+K32+N32+Q32+T32+W32+Z32 -> 976 | AD32: =J32+M32+P32+S32+V32+Y32+AB32 -> 154710
A33: 27 | B33: Краевой фестиваль "Я рисую самбо" | Z33: 30 | AA33: 6 | AB33: =Z33*AA33 -> 180 | AD33: =AB33 -> 180
A34: 28 | B34: Краевые спортивные игры "Спорт против наркотиков" I этап II этап | C34: КС | D34: 12-15 лет | E34: 12.05.2026 26.06.2026 | F34: 01.06.2026 26.06.2026 | G34: МО Краснодарского края | Q34: 24 | R34: 190 | S34: =Q34*R34 -> 4560 | T34: 24 | U34: 190 | V34: =T34*U34 -> 4560 | W34: 24 | X34: 190 | Y34: =W34*X34 -> 4560 | Z34: 72 | AA34: 6 | AB34: =Z34*AA34 -> 432 | AC34: =Q34+T34+W34+Z34 -> 144 | AD34: =S34+V34+Y34+AB34 -> 14112
A35: 29 | B35: 3 этап Краевых соревнований по пляжному волейболу среди команд ветеранов - "Кубок федерации 2026", посвященные Дню Победы в Великой Отечественной войне | C35: КС | D35: мужчины, женщины 35 лет и старше | E35: май | F35: май | G35: г. Краснодар | H35: 4 | I35: 3400 | J35: =H35*I35 -> 13600 | K35: 4 | L35: 3000 | M35: =K35*L35 -> 12000 | N35: 4 | O35: 2900 | P35: =N35*O35 -> 11600 | Q35: 8 | R35: 190 | S35: =Q35*R35 -> 1520 | T35: 8 | U35: 190 | V35: =T35*U35 -> 1520 | W35: 8 | X35: 190 | Y35: =W35*X35 -> 1520 | Z35: 40 | AA35: 6 | AB35: =Z35*AA35 -> 240 | AC35: =H35+K35+N35+Q35+T35+W35+Z35 -> 76 | AD35: =J35+M35+P35+S35+V35+Y35+AB35 -> 42000
A36: 30 | B36: 4 этап Краевых соревнований по пляжному волейболу среди команд ветеранов - "Кубок федерации 2026", посвященные Дню защиты детей | C36: КС | D36: мужчины, женщины 35 лет и старше | E36: май | G36: г. Краснодар | H36: 3 | I36: 3400 | J36: =H36*I36 -> 10200 | K36: 3 | L36: 3000 | M36: =K36*L36 -> 9000 | N36: 3 | O36: 2900 | P36: =N36*O36 -> 8700 | Q36: 6 | R36: 190 | S36: =Q36*R36 -> 1140 | T36: 6 | U36: 190 | V36: =T36*U36 -> 1140 | W36: 6 | X36: 190 | Y36: =W36*X36 -> 1140 | Z36: 30 | AA36: 6 | AB36: =Z36*AA36 -> 180 | AC36: =H36+K36+N36+Q36+T36+W36+Z36 -> 57 | AD36: =J36+M36+P36+S36+V36+Y36+AB36 -> 31500
A37: 31 | B37: 5 этап Краевых соревнований по пляжному волейболу среди команд любителей - "Кубок федерации 2026", посвященные Дню России | C37: КС | D37: 18+ | E37: июнь | F37: июнь | G37: г. Краснодар | H37: 3 | I37: 3400 | J37: =H37*I37 -> 10200 | K37: 3 | L37: 3000 | M37: =K37*L37 -> 9000 | N37: 3 | O37: 2900 | P37: =N37*O37 -> 8700 | Q37: 6 | R37: 190 | S37: =Q37*R37 -> 1140 | T37: 6 | U37: 190 | V37: =T37*U37 -> 1140 | W37: 6 | X37: 190 | Y37: =W37*X37 -> 1140 | Z37: 30 | AA37: 6 | AB37: =Z37*AA37 -> 180 | AC37: =H37+K37+N37+Q37+T37+W37+Z37 -> 57 | AD37: =J37+M37+P37+S37+V37+Y37+AB37 -> 31500
A38: 32 | B38: 6 этап Краевых соревнований по пляжному волейболу среди команд любителей - "Кубок федерации 2026" | C38: КС | D38: 15+ | E38: июнь | F38: июнь | G38: г. Краснодар | H38: 3 | I38: 3400 | J38: =H38*I38 -> 10200 | K38: 3 | L38: 3000 | M38: =K38*L38 -> 9000 | N38: 3 | O38: 2900 | P38: =N38*O38 -> 8700 | Q38: 6 | R38: 190 | S38: =Q38*R38 -> 1140 | T38: 6 | U38: 190 | V38: =T38*U38 -> 1140 | W38: 6 | X38: 190 | Y38: =W38*X38 -> 1140 | Z38: 30 | AA38: 6 | AB38: =Z38*AA38 -> 180 | AC38: =H38+K38+N38+Q38+T38+W38+Z38 -> 57 | AD38: =J38+M38+P38+S38+V38+Y38+AB38 -> 31500
A39: 33 | B39: 7 этап Краевых соревнований по пляжному волейболу среди команд любителей - "Кубок федерации 2026", посвященные Дню семьи, любви и вернности | C39: КС | D39: женщины, мужчины | E39: июль | F39: июль | G39: г. Краснодар | H39: 3 | I39: 3400 | J39: =H39*I39 -> 10200 | K39: 3 | L39: 3000 | M39: =K39*L39 -> 9000 | N39: 3 | O39: 2900 | P39: =N39*O39 -> 8700 | Q39: 6 | R39: 190 | S39: =Q39*R39 -> 1140 | T39: 6 | U39: 190 | V39: =T39*U39 -> 1140 | W39: 6 | X39: 190 | Y39: =W39*X39 -> 1140 | Z39: 30 | AA39: 6 | AB39: =Z39*AA39 -> 180 | AC39: =H39+K39+N39+Q39+T39+W39+Z39 -> 57 | AD39: =J39+M39+P39+S39+V39+Y39+AB39 -> 31500
A40: 34 | B40: 8 этап Краевых соревнований по пляжному волейболу среди команд любителей - "Кубок федерации 2026", посвященные Международному Дню Дружбы | C40: КС | D40: женщины, мужчины | E40: июль | F40: июль | G40: г. Краснодар | H40: 3 | I40: 3400 | J40: =H40*I40 -> 10200 | K40: 3 | L40: 3000 | M40: =K40*L40 -> 9000 | N40: 3 | O40: 2900 | P40: =N40*O40 -> 8700 | Q40: 6 | R40: 190 | S40: =Q40*R40 -> 1140 | T40: 6 | U40: 190 | V40: =T40*U40 -> 1140 | W40: 6 | X40: 190 | Y40: =W40*X40 -> 1140 | Z40: 30 | AA40: 6 | AB40: =Z40*AA40 -> 180 | AC40: =H40+K40+N40+Q40+T40+W40+Z40 -> 57 | AD40: =J40+M40+P40+S40+V40+Y40+AB40 -> 31500
A41: 35 | B41: 9 этап Краевых соревнований по пляжному волейболу среди команд любителей - "Кубок федерации 2026", посвященные Дню Физкультурника | C41: КС | D41: женщины | E41: июль | F41: июль | G41: г. Краснодар | H41: 3 | I41: 3400 | J41: =H41*I41 -> 10200 | K41: 3 | L41: 3000 | M41: =K41*L41 -> 9000 | N41: 3 | O41: 2900 | P41: =N41*O41 -> 8700 | Q41: 6 | R41: 190 | S41: =Q41*R41 -> 1140 | T41: 6 | U41: 190 | V41: =T41*U41 -> 1140 | W41: 6 | X41: 190 | Y41: =W41*X41 -> 1140 | Z41: 30 | AA41: 6 | AB41: =Z41*AA41 -> 180 | AC41: =H41+K41+N41+Q41+T41+W41+Z41 -> 57 | AD41: =J41+M41+P41+S41+V41+Y41+AB41 -> 31500
A42: 36 | B42: 10 этап Краевых соревнований по пляжному волейболу среди команд любителей - "Кубок федерации 2026", посвященные Дню государственного флага РФ | C42: КС | D42: женщины | E42: июль | F42: июль | G42: г. Краснодар | H42: 3 | I42: 3400 | J42: =H42*I42 -> 10200 | K42: 3 | L42: 3000 | M42: =K42*L42 -> 9000 | N42: 3 | O42: 2900 | P42: =N42*O42 -> 8700 | Q42: 6 | R42: 190 | S42: =Q42*R42 -> 1140 | T42: 6 | U42: 190 | V42: =T42*U42 -> 1140 | W42: 6 | X42: 190 | Y42: =W42*X42 -> 1140 | Z42: 30 | AA42: 6 | AB42: =Z42*AA42 -> 180 | AC42: =H42+K42+N42+Q42+T42+W42+Z42 -> 57 | AD42: =J42+M42+P42+S42+V42+Y42+AB42 -> 31500
A43: 37 | B43: 11 этап Краевых соревнований по пляжному волейболу среди команд любителей - "Кубок федерации 2026", посвященные Дню Краснодарского края | C43: КС | D43: женщины | E43: июль | F43: июль | G43: г. Краснодар | H43: 3 | I43: 3400 | J43: =H43*I43 -> 10200 | K43: 3 | L43: 3000 | M43: =K43*L43 -> 9000 | N43: 3 | O43: 2900 | P43: =N43*O43 -> 8700 | Q43: 6 | R43: 190 | S43: =Q43*R43 -> 1140 | T43: 6 | U43: 190 | V43: =T43*U43 -> 1140 | W43: 6 | X43: 190 | Y43: =W43*X43 -> 1140 | Z43: 30 | AA43: 6 | AB43: =Z43*AA43 -> 180 | AC43: =H43+K43+N43+Q43+T43+W43+Z43 -> 57 | AD43: =J43+M43+P43+S43+V43+Y43+AB43 -> 31500
A44: 38 | B44: Спартакиада трудящихся Краснодарского края, посвященная празднованию 80-летия Победы советского народа в Великой Отечественной войне 1941-1945 годов | C44: КС | D44: согласно положению | E44: январь | F44: июнь | G44: МО Краснодарского края | H44: 44 | I44: 3400 | J44: =H44*I44 -> 149600 | K44: 44 | L44: 3000 | M44: =K44*L44 -> 132000 | N44: 44 | O44: 2900 | P44: =N44*O44 -> 127600 | Q44: 280 | R44: 190 | S44: =Q44*R44 -> 53200 | T44: 280 | U44: 190 | V44: =T44*U44 -> 53200 | W44: 280 | X44: 190 | Y44: =W44*X44 -> 53200 | Z44: 972 | AA44: 6 | AB44: =Z44*AA44 -> 5832 | AC44: =H44+K44+N44+Q44+T44+W44+Z44 -> 1944 | AD44: =J44+M44+P44+S44+V44+Y44+AB44 -> 574632
A45: 39 | B45: 12 этап Краевых соревнований по пляжному волейболу среди команд любителей - "Кубок федерации 2026", посвященные Дню города Краснодара | C45: КС | D45: женщины | E45: июль | F45: июль | G45: г. Краснодар | H45: 3 | I45: 3400 | J45: =H45*I45 -> 10200 | K45: 3 | L45: 3000 | M45: =K45*L45 -> 9000 | N45: 3 | O45: 2900 | P45: =N45*O45 -> 8700 | Q45: 6 | R45: 190 | S45: =Q45*R45 -> 1140 | T45: 6 | U45: 190 | V45: =T45*U45 -> 1140 | W45: 6 | X45: 190 | Y45: =W45*X45 -> 1140 | Z45: 30 | AA45: 6 | AB45: =Z45*AA45 -> 180 | AC45: =H45+K45+N45+Q45+T45+W45+Z45 -> 57 | AD45: =J45+M45+P45+S45+V45+Y45+AB45 -> 31500
A46: 40 | B46: Всекубанский турнир по футболу среди детских дворовых команд на Кубок Губернатора Краснодарского края I этап II этап III этап IV этап | C46: КГ | D46: 10-15 лет | E46: 15.06.2026 01.07.2026 15.07.2026 20.07.2026 | F46: 29.06.2026 12.07.2026 31.07.2026 03.08.2026 | G46: муниципальные образования, городских и сельских поселениях Кранодарского края | H46: 3 | I46: 7300 | J46: =H46*I46 -> 21900 | K46: 3 | L46: 6650 | M46: =K46*L46 -> 19950 | N46: 3 | O46: 6050 | P46: =N46*O46 -> 18150 | Q46: 11 | R46: 190 | S46: =Q46*R46 -> 2090 | T46: 11 | U46: 190 | V46: =T46*U46 -> 2090 | W46: 11 | X46: 190 | Y46: =W46*X46 -> 2090 | Z46: 693 | AA46: 6 | AB46: =Z46*AA46 -> 4158 | AC46: =H46+K46+N46+Q46+T46+W46+Z46 -> 735 | AD46: =J46+M46+P46+S46+V46+Y46+AB46 -> 70428
A47: 41 | B47: Краевой фестиваль по плаванию "Я-Пловец" II этап | C47: КС | D47: мальчики, девочки 8 лет, девушки, юноши 10-11 лет, девушки, юноши 11-13 лет | E47: 18.05.2026 | F47: 19.05.2026 | G47: г. Краснодар | Q47: 8 | R47: 190 | S47: =Q47*R47 -> 1520 | T47: 8 | U47: 190 | V47: =T47*U47 -> 1520 | W47: 8 | X47: 190 | Y47: =W47*X47 -> 1520 | Z47: 24 | AA47: 6 | AB47: =Z47*AA47 -> 144 | AC47: =H47+K47+N47+Q47+T47+W47+Z47 -> 48 | AD47: =J47+M47+P47+S47+V47+Y47+AB47 -> 4704 | AF47: 54
A48: 42 | B48: Краевой фестиваль по плаванию "Я-Пловец" III этап | C48: КС | D48: мальчики, девочки 8 лет, девушки, юноши 10-11 лет, девушки, юноши 11-13 лет | E48: 17.09.2026 | F48: 18.09.2026 | G48: г. Краснодар | Q48: 8 | R48: 190 | S48: =Q48*R48 -> 1520 | T48: 8 | U48: 190 | V48: =T48*U48 -> 1520 | W48: 8 | X48: 190 | Y48: =W48*X48 -> 1520 | Z48: 24 | AA48: 6 | AB48: =Z48*AA48 -> 144 | AC48: =H48+K48+N48+Q48+T48+W48+Z48 -> 48 | AD48: =J48+M48+P48+S48+V48+Y48+AB48 -> 4704 | AF48: 54
A49: 43 | B49: Краевой фестиваль по плаванию "Я-Пловец" IV этап | C49: КС | D49: мальчики, девочки 8 лет, девушки, юноши 10-11 лет, девушки, юноши 11-13 лет | E49: 10.11.2026 | F49: 11.11.2026 | G49: г. Краснодар | Q49: 8 | R49: 190 | S49: =Q49*R49 -> 1520 | T49: 8 | U49: 190 | V49: =T49*U49 -> 1520 | W49: 8 | X49: 190 | Y49: =W49*X49 -> 1520 | Z49: 24 | AA49: 6 | AB49: =Z49*AA49 -> 144 | AC49: =H49+K49+N49+Q49+T49+W49+Z49 -> 48 | AD49: =J49+M49+P49+S49+V49+Y49+AB49 -> 4704 | AF49: 54
A50: 44 | B50: Личное первенство Краснодарского края среди ветеранов (рывок мужчины и женщины) | C50: ПК | D50: мужчины, женщины | E50: 46101 | F50: 46102 | G50: ст.Анастасиевская, Славянский район | Q50: 18 | R50: 190 | S50: =Q50*R50 -> 3420 | T50: 18 | U50: 190 | V50: =T50*U50 -> 3420 | W50: 18 | X50: 190 | Y50: =W50*X50 -> 3420 | Z50: 54 | AA50: 6 | AB50: =Z50*AA50 -> 324 | AC50: =H50+K50+N50+Q50+T50+W50+Z50 -> 108 | AD50: =J50+M50+P50+S50+V50+Y50+AB50 -> 10584 | AF50: положение 27.01.2026
A51: 45 | B51: Краевой предновогодний гиревой марафон и полумарафон среди юношей и девушек, мужчин и женщин | C51: КС | D51: мальчики и девочки (10-12 лет), юноши, девушки 14-16 лет, 17-18 лет, юниоры и юниорки 19-23 года, мужчины (19-39 лет, женщины 19-35 лет), ветераны мужчины ( 40 лет и старше), женщины (35 лет и старше) | E51: 46375 | F51: 46376 | G51: ст-ца Анастасиевская (Славянский район) | Q51: 12 | R51: 190 | S51: =Q51*R51 -> 2280 | T51: 12 | U51: 190 | V51: =T51*U51 -> 2280 | W51: 12 | X51: 190 | Y51: =W51*X51 -> 2280 | Z51: 36 | AA51: 6 | AB51: =Z51*AA51 -> 216 | AC51: =H51+K51+N51+Q51+T51+W51+Z51 -> 72 | AD51: =J51+M51+P51+S51+V51+Y51+AB51 -> 7056
A52: ГОСУДАРСТВЕННАЯ ПРОГРАММА КРАСНОДАРСКОГО КРАЯ
B53: "ДОСТУПНАЯ СРЕДА"
A54: 46 | B54: Краевой фестиваль шахмат среди инвалидов по зрению программа | C54: КС | D54: 14 лет и старше | E54: по назначению | F54: согласно положению | G54: согласно положению | Q54: 2 | R54: 190 | S54: =Q54*R54 -> 380 | T54: 2 | U54: 190 | V54: =T54*U54 -> 380 | W54: 2 | X54: 190 | Y54: =W54*X54 -> 380 | Z54: 6 | AA54: 6 | AB54: =Z54*AA54 -> 36 | AC54: =H54+K54+N54+Q54+T54+W54+Z54 -> 12 | AD54: =J54+M54+P54+S54+V54+Y54+AB54 -> 1176
A55: 47 | B55: Краевой фестиваль шашек среди инвалидов по зрению | C55: КС | D55: мужчины, женщины от 18 и старше | E55: по назначению | F55: согласно положению | G55: согласно положению | Q55: 4 | R55: 190 | S55: =Q55*R55 -> 760 | T55: 4 | U55: 190 | V55: =T55*U55 -> 760 | W55: 4 | X55: 190 | Y55: =W55*X55 -> 760 | Z55: 12 | AA55: 6 | AB55: =Z55*AA55 -> 72 | AC55: =H55+K55+N55+Q55+T55+W55+Z55 -> 24 | AD55: =J55+M55+P55+S55+V55+Y55+AB55 -> 2352
A56: 48 | B56: Краевой фестиваль по шоудауну среди инвалидов по зрению | C56: КС | D56: 14 лет и старше | E56: по назначению | F56: согласно положению | G56: согласно положению | Q56: 2 | R56: 190 | S56: =Q56*R56 -> 380 | T56: 2 | U56: 190 | V56: =T56*U56 -> 380 | W56: 2 | X56: 190 | Y56: =W56*X56 -> 380 | Z56: 6 | AA56: 6 | AB56: =Z56*AA56 -> 36 | AC56: =H56+K56+N56+Q56+T56+W56+Z56 -> 12 | AD56: =J56+M56+P56+S56+V56+Y56+AB56 -> 1176
A57: 49 | B57: Краевой спортивный фестиваль среди инвалидов с нарушением слуха | C57: КС | D57: мужчины, женщины от 18 и старше | E57: по назначению | F57: по назначению | G57: по назначению | H57: 1 | I57: 3400 | J57: =H57*I57 -> 3400 | K57: 1 | L57: 3000 | M57: =K57*L57 -> 3000 | N57: 1 | O57: 2900 | P57: =N57*O57 -> 2900 | Q57: 34 | R57: 190 | S57: =Q57*R57 -> 6460 | T57: 34 | U57: 190 | V57: =T57*U57 -> 6460 | W57: 34 | X57: 190 | Y57: =W57*X57 -> 6460 | Z57: 120 | AA57: 6 | AB57: =H57+K57+N57+Q57+T57+W57+Z57 -> 225 | AC57: =H57+K57+N57+Q57+T57+W57+Z57 -> 225 | AD57: =J57+M57+P57+S57+V57+Y57 -> 28680
A58: 50 | B58: Краевой фестиваль среди инвалидов с нарушением слуха № 2 | C58: КС | D58: 12-17 лет | E58: по назначению | F58: по назначению | G58: по назначению | H58: 1 | I58: 3400 | J58: =H58*I58 -> 3400 | K58: 1 | L58: 3000 | M58: =K58*L58 -> 3000 | N58: 1 | O58: 2900 | P58: =N58*O58 -> 2900 | Q58: 15 | R58: 190 | S58: =Q58*R58 -> 2850 | T58: 15 | U58: 190 | V58: =T58*U58 -> 2850 | W58: 15 | X58: 190 | Y58: =W58*X58 -> 2850 | Z58: 186 | AA58: 6 | AB58: 186 | AC58: =H58+K58+N58+Q58+T58+W58+Z58 -> 234 | AD58: =J58+M58+P58+S58+V58+Y58 -> 17850
A59: 51 | B59: Краевые спортивные соревнования для детей-инвалидов с поражением опорно-двигательного аппарата | C59: КС | D59: до 18 лет | E59: по назначению | F59: по назначению | G59: по назначению | Q59: 18 | R59: 190 | S59: =Q59*R59 -> 3420 | T59: 18 | U59: 190 | V59: =T59*U59 -> 3420 | W59: 18 | X59: 190 | Y59: =W59*X59 -> 3420 | Z59: 54 | AA59: 6 | AB59: =Z59*AA59 -> 324 | AC59: =H59+K59+N59+Q59+T59+W59+Z59 -> 108 | AD59: =J59+M59+P59+S59+V59+Y59+AB59 -> 10584
A60: 52 | B60: Краевой спортивный конкурс среди инвалидов по зрению "Современная мозайка" | C60: КС | D60: 18 лет и старше | E60: по назначению | F60: по назначению | G60: по назначению | H60: 1 | I60: 3400 | J60: =H60*I60 -> 3400 | K60: 1 | L60: 3000 | M60: =K60*L60 -> 3000 | N60: 1 | O60: 2900 | P60: =N60*O60 -> 2900 | Q60: 21 | R60: 190 | S60: =Q60*R60 -> 3990 | T60: 21 | U60: 190 | V60: =T60*U60 -> 3990 | W60: 21 | X60: 190 | Y60: =W60*X60 -> 3990 | Z60: 75 | AA60: 6 | AB60: 75 | AC60: =H60+K60+N60+Q60+T60+W60+Z60 -> 141 | AD60: =J60+M60+P60+S60+V60+Y60+AB60 -> 21345
A61: 53 | B61: Краевой фестиваль для детей -инвалидов и их сверстников, не имеющих инвалидности, в возрасте от 12 до 16 лет | C61: КС | D61: от 12-16 лет | E61: по назначению | F61: по назначению | G61: по назначению | H61: 1 | I61: 3400 | J61: =H61*I61 -> 3400 | K61: 1 | L61: 3000 | M61: =K61*L61 -> 3000 | N61: 1 | O61: 2900 | P61: =N61*O61 -> 2900 | Q61: 20 | R61: 190 | S61: =Q61*R61 -> 3800 | T61: 20 | U61: 190 | V61: =T61*U61 -> 3800 | W61: 20 | X61: 190 | Y61: =W61*X61 -> 3800 | Z61: 51 | AA61: 6 | AB61: =H61+K61+N61+Q61+T61+W61+Z61 -> 114 | AC61: =H61+K61+N61+Q61+T61+W61+Z61 -> 114 | AD61: =J61+M61+P61+S61+V61+Y61+AB61 -> 20814
A62: 54 | B62: Спартакиада инвалидов Кубани | C62: КС | D62: 12-60 лет | E62: по назначению | F62: по назначению | G62: по назначению | H62: 8 | I62: 3400 | J62: =H62*I62 -> 27200 | K62: 8 | L62: 3000 | M62: =K62*L62 -> 24000 | N62: 8 | O62: 2900 | P62: =N62*O62 -> 23200 | Q62: 102 | R62: 190 | S62: =Q62*R62 -> 19380 | T62: 102 | U62: 190 | V62: =T62*U62 -> 19380 | W62: 102 | X62: 190 | Y62: =W62*X62 -> 19380 | Z62: 330 | AA62: 6 | AB62: =Z62*AA62 -> 1980 | AC62: =H62+K62+N62+Q62+T62+W62+Z62 -> 660 | AD62: =J62+M62+P62+S62+V62+Y62+AB62 -> 134520
A63: 55 | B63: Первенство Краснодарского края | C63: ПК | D63: 12 лет 13-15 лет 16-18 лет | E63: 46082 | F63: 46082 | G63: по назначению | H63: 1 | I63: 3400 | J63: =H63*I63 -> 3400 | K63: 1 | L63: 3000 | M63: =K63*L63 -> 3000 | N63: 2 | O63: 2900 | P63: =N63*O63 -> 5800 | Q63: 24 | R63: 190 | S63: =Q63*R63 -> 4560 | T63: 24 | U63: 190 | V63: =T63*U63 -> 4560 | W63: 48 | X63: 190 | Y63: =W63*X63 -> 9120 | Z63: 96 | AA63: 6 | AB63: =Z63*AA63 -> 576 | AC63: =H63+K63+N63+Q63+T63+W63+Z63 -> 196 | AD63: =J63+M63+P63+S63++V63+Y63+AB63 -> 31016
A64: 56 | B64: Чемпионат Краснодарского края | C64: ЧК | D64: 19 лет и старше | E64: по назначению | F64: по назначению | G64: по назначению | H64: 1 | I64: 4100 | J64: =H64*I64 -> 4100 | K64: 1 | L64: 3350 | M64: =K64*L64 -> 3350 | N64: 2 | O64: 3000 | P64: =N64*O64 -> 6000 | Q64: 8 | R64: 190 | S64: =Q64*R64 -> 1520 | T64: 8 | U64: 190 | V64: =T64*U64 -> 1520 | W64: 16 | X64: 190 | Y64: =W64*X64 -> 3040 | Z64: 32 | AA64: 6 | AB64: =Z64*AA64 -> 192 | AC64: =H64+K64+N64+Q64+T64+W64+Z64 -> 68 | AD64: =J64+M64+P64+S64++V64+Y64+AB64 -> 19722
A65: 57 | B65: Первенство Краснодарского края | C65: ПК | D65: 12 лет 13-15 лет 16-18 лет 19 лет и старше | E65: по назначению | F65: по назначению | G65: по назначению | H65: 1 | I65: 3400 | J65: =H65*I65 -> 3400 | K65: 1 | L65: 3000 | M65: =K65*L65 -> 3000 | N65: 2 | O65: 2900 | P65: =N65*O65 -> 5800 | Q65: 32 | R65: 190 | S65: =Q65*R65 -> 6080 | T65: 32 | U65: 190 | V65: =T65*U65 -> 6080 | W65: 64 | X65: 190 | Y65: =W65*X65 -> 12160 | Z65: 96 | AA65: 6 | AB65: =Z65*AA65 -> 576 | AC65: =H65+K65+N65+Q65+T65+W65+Z65 -> 228 | AD65: =J65+M65+P65+S65++V65+Y65+AB65 -> 37096
B66: ДИНАМО
A67: 58 | B67: 68-я Спартакиада Краснодарской краевой организации Общества «Динамо» | C67: КС | D67: 21-50 лет | E67: по назначению | F67: по назначению | G67: МО Краснодарского края | H67: 27 | I67: 3400 | J67: =H67*I67 -> 91800 | K67: 27 | L67: 3000 | M67: =K67*L67 -> 81000 | N67: 27 | O67: 2900 | P67: =N67*O67 -> 78300 | Q67: 151 | R67: 190 | S67: =Q67*R67 -> 28690 | T67: 151 | U67: 190 | V67: =T67*U67 -> 28690 | W67: 151 | X67: 190 | Y67: =W67*X67 -> 28690 | AC67: =H67+K67+N67+Q67+T67+W67+Z67 -> 534 | AD67: =J67+M67+P67+S67+V67+Y67+AB67 -> 337170 | AE67: =SUM(AD67:AD70) -> 874770
A68: 59 | B68: Спартакиада Краснодарской краевой организации Общества «Динамо» совместно с Новороссийской городской организацией Общества "Динамо" | C68: КС | D68: 21-50 лет | E68: по назначению | F68: по назначению | G68: МО Краснодарского края | H68: 24 | I68: 3400 | J68: =H68*I68 -> 81600 | K68: 24 | L68: 3000 | M68: =K68*L68 -> 72000 | N68: 24 | O68: 2900 | P68: =N68*O68 -> 69600 | Q68: 92 | R68: 190 | S68: =Q68*R68 -> 17480 | T68: 92 | U68: 190 | V68: =T68*U68 -> 17480 | W68: 92 | X68: 190 | Y68: =W68*X68 -> 17480 | AC68: =H68+K68+N68+Q68+T68+W68+Z68 -> 348 | AD68: =J68+M68+P68+S68+V68+Y68+AB68 -> 275640
A69: 60 | B69: VIII Спартакиада Краснодарской краевой организации Общества «Динамо» среди ветеранов-пенсионеров органов безопасности и правопорядка | C69: КС | D69: 45+ | E69: по назначению | F69: по назначению | G69: МО Краснодарского края | H69: 9 | I69: 3400 | J69: =H69*I69 -> 30600 | K69: 9 | L69: 3000 | M69: =K69*L69 -> 27000 | N69: 9 | O69: 2900 | P69: =N69*O69 -> 26100 | Q69: 40 | R69: 190 | S69: =Q69*R69 -> 7600 | T69: 40 | U69: 190 | V69: =T69*U69 -> 7600 | W69: 40 | X69: 190 | Y69: =W69*X69 -> 7600 | AC69: =H69+K69+N69+Q69+T69+W69+Z69 -> 147 | AD69: =J69+M69+P69+S69+V69+Y69+AB69 -> 106500
A70: 61 | B70: Спартакиада Главного управления по Краснодарскому краю Федеральной службы войск национальной гвардии Российской Федерации и Краснодарской краевой организации Общества "Динамо" в 2026 году | C70: КС | D70: 21-50 лет | E70: февраль | F70: декабрь | G70: МО Краснодарского края | H70: 11 | I70: 3400 | J70: =H70*I70 -> 37400 | K70: 11 | L70: 3000 | M70: =K70*L70 -> 33000 | N70: 11 | O70: 2900 | P70: =N70*O70 -> 31900 | Q70: 90 | R70: 190 | S70: =Q70*R70 -> 17100 | T70: 90 | U70: 190 | V70: =T70*U70 -> 17100 | W70: 90 | X70: 190 | Y70: =W70*X70 -> 17100 | Z70: 310 | AA70: 6 | AB70: =Z70*AA70 -> 1860 | AC70: =H70+K70+N70+Q70+T70+W70+Z70 -> 613 | AD70: =J70+M70+P70+S70+V70+Y70+AB70 -> 155460
A71: СПОРТИВНЫЕ СОРЕВНОВАНИЯ ПО ВИДАМ СПОРТА
A72: АРМРЕСТЛИНГ
A73: 62 | B73: Первенство Краснодарского края | C73: ПК | D73: юноши, девушки (14- 15 лет), юниоры, юниорки (16-18 лет), юниоры, юниорки (19-21 год), мужчины, женщины | E73: 46332 | F73: 46334 | G73: Красноармейский район, ст-ца Старонижестеблиевская | H73: 1 | I73: 3400 | J73: =H73*I73 -> 3400 | K73: 1 | L73: 3000 | M73: =K73*L73 -> 3000 | N73: 1 | O73: 2900 | P73: =N73*O73 -> 2900 | Q73: 44 | R73: 190 | S73: =Q73*R73 -> 8360 | T73: 44 | U73: 190 | V73: =T73*U73 -> 8360 | W73: 44 | X73: 190 | Y73: =W73*X73 -> 8360 | Z73: 145 | AA73: 6 | AB73: =Z73*AA73 -> 870 | AC73: =H73+K73+N73+Q73+T73+W73+Z73 -> 280 | AD73: =J73+M73+P73+S73++V73+Y73+AB73 -> 35250
A74: 63 | B74: Чемпионат Краснодарского края | C74: ЧК | D74: мужчины, женщины | E74: 46346 | F74: 46348 | G74: Красноармейский район, ст-ца Старонижестеблиевская | H74: 1 | I74: 4100 | J74: =H74*I74 -> 4100 | K74: 1 | L74: 3350 | M74: =K74*L74 -> 3350 | N74: 1 | O74: 3000 | P74: =N74*O74 -> 3000 | Q74: 19 | R74: 190 | S74: =Q74*R74 -> 3610 | T74: 19 | U74: 190 | V74: =T74*U74 -> 3610 | W74: 19 | X74: 190 | Y74: =W74*X74 -> 3610 | Z74: 70 | AA74: 6 | AB74: =Z74*AA74 -> 420 | AC74: =H74+K74+N74+Q74+T74+W74+Z74 -> 130 | AD74: =J74+M74+P74+S74++V74+Y74+AB74 -> 21700
B75: АВИАМОДЕЛЬНЫЙ СПОРТ
A76: 64 | B76: Кубок Краснодарского края в классе моделей F2B-моделей -пилотажные модели | C76: КК | D76: юниоры, юниорки (14 лет и старше) | E76: 46147 | F76: 46180 | G76: с. Красногвардейское, Республика Адыгея | H76: 1 | I76: 3300 | J76: =H76*I76 -> 3300 | K76: 1 | L76: 2850 | M76: =K76*L76 -> 2850 | N76: 1 | O76: 2750 | P76: =N76*O76 -> 2750 | Q76: 2 | R76: 190 | S76: =Q76*R76 -> 380 | T76: 2 | U76: 190 | V76: =T76*U76 -> 380 | W76: 2 | X76: 190 | Y76: =W76*X76 -> 380 | Z76: 6 | AA76: 6 | AB76: =Z76*AA76 -> 36 | AC76: =Q76+T76+W76+Z76 -> 12 | AD76: =S76+V76+Y76+AB76 -> 1176 | AF76: положение 29.12.2026
A77: 65 | B77: Чемпионат Краснодарского края по авиамодельному спорту в классе моделей F2D-модели "воздушного боя" | C77: ЧК | D77: юниоры, юниорки (14 лет и старше) | E77: 46136 | F77: 46139 | G77: Красносельское городское поселение, Гулькевичского района | H77: 1 | I77: 3300 | J77: =H77*I77 -> 3300 | K77: 1 | L77: 2850 | M77: =K77*L77 -> 2850 | N77: 1 | O77: 2750 | P77: =N77*O77 -> 2750 | Q77: 4 | R77: 190 | S77: =Q77*R77 -> 760 | T77: 4 | U77: 190 | V77: =T77*U77 -> 760 | W77: 4 | X77: 190 | Y77: =W77*X77 -> 760 | Z77: 12 | AA77: 6 | AB77: =Z77*AA77 -> 72 | AC77: =Q77+T77+W77+Z77 -> 24 | AD77: =S77+V77+Y77+AB77 -> 2352 | AF77: положение 29.12.2026
A78: 66 | B78: Первенство Краснодарского края по авиамодельному спорту в классе моделей F2D-модели "воздушного боя" | C78: ПК | D78: юниоры, юниорки (10-18 лет) | E78: 46135 | F78: 46137 | G78: Красносельское городское поселение, Гулькевичского района | H78: 1 | I78: 3300 | J78: =H78*I78 -> 3300 | K78: 1 | L78: 2850 | M78: =K78*L78 -> 2850 | N78: 1 | O78: 2750 | P78: =N78*O78 -> 2750 | Q78: 4 | R78: 190 | S78: =Q78*R78 -> 760 | T78: 4 | U78: 190 | V78: =T78*U78 -> 760 | W78: 4 | X78: 190 | Y78: =W78*X78 -> 760 | Z78: 12 | AA78: 6 | AB78: =Z78*AA78 -> 72 | AC78: =Q78+T78+W78+Z78 -> 24 | AD78: =S78+V78+Y78+AB78 -> 2352 | AF78: положение 29.12.2026
B79: АКРОБАТИЧЕСКИЙ РОК-Н-РОЛЛ
A80: 67 | B80: Краевые соревнования, посвященные Международному женскому дню | C80: КС | D80: мужчины и женщины, юниоры и юниорки до 18 лет, юноши и девушки до 16 лет, до 15 лет, мальчики и девочки до 12 лет | E80: 46087 | F80: 46088 | G80: г. Краснодар | Q80: 105 | R80: 190 | S80: =Q80*R80 -> 19950 | T80: 88 | U80: 190 | V80: =T80*U80 -> 16720 | W80: 88 | X80: 190 | Y80: =W80*X80 -> 16720 | Z80: 281 | AA80: 6 | AB80: =Z80*AA80 -> 1686 | AC80: =H80+K80+N80+Q80+T80+W80+Z80 -> 562 | AD80: =J80+M80+P80+S80+V80+Y80+AB80 -> 55076 | AF80: 281
A81: 68 | B81: Краевые соревнования | C81: КС | D81: мужчины и женщины, юниоры и юниорки до 18 лет, юноши и девушки до 16 лет, до 15 лет, мальчики и девочки до 12 лет | E81: 46116 | F81: 46117 | G81: г. Краснодар | Q81: 105 | R81: 190 | S81: =Q81*R81 -> 19950 | T81: 88 | U81: 190 | V81: =T81*U81 -> 16720 | W81: 88 | X81: 190 | Y81: =W81*X81 -> 16720 | Z81: 281 | AA81: 6 | AB81: =Z81*AA81 -> 1686 | AC81: =H81+K81+N81+Q81+T81+W81+Z81 -> 562 | AD81: =J81+M81+P81+S81+V81+Y81+AB81 -> 55076 | AF81: 281
A82: 69 | B82: Первенство Краснодарского края | C82: ПК | D82: юниоры и юниорки до 18 лет, юноши и девушки до 16 лет, до 15 лет, мальчики и девочки до 12 лет | E82: 46299 | F82: 46301 | G82: г. Краснодар | Q82: 63 | R82: 190 | S82: =Q82*R82 -> 11970 | T82: 52 | U82: 190 | V82: =T82*U82 -> 9880 | W82: 52 | X82: 190 | Y82: =W82*X82 -> 9880 | Z82: 167 | AA82: 6 | AB82: =Z82*AA82 -> 1002 | AC82: =H82+K82+N82+Q82+T82+W82+Z82 -> 334 | AD82: =J82+M82+P82+S82+V82+Y82+AB82 -> 32732
A83: 70 | B83: Чемпионат Краснодарского края | C83: ЧК | D83: юниоры и юниорки до 18 лет, юноши и девушки до 16 лет, до 15 лет, мальчики и девочки до 12 лет | E83: 26.09.206 | F83: 46292 | G83: г. Краснодар | Q83: 42 | R83: 190 | S83: =Q83*R83 -> 7980 | T83: 36 | U83: 190 | V83: =T83*U83 -> 6840 | W83: 36 | X83: 190 | Y83: =W83*X83 -> 6840 | Z83: 114 | AA83: 6 | AB83: =Z83*AA83 -> 684 | AC83: =H83+K83+N83+Q83+T83+W83+Z83 -> 228 | AD83: =J83+M83+P83+S83+V83+Y83+AB83 -> 22344
A84: 71 | B84: Краевые соревнования | C84: КС | D84: мужчины и женщины, юниоры и юниорки до 18 лет, юноши и девушки до 16 лет, до 15 лет, мальчики и девочки до 12 лет | E84: 46184 | F84: 46185 | G84: г. Краснодар | Q84: 105 | R84: 190 | S84: =Q84*R84 -> 19950 | T84: 88 | U84: 190 | V84: =T84*U84 -> 16720 | W84: 88 | X84: 190 | Y84: =W84*X84 -> 16720 | Z84: 281 | AA84: 6 | AB84: =Z84*AA84 -> 1686 | AC84: =H84+K84+N84+Q84+T84+W84+Z84 -> 562 | AD84: =J84+M84+P84+S84+V84+Y84+AB84 -> 55076
A85: 72 | B85: Краевые соревнования "Новогодняя сказка-2025" | C85: КС | D85: мужчины и женщины, юниоры и юниорки до 18 лет, юноши и девушки до 16 лет, до 15 лет, мальчики и девочки до 12 лет | E85: 46368 | F85: 46369 | G85: г. Краснодар | Q85: 105 | R85: 190 | S85: =Q85*R85 -> 19950 | T85: 88 | U85: 190 | V85: =T85*U85 -> 16720 | W85: 88 | X85: 190 | Y85: =W85*X85 -> 16720 | Z85: 281 | AA85: 6 | AB85: =Z85*AA85 -> 1686 | AC85: =H85+K85+N85+Q85+T85+W85+Z85 -> 562 | AD85: =J85+M85+P85+S85+V85+Y85+AB85 -> 55076
B86: БАДМИНТОН
A87: 73 | B87: Краевые соревнования по бадминтону | C87: ПК | D87: мальчики, девочки до 11 лет, до 13 лет | E87: 46359 | F87: 46362 | G87: г.Кореновск | Q87: 16 | R87: 190 | S87: =Q87*R87 -> 3040 | T87: 16 | U87: 190 | V87: =T87*U87 -> 3040 | W87: 32 | X87: 190 | Y87: =W87*X87 -> 6080 | Z87: 64 | AA87: 6 | AB87: =Z87*AA87 -> 384 | AC87: =H87+K87+N87+Q87+T87+W87+Z87 -> 128 | AD87: =J87+M87+P87+S87+V87+Y87+AB87 -> 12544 | AF87: 32
A88: 74 | B88: Краевые соревнования по бадминтону | C88: КС | D88: мальчики, девочки до 11 лет, до 13 лет | E88: 46100 | F88: 46102 | G88: г.Усть -Лабинск | Q88: 16 | R88: 190 | S88: =Q88*R88 -> 3040 | T88: 16 | U88: 190 | V88: =T88*U88 -> 3040 | W88: 32 | X88: 190 | Y88: =W88*X88 -> 6080 | Z88: 64 | AA88: 6 | AB88: =Z88*AA88 -> 384 | AC88: =H88+K88+N88+Q88+T88+W88+Z88 -> 128 | AD88: =J88+M88+P88+S88+V88+Y88+AB88 -> 12544 | AF88: 64
A89: 75 | B89: Краевые соревнования по бадминтону, посвященные Кузнецовой О.М. | C89: КС | D89: мальчики, девочки до 11 лет, до 13 лет | E89: 46135 | F89: 46138 | G89: г.Кореновск | Q89: 16 | R89: 190 | S89: =Q89*R89 -> 3040 | T89: 16 | U89: 190 | V89: =T89*U89 -> 3040 | W89: 33 | X89: 190 | Y89: =W89*X89 -> 6270 | Z89: 64 | AA89: 6 | AB89: =Z89*AA89 -> 384 | AC89: =H89+K89+N89+Q89+T89+W89+Z89 -> 129 | AD89: =J89+M89+P89+S89+V89+Y89+AB89 -> 12734
A90: 76 | B90: Первенство Краснодарского края по бадминтону среди юношей и девушек до 15 лет | C90: ПК | D90: юноши, девушки до 15 лет | E90: 46282 | F90: 46285 | G90: г.Кореновск | Q90: 8 | R90: 190 | S90: =Q90*R90 -> 1520 | T90: 8 | U90: 190 | V90: =T90*U90 -> 1520 | W90: 16 | X90: 190 | Y90: =W90*X90 -> 3040 | Z90: 32 | AA90: 6 | AB90: =Z90*AA90 -> 192 | AC90: =H90+K90+N90+Q90+T90+W90+Z90 -> 64 | AD90: =J90+M90+P90+S90+V90+Y90+AB90 -> 6272
A91: 77 | B91: Первенство Краснодарского края по бадминтону среди мальчиков и девочек до 13 лет | C91: ПК | D91: мальчики, девочки до 13 лет | E91: 46303 | F91: 46306 | G91: г.Кореновск | Q91: 8 | R91: 190 | S91: =Q91*R91 -> 1520 | T91: 8 | U91: 190 | V91: =T91*U91 -> 1520 | W91: 16 | X91: 190 | Y91: =W91*X91 -> 3040 | Z91: 32 | AA91: 6 | AB91: =Z91*AA91 -> 192 | AC91: =H91+K91+N91+Q91+T91+W91+Z91 -> 64 | AD91: =J91+M91+P91+S91+V91+Y91+AB91 -> 6272
A92: 78 | B92: Краевые соревнования по бадминтону | C92: КС | D92: мальчики, девочки до 11 лет, до 13 лет | E92: 46170 | F92: 46173 | G92: г.Кореновск | Q92: 16 | R92: 190 | S92: =Q92*R92 -> 3040 | T92: 16 | U92: 190 | V92: =T92*U92 -> 3040 | W92: 32 | X92: 190 | Y92: =W92*X92 -> 6080 | Z92: 64 | AA92: 6 | AB92: =Z92*AA92 -> 384 | AC92: =H92+K92+N92+Q92+T92+W92+Z92 -> 128 | AD92: =J92+M92+P92+S92+V92+Y92+AB92 -> 12544
A93: 79 | B93: Чемпионат Краснодарского края по бадминтону среди мужчин и женщин | C93: ЧК | D93: мужчины, женщины | E93: 46331 | F93: 46334 | G93: г. Краснодар | Q93: 8 | R93: 190 | S93: =Q93*R93 -> 1520 | T93: 8 | U93: 190 | V93: =T93*U93 -> 1520 | W93: 16 | X93: 190 | Y93: =W93*X93 -> 3040 | Z93: 32 | AA93: 6 | AB93: =Z93*AA93 -> 192 | AC93: =H93+K93+N93+Q93+T93+W93+Z93 -> 64 | AD93: =J93+M93+P93+S93+V93+Y93+AB93 -> 6272
A94: 80 | B94: Краевые соревнования по бадминтону | C94: КС | D94: мальчики, девочки до 11 лет, до 13 лет | E94: 46268 | F94: 46271 | G94: г.Кореновск | Q94: 16 | R94: 190 | S94: =Q94*R94 -> 3040 | T94: 16 | U94: 190 | V94: =T94*U94 -> 3040 | W94: 32 | X94: 190 | Y94: =W94*X94 -> 6080 | Z94: 64 | AA94: 6 | AB94: =Z94*AA94 -> 384 | AC94: =H94+K94+N94+Q94+T94+W94+Z94 -> 128 | AD94: =J94+M94+P94+S94+V94+Y94+AB94 -> 12544
B95: БАСКЕТБОЛ
A97: 81 | B97: Первенство Краснодарского края по баскетболу среди юниорок до 18 лет | C97: ПК | D97: до 18 лет | E97: 46133 | F97: 46139 | G97: г. Кропоткин | H97: 1 | I97: 3400 | J97: =H97*I97 -> 3400 | K97: 1 | L97: 3000 | M97: =K97*L97 -> 3000 | N97: 1 | O97: 2900 | P97: =N97*O97 -> 2900 | Q97: 14 | R97: 190 | S97: =Q97*R97 -> 2660 | T97: 14 | U97: 190 | V97: =T97*U97 -> 2660 | W97: 14 | X97: 190 | Y97: =W97*X97 -> 2660 | Z97: 45 | AA97: 6 | AB97: =Z97*AA97 -> 270 | AC97: =H97+K97+N97+Q97+T97+W97+Z97 -> 90 | AD97: =J97+M97+P97+S97+V97+Y97+AB97 -> 17550 | AF97: 45
A98: 82 | B98: Первенство Краснодарского края по баскетболу среди юниоров до 18 лет | C98: ПК | D98: до 18 лет | E98: 46126 | F98: 46132 | G98: г. Белореченск | H98: 1 | I98: 3400 | J98: =H98*I98 -> 3400 | K98: 1 | L98: 3000 | M98: =K98*L98 -> 3000 | N98: 1 | O98: 2900 | P98: =N98*O98 -> 2900 | Q98: 14 | R98: 190 | S98: =Q98*R98 -> 2660 | T98: 14 | U98: 190 | V98: =T98*U98 -> 2660 | W98: 14 | X98: 190 | Y98: =W98*X98 -> 2660 | Z98: 45 | AA98: 6 | AB98: =Z98*AA98 -> 270 | AC98: =H98+K98+N98+Q98+T98+W98+Z98 -> 90 | AD98: =J98+M98+P98+S98+V98+Y98+AB98 -> 17550 | AF98: 45
A99: 83 | B99: Первенство Краснодарского края по баскетболу 3х3 среди юниоров до 19 лет | C99: ПК | D99: до 19 лет | E99: 46160 | F99: 46161 | G99: г. Белореченск | H99: 1 | I99: 3400 | J99: =H99*I99 -> 3400 | K99: 1 | L99: 3000 | M99: =K99*L99 -> 3000 | N99: 1 | O99: 2900 | P99: =N99*O99 -> 2900 | Q99: 5 | R99: 190 | S99: =Q99*R99 -> 950 | T99: 5 | U99: 190 | V99: =T99*U99 -> 950 | W99: 5 | X99: 190 | Y99: =W99*X99 -> 950 | Z99: 18 | AA99: 6 | AB99: =Z99*AA99 -> 108 | AC99: =H99+K99+N99+Q99+T99+W99+Z99 -> 36 | AD99: =J99+M99+P99+S99+V99+Y99+AB99 -> 12258 | AF99: 18
A100: 84 | B100: Первенство Краснодарского края по баскетболу 3х3 среди юниорок до 19 лет | C100: ПК | D100: до 19 лет | E100: 46160 | F100: 46161 | G100: г. Белореченск | H100: 1 | I100: 3400 | J100: =H100*I100 -> 3400 | K100: 1 | L100: 3000 | M100: =K100*L100 -> 3000 | N100: 1 | O100: 2900 | P100: =N100*O100 -> 2900 | Q100: 5 | R100: 190 | S100: =Q100*R100 -> 950 | T100: 5 | U100: 190 | V100: =T100*U100 -> 950 | W100: 5 | X100: 190 | Y100: =W100*X100 -> 950 | Z100: 18 | AA100: 6 | AB100: =Z100*AA100 -> 108 | AC100: =H100+K100+N100+Q100+T100+W100+Z100 -> 36 | AD100: =J100+M100+P100+S100+V100+Y100+AB100 -> 12258 | AF100: 18
A101: 85 | B101: Краевые соревнования по баскетболу 3х3 среди юношей до 15 лет | C101: КС | D101: до 15 лет | E101: 46162 | F101: 46163 | G101: г. Белореченск | H101: 1 | I101: 3400 | J101: =H101*I101 -> 3400 | K101: 1 | L101: 3000 | M101: =K101*L101 -> 3000 | N101: 1 | O101: 2900 | P101: =N101*O101 -> 2900 | Q101: 5 | R101: 190 | S101: =Q101*R101 -> 950 | T101: 5 | U101: 190 | V101: =T101*U101 -> 950 | W101: 5 | X101: 190 | Y101: =W101*X101 -> 950 | Z101: 18 | AA101: 6 | AB101: =Z101*AA101 -> 108 | AC101: =H101+K101+N101+Q101+T101+W101+Z101 -> 36 | AD101: =J101+M101+P101+S101+V101+Y101+AB101 -> 12258 | AF101: 18
A102: 86 | B102: Краевые соревнования по баскетболу 3х3 среди девушек до 15 лет | C102: КС | D102: до 15 лет | E102: 46162 | F102: 46163 | G102: г. Белореченск | H102: 1 | I102: 3400 | J102: =H102*I102 -> 3400 | K102: 1 | L102: 3000 | M102: =K102*L102 -> 3000 | N102: 1 | O102: 2900 | P102: =N102*O102 -> 2900 | Q102: 5 | R102: 190 | S102: =Q102*R102 -> 950 | T102: 5 | U102: 190 | V102: =T102*U102 -> 950 | W102: 5 | X102: 190 | Y102: =W102*X102 -> 950 | Z102: 18 | AA102: 6 | AB102: =Z102*AA102 -> 108 | AC102: =H102+K102+N102+Q102+T102+W102+Z102 -> 36 | AD102: =J102+M102+P102+S102+V102+Y102+AB102 -> 12258 | AF102: 18
A103: 87 | B103: Краевые соревнования по баскетболу 3х3 среди юношей до 14 лет | C103: КС | D103: до 14 лет | E103: 46163 | F103: 46164 | G103: г. Белореченск | H103: 1 | I103: 3400 | J103: =H103*I103 -> 3400 | K103: 1 | L103: 3000 | M103: =K103*L103 -> 3000 | N103: 1 | O103: 2900 | P103: =N103*O103 -> 2900 | Q103: 5 | R103: 190 | S103: =Q103*R103 -> 950 | T103: 5 | U103: 190 | V103: =T103*U103 -> 950 | W103: 5 | X103: 190 | Y103: =W103*X103 -> 950 | Z103: 18 | AA103: 6 | AB103: =Z103*AA103 -> 108 | AC103: =H103+K103+N103+Q103+T103+W103+Z103 -> 36 | AD103: =J103+M103+P103+S103+V103+Y103+AB103 -> 12258 | AF103: 18
...

Sheet потребность на 07-09
A1: 5. Работа: "Участие в организации официальных спортивных мероприятий"
A3: № п/п | B3: Ответственный за проведение мероприятия | C3: Вид спорта | D3: Наименование мероприятия | E3: Возраст спортсменов в соответствии с ЕВСК | F3: Дата проведения (начало мероприятия) | G3: Дата проведения (конец мероприятия) | H3: Место проведения | I3: Возраст спортсменов в соответствии с ЕВСК | J3: Начало мероприятия | K3: Конец мероприятия | L3: Количество кубков | U3: Количество медалей | AD3: Грамоты | AG3: Услуги по изготовлению и поставке | AJ3: Итого стоимость, руб. | AM3: сравнение с календарем от 10.06
L4: Количество, шт. | M4: Стоимость 1 | N4: Итого | O4: Количество, шт. | P4: Стоимость 1 | Q4: Итого | R4: Количество, шт. | S4: Стоимость 1 | T4: Итого | U4: Количество, шт. | V4: Стоимость 1 | W4: Итого | X4: Количество, шт. | Y4: Стоимость 1 | Z4: Итого | AA4: Количество, шт. | AB4: Стоимость 1 | AC4: Итого | AD4: Количество, шт. | AE4: Стоимость 1 | AF4: Итого | AG4: Кол-во услуг | AH4: Кол-во ед. | AI4: Нормативные затраты | AM4: наименование | AN4: возраст | AO4: дата начала | AP4: дата конца | AQ4: место проведения
D5: БАДМИНТОН
A6: 1 | B6: КРСОО "Федерация бадминтона" | C6: бадминтон | D6: Первенство Краснодарского края | E6: мальчики, девочки до 15 лет | F6: 44812 | G6: 44815 | H6: г. Кореновск | I6: мальчики, девочки до 15 лет | J6: 44812 | K6: 44815 | M6: 3400 | N6: =L6*M6 -> 0 | P6: 2900 | Q6: =O6*P6 -> 0 | S6: 2800 | T6: =R6*S6 -> 0 | U6: 8 | V6: 150 | W6: =U6*V6 -> 1200 | X6: 8 | Y6: 150 | Z6: =X6*Y6 -> 1200 | AA6: 16 | AB6: 150 | AC6: =AA6*AB6 -> 2400 | AD6: 32 | AE6: 7 | AF6: =AD6*AE6 -> 224 | AG6: 1 | AH6: =L6+O6+R6+U6+X6+AA6+AD6 -> 64 | AI6: =AJ6 -> 5024 | AJ6: =N6+Q6+T6+W6+Z6+AC6+AF6 -> 5024 | AK6: 9 | AM6: =D6='10.06.2022 КП'!D6 -> TRUE | AN6: =E6='10.06.2022 КП'!E6 -> TRUE | AO6: =F6='10.06.2022 КП'!F6 -> TRUE | AP6: =G6='10.06.2022 КП'!G6 -> TRUE | AQ6: =H6='10.06.2022 КП'!H6 -> TRUE
D7: БАСКЕТБОЛ | AM7: =D7='10.06.2022 КП'!D7 -> TRUE | AN7: =E7='10.06.2022 КП'!E7 -> TRUE | AO7: =F7='10.06.2022 КП'!F7 -> TRUE | AP7: =G7='10.06.2022 КП'!G7 -> TRUE | AQ7: =H7='10.06.2022 КП'!H7 -> TRUE
A8: 5 | B8: ГБУ КК "ЦОП по баскетболу" | C8: баскетбол | D8: Краевой турнир по баскетболу «Золотая корзина» среди юношей 2009 г.р. и моложе памяти Е.Д. Турченко | E8: 2009 г.р. и моложе | F8: 44824 | G8: 44829 | H8: г. Краснодар | I8: 2009 г.р. и моложе | J8: 44824 | K8: 44829 | L8: 1 | M8: 3400 | N8: =L8*M8 -> 3400 | O8: 1 | P8: 2900 | Q8: =O8*P8 -> 2900 | R8: 1 | S8: 2800 | T8: =R8*S8 -> 2800 | U8: 14 | V8: 150 | W8: =U8*V8 -> 2100 | X8: 14 | Y8: 150 | Z8: =X8*Y8 -> 2100 | AA8: 14 | AB8: 150 | AC8: =AA8*AB8 -> 2100 | AD8: 45 | AE8: 7 | AF8: =AD8*AE8 -> 315 | AG8: 1 | AH8: =L8+O8+R8+U8+X8+AA8+AD8 -> 90 | AI8: =AJ8 -> 15715 | AJ8: =N8+Q8+T8+W8+Z8+AC8+AF8 -> 15715 | AK8: 9 | AM8: =D8='10.06.2022 КП'!D11 -> TRUE | AN8: =E8='10.06.2022 КП'!E11 -> TRUE | AO8: =F8='10.06.2022 КП'!F11 -> TRUE | AP8: =G8='10.06.2022 КП'!G11 -> TRUE | AQ8: =H8='10.06.2022 КП'!H11 -> TRUE
D9: ВЕЛОСИПЕДНЫЙ СПОРТ | AM9: =D9='10.06.2022 КП'!D21 -> TRUE | AN9: =E9='10.06.2022 КП'!E21 -> TRUE | AO9: =F9='10.06.2022 КП'!F21 -> TRUE | AP9: =G9='10.06.2022 КП'!G21 -> TRUE | AQ9: =H9='10.06.2022 КП'!H21 -> TRUE
A10: 20 | B10: ГБУ КК "ЦОП по велосипедному спорту" | C10: велосипедный спорт | D10: Краевые соревнования, посвященные Дню города Гулькевичи (шоссе) | E10: юноши, девушки 15-16 лет; юноши, девушки 13-14 лет | F10: 44773 | G10: 44773 | H10: г. Гулькевичи | I10: юноши, девушки 15-16 лет; юноши, девушки 13-14 лет | J10: 44773 | K10: 44773 | M10: 3400 | N10: =L10*M10 -> 0 | P10: 2900 | Q10: =O10*P10 -> 0 | S10: 2800 | T10: =R10*S10 -> 0 | U10: 4 | V10: 150 | W10: =U10*V10 -> 600 | X10: 4 | Y10: 150 | Z10: =X10*Y10 -> 600 | AA10: 4 | AB10: 150 | AC10: =AA10*AB10 -> 600 | AD10: 12 | AE10: 7 | AF10: =AD10*AE10 -> 84 | AG10: 1 | AH10: =L10+O10+R10+U10+X10+AA10+AD10 -> 24 | AI10: =AJ10 -> 1884 | AJ10: =N10+Q10+T10+W10+Z10+AC10+AF10 -> 1884 | AK10: 7 | AM10: =D10='10.06.2022 КП'!D29 -> TRUE | AN10: =E10='10.06.2022 КП'!E29 -> TRUE | AO10: =F10='10.06.2022 КП'!F29 -> TRUE | AP10: =G10='10.06.2022 КП'!G29 -> TRUE | AQ10: =H10='10.06.2022 КП'!H29 -> TRUE
A11: 21 | B11: ГБУ КК "ЦОП по велосипедному спорту" | C11: велосипедный спорт | D11: Краевые соревнования, посвященные памяти Заслуженного работника физической культуры и спорта Кубани, тренера по велоспорту В.Ф. Резникова (шоссе) | E11: юноши, девушки 15-16 лет; юноши, девушки 13-14 лет | F11: 44787 | G11: 44787 | H11: г. Армавир | I11: юноши, девушки 15-16 лет; юноши, девушки 13-14 лет | J11: 44787 | K11: 44787 | M11: 3400 | N11: =L11*M11 -> 0 | P11: 2900 | Q11: =O11*P11 -> 0 | S11: 2800 | T11: =R11*S11 -> 0 | U11: 4 | V11: 150 | W11: =U11*V11 -> 600 | X11: 4 | Y11: 150 | Z11: =X11*Y11 -> 600 | AA11: 4 | AB11: 150 | AC11: =AA11*AB11 -> 600 | AD11: 12 | AE11: 7 | AF11: =AD11*AE11 -> 84 | AG11: 1 | AH11: =L11+O11+R11+U11+X11+AA11+AD11 -> 24 | AI11: =AJ11 -> 1884 | AJ11: =N11+Q11+T11+W11+Z11+AC11+AF11 -> 1884 | AK11: 8 | AM11: =D11='10.06.2022 КП'!D30 -> TRUE | AN11: =E11='10.06.2022 КП'!E30 -> TRUE | AO11: =F11='10.06.2022 КП'!F30 -> TRUE | AP11: =G11='10.06.2022 КП'!G30 -> TRUE | AQ11: =H11='10.06.2022 КП'!H30 -> TRUE
A12: 22 | B12: ГБУ КК "ЦОП по велосипедному спорту" | C12: велосипедный спорт | D12: Краевые соревнования в гонке критериум на приз главы администрации Терновского сельского поселения (шоссе) | E12: юноши, девушки 15-16 лет; юноши, девушки 13-14 лет | F12: 44829 | G12: 44829 | H12: ст-ца Терновская (Тихорецкий район) | I12: юноши, девушки 15-16 лет; юноши, девушки 13-14 лет | J12: 44829 | K12: 44829 | M12: 3400 | N12: =L12*M12 -> 0 | P12: 2900 | Q12: =O12*P12 -> 0 | S12: 2800 | T12: =R12*S12 -> 0 | U12: 4 | V12: 150 | W12: =U12*V12 -> 600 | X12: 4 | Y12: 150 | Z12: =X12*Y12 -> 600 | AA12: 4 | AB12: 150 | AC12: =AA12*AB12 -> 600 | AD12: 12 | AE12: 7 | AF12: =AD12*AE12 -> 84 | AG12: 1 | AH12: =L12+O12+R12+U12+X12+AA12+AD12 -> 24 | AI12: =AJ12 -> 1884 | AJ12: =N12+Q12+T12+W12+Z12+AC12+AF12 -> 1884 | AK12: 9 | AM12: =D12='10.06.2022 КП'!D31 -> TRUE | AN12: =E12='10.06.2022 КП'!E31 -> TRUE | AO12: =F12='10.06.2022 КП'!F31 -> TRUE | AP12: =G12='10.06.2022 КП'!G31 -> TRUE | AQ12: =H12='10.06.2022 КП'!H31 -> TRUE
D13: ВОЛЕЙБОЛ | AM13: =D13='10.06.2022 КП'!D36 -> TRUE | AN13: =E13='10.06.2022 КП'!E36 -> TRUE | AO13: =F13='10.06.2022 КП'!F36 -> TRUE | AP13: =G13='10.06.2022 КП'!G36 -> TRUE | AQ13: =H13='10.06.2022 КП'!H36 -> TRUE
A14: 33 | B14: ГБУ КК "ЦОП по пляжным видам спорта" | C14: волейбол | D14: Первенство Краснодарского края по пляжному волейболу среди юношей и девушек до 15 лет | E14: юноши, девушки (до 15 лет) | F14: 44765 | G14: 44768 | H14: с. Витязево (г. Анапа) | I14: юноши, девушки (до 15 лет) | J14: 44763 | K14: 44766 | L14: 2 | M14: 3400 | N14: =L14*M14 -> 6800 | O14: 2 | P14: 2900 | Q14: =O14*P14 -> 5800 | R14: 2 | S14: 2800 | T14: =R14*S14 -> 5600 | U14: 6 | V14: 150 | W14: =U14*V14 -> 900 | X14: 6 | Y14: 150 | Z14: =X14*Y14 -> 900 | AA14: 6 | AB14: 150 | AC14: =AA14*AB14 -> 900 | AD14: 24 | AE14: 7 | AF14: =AD14*AE14 -> 168 | AG14: 1 | AH14: =L14+O14+R14+U14+X14+AA14+AD14 -> 48 | AI14: =AJ14 -> 21068 | AJ14: =N14+Q14+T14+W14+Z14+AC14+AF14 -> 21068 | AK14: 7 | AM14: =D14='10.06.2022 КП'!D44 -> TRUE | AN14: =E14='10.06.2022 КП'!E44 -> TRUE | AO14: =F14='10.06.2022 КП'!F44 -> FALSE | AP14: =G14='10.06.2022 КП'!G44 -> FALSE | AQ14: =H14='10.06.2022 КП'!H44 -> TRUE
A15: 34 | B15: ГБУ КК "ЦОП по пляжным видам спорта" | C15: волейбол | D15: Первенство Краснодарского края по пляжному волейболу среди юношей и девушек до 17 лет | E15: юноши, девушки (до 17 лет) | F15: 44780 | G15: 44783 | H15: с. Витязево (г. Анапа) | I15: юноши, девушки (до 17 лет) | J15: 44766 | K15: 44769 | L15: 2 | M15: 3400 | N15: =L15*M15 -> 6800 | O15: 2 | P15: 2900 | Q15: =O15*P15 -> 5800 | R15: 2 | S15: 2800 | T15: =R15*S15 -> 5600 | U15: 6 | V15: 150 | W15: =U15*V15 -> 900 | X15: 6 | Y15: 150 | Z15: =X15*Y15 -> 900 | AA15: 6 | AB15: 150 | AC15: =AA15*AB15 -> 900 | AD15: 24 | AE15: 7 | AF15: =AD15*AE15 -> 168 | AG15: 1 | AH15: =L15+O15+R15+U15+X15+AA15+AD15 -> 48 | AI15: =AJ15 -> 21068 | AJ15: =N15+Q15+T15+W15+Z15+AC15+AF15 -> 21068 | AK15: 8 | AM15: =D15='10.06.2022 КП'!D45 -> TRUE | AN15: =E15='10.06.2022 КП'!E45 -> TRUE | AO15: =F15='10.06.2022 КП'!F45 -> FALSE | AP15: =G15='10.06.2022 КП'!G45 -> FALSE | AQ15: =H15='10.06.2022 КП'!H45 -> TRUE
A16: 35 | B16: ГБУ КК "ЦОП по пляжным видам спорта" | C16: волейбол | D16: Краевые соревнования по пляжному волейболу среди юношей и девушек до 15 лет | E16: юноши, девушки (до 15 лет) | F16: 44798 | G16: 44801 | H16: с. Витязево (г. Анапа) | I16: юноши, девушки (до 15 лет) | J16: 44803 | K16: 44806 | L16: 2 | M16: 3400 | N16: =L16*M16 -> 6800 | O16: 2 | P16: 2900 | Q16: =O16*P16 -> 5800 | R16: 2 | S16: 2800 | T16: =R16*S16 -> 5600 | U16: 6 | V16: 150 | W16: =U16*V16 -> 900 | X16: 6 | Y16: 150 | Z16: =X16*Y16 -> 900 | AA16: 6 | AB16: 150 | AC16: =AA16*AB16 -> 900 | AD16: 24 | AE16: 7 | AF16: =AD16*AE16 -> 168 | AG16: 1 | AH16: =L16+O16+R16+U16+X16+AA16+AD16 -> 48 | AI16: =AJ16 -> 21068 | AJ16: =N16+Q16+T16+W16+Z16+AC16+AF16 -> 21068 | AK16: 8 | AM16: =D16='10.06.2022 КП'!D46 -> TRUE | AN16: =E16='10.06.2022 КП'!E46 -> TRUE | AO16: =F16='10.06.2022 КП'!F46 -> FALSE | AP16: =G16='10.06.2022 КП'!G46 -> FALSE | AQ16: =H16='10.06.2022 КП'!H46 -> TRUE
A17: 36 | B17: ГБУ КК "ЦОП по пляжным видам спорта" | C17: волейбол | D17: Кубок Краснодарского края по пляжному волейболу | E17: мужчины, женщины | F17: 44801 | G17: 44804 | H17: с. Витязево (г. Анапа) | I17: мужчины, женщины | J17: 44806 | K17: 44809 | L17: 2 | M17: 3400 | N17: =L17*M17 -> 6800 | O17: 2 | P17: 2900 | Q17: =O17*P17 -> 5800 | R17: 2 | S17: 2800 | T17: =R17*S17 -> 5600 | U17: 6 | V17: 150 | W17: =U17*V17 -> 900 | X17: 6 | Y17: 150 | Z17: =X17*Y17 -> 900 | AA17: 6 | AB17: 150 | AC17: =AA17*AB17 -> 900 | AD17: 24 | AE17: 7 | AF17: =AD17*AE17 -> 168 | AG17: 1 | AH17: =L17+O17+R17+U17+X17+AA17+AD17 -> 48 | AI17: =AJ17 -> 21068 | AJ17: =N17+Q17+T17+W17+Z17+AC17+AF17 -> 21068 | AK17: 8 | AM17: =D17='10.06.2022 КП'!D47 -> TRUE | AN17: =E17='10.06.2022 КП'!E47 -> TRUE | AO17: =F17='10.06.2022 КП'!F47 -> FALSE | AP17: =G17='10.06.2022 КП'!G47 -> FALSE | AQ17: =H17='10.06.2022 КП'!H47 -> TRUE
A18: 37 | B18: ГБУ КК "ЦОП по волейболу" | C18: волейбол | D18: Первенство Краснодарского края по волейболу среди юношей до 18 лет | E18: юноши (до 18 лет) | F18: 44817 | G18: 44822 | H18: пгт Ильский (Северский район) | I18: юноши (до 18 лет) | J18: 44817 | K18: 44822 | L18: 1 | M18: 3400 | N18: =L18*M18 -> 3400 | O18: 1 | P18: 2900 | Q18: =O18*P18 -> 2900 | R18: 1 | S18: 2800 | T18: =R18*S18 -> 2800 | U18: 14 | V18: 150 | W18: =U18*V18 -> 2100 | X18: 14 | Y18: 150 | Z18: =X18*Y18 -> 2100 | AA18: 14 | AB18: 150 | AC18: =AA18*AB18 -> 2100 | AD18: 45 | AE18: 7 | AF18: =AD18*AE18 -> 315 | AG18: 1 | AH18: =L18+O18+R18+U18+X18+AA18+AD18 -> 90 | AI18: =AJ18 -> 15715 | AJ18: =N18+Q18+T18+W18+Z18+AC18+AF18 -> 15715 | AK18: 9 | AM18: =D18='10.06.2022 КП'!D48 -> TRUE | AN18: =E18='10.06.2022 КП'!E48 -> TRUE | AO18: =F18='10.06.2022 КП'!F48 -> TRUE | AP18: =G18='10.06.2022 КП'!G48 -> TRUE | AQ18: =H18='10.06.2022 КП'!H48 -> TRUE
A19: 38 | B19: ГБУ КК "ЦОП по волейболу" | C19: волейбол | D19: Первенство Краснодарского края по волейболу среди девушек до 18 лет | E19: девушки (до 18 лет) | F19: 44824 | G19: 44829 | H19: пгт Ильский (Северский район) | I19: девушки (до 18 лет) | J19: 44824 | K19: 44829 | L19: 1 | M19: 3400 | N19: =L19*M19 -> 3400 | O19: 1 | P19: 2900 | Q19: =O19*P19 -> 2900 | R19: 1 | S19: 2800 | T19: =R19*S19 -> 2800 | U19: 14 | V19: 150 | W19: =U19*V19 -> 2100 | X19: 14 | Y19: 150 | Z19: =X19*Y19 -> 2100 | AA19: 14 | AB19: 150 | AC19: =AA19*AB19 -> 2100 | AD19: 45 | AE19: 7 | AF19: =AD19*AE19 -> 315 | AG19: 1 | AH19: =L19+O19+R19+U19+X19+AA19+AD19 -> 90 | AI19: =AJ19 -> 15715 | AJ19: =N19+Q19+T19+W19+Z19+AC19+AF19 -> 15715 | AK19: 9 | AM19: =D19='10.06.2022 КП'!D49 -> TRUE | AN19: =E19='10.06.2022 КП'!E49 -> TRUE | AO19: =F19='10.06.2022 КП'!F49 -> TRUE | AP19: =G19='10.06.2022 КП'!G49 -> TRUE | AQ19: =H19='10.06.2022 КП'!H49 -> TRUE
A20: 39 | C20: волейбол | D20: Первенство Краснодарского края по волейболу среди юношей до 16 лет | E20: юноши (до 16 лет) | F20: 44831 | G20: 44836 | H20: г. Лабинск | I20: юноши (до 16 лет) | J20: 44831 | K20: 44836 | U20: 15 | V20: 150 | W20: =U20*V20 -> 2250 | X20: 15 | Y20: 150 | Z20: =X20*Y20 -> 2250 | AA20: 15 | AB20: 150 | AC20: =AA20*AB20 -> 2250 | AD20: 45 | AE20: 7 | AF20: =AD20*AE20 -> 315 | AG20: 1 | AH20: =L20+O20+R20+U20+X20+AA20+AD20 -> 90 | AI20: =AJ20 -> 7065 | AJ20: =N20+Q20+T20+W20+Z20+AC20+AF20 -> 7065 | AK20: 9 | AM20: =D20='10.06.2022 КП'!D50 -> TRUE | AN20: =E20='10.06.2022 КП'!E50 -> TRUE | AO20: =F20='10.06.2022 КП'!F50 -> TRUE | AP20: =G20='10.06.2022 КП'!G50 -> TRUE | AQ20: =H20='10.06.2022 КП'!H50 -> TRUE
D21: ГАНДБОЛ | AM21: =D21='10.06.2022 КП'!D51 -> TRUE | AN21: =E21='10.06.2022 КП'!E51 -> TRUE | AO21: =F21='10.06.2022 КП'!F51 -> TRUE | AP21: =G21='10.06.2022 КП'!G51 -> TRUE | AQ21: =H21='10.06.2022 КП'!H51 -> TRUE
A22: 45 | B22: ГБУ КК "ЦОП по пляжным видам спорта" | C22: гандбол | D22: Первенство Краснодарского края по пляжному гандболу | E22: юноши, девушки до 17 лет | F22: 44761 | G22: 44764 | H22: ст-ца Павловская (Павловский район) | I22: юноши, девушки до 17 лет | J22: 44761 | K22: 44764 | L22: 2 | M22: 3400 | N22: =L22*M22 -> 6800 | O22: 2 | P22: 2900 | Q22: =O22*P22 -> 5800 | R22: 2 | S22: 2800 | T22: =R22*S22 -> 5600 | U22: 26 | V22: 150 | W22: =U22*V22 -> 3900 | X22: 26 | Y22: 150 | Z22: =X22*Y22 -> 3900 | AA22: 26 | AB22: 150 | AC22: =AA22*AB22 -> 3900 | AD22: 84 | AE22: 7 | AF22: =AD22*AE22 -> 588 | AG22: 1 | AH22: =L22+O22+R22+U22+X22+AA22+AD22 -> 168 | AI22: =AJ22 -> 30488 | AJ22: =N22+Q22+T22+W22+Z22+AC22+AF22 -> 30488 | AK22: 7 | AM22: =D22='10.06.2022 КП'!D57 -> TRUE | AN22: =E22='10.06.2022 КП'!E57 -> TRUE | AO22: =F22='10.06.2022 КП'!F57 -> TRUE | AP22: =G22='10.06.2022 КП'!G57 -> TRUE | AQ22: =H22='10.06.2022 КП'!H57 -> FALSE
A23: 46 | B23: ГБУ КК "ЦОП по пляжным видам спорта" | C23: гандбол | D23: Первенство Краснодарского края по пляжному гандболу | E23: юноши, девушки до 16 лет | F23: 44796 | G23: 44799 | H23: ст-ца Павловская (Павловский район) | I23: юноши, девушки до 16 лет | J23: 44796 | K23: 44799 | L23: 2 | M23: 3400 | N23: =L23*M23 -> 6800 | O23: 2 | P23: 2900 | Q23: =O23*P23 -> 5800 | R23: 2 | S23: 2800 | T23: =R23*S23 -> 5600 | U23: 26 | V23: 150 | W23: =U23*V23 -> 3900 | X23: 26 | Y23: 150 | Z23: =X23*Y23 -> 3900 | AA23: 26 | AB23: 150 | AC23: =AA23*AB23 -> 3900 | AD23: 84 | AE23: 7 | AF23: =AD23*AE23 -> 588 | AG23: 1 | AH23: =L23+O23+R23+U23+X23+AA23+AD23 -> 168 | AI23: =AJ23 -> 30488 | AJ23: =N23+Q23+T23+W23+Z23+AC23+AF23 -> 30488 | AK23: 8 | AM23: =D23='10.06.2022 КП'!D58 -> TRUE | AN23: =E23='10.06.2022 КП'!E58 -> TRUE | AO23: =F23='10.06.2022 КП'!F58 -> TRUE | AP23: =G23='10.06.2022 КП'!G58 -> TRUE | AQ23: =H23='10.06.2022 КП'!H58 -> FALSE
A24: 47 | B24: ГБУ КК "ЦОП № 1"/КРОО "Федерация гандбола" | C24: гандбол | D24: Первенство Краснодарского края по гандболу | E24: юноши до 15 лет | F24: 44810 | G24: 44813 | H24: ст-ца Павловская (Павловский район) | I24: юноши до 15 лет | J24: 44810 | K24: 44813 | L24: 1 | M24: 3400 | N24: =L24*M24 -> 3400 | O24: 1 | P24: 2900 | Q24: =O24*P24 -> 2900 | R24: 1 | S24: 2800 | T24: =R24*S24 -> 2800 | U24: 18 | V24: 150 | W24: =U24*V24 -> 2700 | X24: 18 | Y24: 150 | Z24: =X24*Y24 -> 2700 | AA24: 18 | AB24: 150 | AC24: =AA24*AB24 -> 2700 | AD24: 54 | AE24: 7 | AF24: =AD24*AE24 -> 378 | AG24: 1 | AH24: =L24+O24+R24+U24+X24+AA24+AD24 -> 111 | AI24: =AJ24 -> 17578 | AJ24: =N24+Q24+T24+W24+Z24+AC24+AF24 -> 17578 | AK24: 9 | AM24: =D24='10.06.2022 КП'!D59 -> TRUE | AN24: =E24='10.06.2022 КП'!E59 -> TRUE | AO24: =F24='10.06.2022 КП'!F59 -> TRUE | AP24: =G24='10.06.2022 КП'!G59 -> TRUE | AQ24: =H24='10.06.2022 КП'!H59 -> TRUE
A25: 48 | C25: гандбол | D25: Первенство Краснодарского края по гандболу | E25: девушки до 15 лет | F25: 44831 | G25: 44834 | H25: г. Тимашевск | I25: девушки до 15 лет | J25: 44831 | K25: 44834 | L25: 1 | M25: 3400 | N25: =L25*M25 -> 3400 | O25: 1 | P25: 2900 | Q25: =O25*P25 -> 2900 | R25: 1 | S25: 2800 | T25: =R25*S25 -> 2800 | U25: 18 | V25: 150 | W25: =U25*V25 -> 2700 | X25: 18 | Y25: 150 | Z25: =X25*Y25 -> 2700 | AA25: 18 | AB25: 150 | AC25: =AA25*AB25 -> 2700 | AD25: 54 | AE25: 7 | AF25: =AD25*AE25 -> 378 | AG25: 1 | AH25: =L25+O25+R25+U25+X25+AA25+AD25 -> 111 | AI25: =AJ25 -> 17578 | AJ25: =N25+Q25+T25+W25+Z25+AC25+AF25 -> 17578 | AK25: 9 | AM25: =D25='10.06.2022 КП'!D60 -> TRUE | AN25: =E25='10.06.2022 КП'!E60 -> TRUE | AO25: =F25='10.06.2022 КП'!F60 -> TRUE | AP25: =G25='10.06.2022 КП'!G60 -> TRUE | AQ25: =H25='10.06.2022 КП'!H60 -> TRUE
D26: ГРЕБЛЯ НА БАЙДАРКАХ И КАНОЭ | AM26: =D26='10.06.2022 КП'!D61 -> TRUE | AN26: =E26='10.06.2022 КП'!E61 -> TRUE | AO26: =F26='10.06.2022 КП'!F61 -> TRUE | AP26: =G26='10.06.2022 КП'!G61 -> TRUE | AQ26: =H26='10.06.2022 КП'!H61 -> TRUE
A27: 51 | B27: ГБУ КК "ЦОП по гребле на байдарках и каноэ" | C27: гребля на байдарках и каноэ | D27: Первенство Краснодарского края | E27: юноши, девушки до 17 лет | F27: 44753 | G27: 44756 | H27: г. Краснодар | I27: юноши, девушки до 17 лет | J27: 44753 | K27: 44756 | M27: 3400 | N27: =L27*M27 -> 0 | P27: 2900 | Q27: =O27*P27 -> 0 | S27: 2800 | T27: =R27*S27 -> 0 | U27: 81 | V27: 150 | W27: =U27*V27 -> 12150 | X27: 81 | Y27: 150 | Z27: =X27*Y27 -> 12150 | AA27: 81 | AB27: 150 | AC27: =AA27*AB27 -> 12150 | AD27: 243 | AE27: 7 | AF27: =AD27*AE27 -> 1701 | AG27: 1 | AH27: =L27+O27+R27+U27+X27+AA27+AD27 -> 486 | AI27: =AJ27 -> 38151 | AJ27: =N27+Q27+T27+W27+Z27+AC27+AF27 -> 38151 | AK27: 7 | AM27: =D27='10.06.2022 КП'!D64 -> TRUE | AN27: =E27='10.06.2022 КП'!E64 -> TRUE | AO27: =F27='10.06.2022 КП'!F64 -> TRUE | AP27: =G27='10.06.2022 КП'!G64 -> TRUE | AQ27: =H27='10.06.2022 КП'!H64 -> TRUE
A28: 52 | B28: ГБУ КК "ЦОП по гребле на байдарках и каноэ" | C28: гребля на байдарках и каноэ | D28: Первенство Краснодарского края | E28: юноши, девушки до 15 лет | F28: 44756 | G28: 44760 | H28: г. Краснодар | I28: юноши, девушки до 15 лет | J28: 44756 | K28: 44760 | M28: 3400 | N28: =L28*M28 -> 0 | P28: 2900 | Q28: =O28*P28 -> 0 | S28: 2800 | T28: =R28*S28 -> 0 | U28: 81 | V28: 150 | W28: =U28*V28 -> 12150 | X28: 81 | Y28: 150 | Z28: =X28*Y28 -> 12150 | AA28: 81 | AB28: 150 | AC28: =AA28*AB28 -> 12150 | AD28: 243 | AE28: 7 | AF28: =AD28*AE28 -> 1701 | AG28: 1 | AH28: =L28+O28+R28+U28+X28+AA28+AD28 -> 486 | AI28: =AJ28 -> 38151 | AJ28: =N28+Q28+T28+W28+Z28+AC28+AF28 -> 38151 | AK28: 7 | AM28: =D28='10.06.2022 КП'!D65 -> TRUE | AN28: =E28='10.06.2022 КП'!E65 -> TRUE | AO28: =F28='10.06.2022 КП'!F65 -> TRUE | AP28: =G28='10.06.2022 КП'!G65 -> TRUE | AQ28: =H28='10.06.2022 КП'!H65 -> TRUE
A29: 53 | B29: ГБУ КК "ЦОП по гребле на байдарках и каноэ" | C29: гребля на байдарках и каноэ | D29: Кубок Краснодарского края (мужчины,женщины) | E29: мужчины, женщины | F29: 44774 | G29: 44777 | H29: г. Краснодар | I29: мужчины, женщины | J29: 44774 | K29: 44777 | L29: 11 | M29: 3400 | N29: =L29*M29 -> 37400 | O29: 11 | P29: 2900 | Q29: =O29*P29 -> 31900 | R29: 11 | S29: 2800 | T29: =R29*S29 -> 30800 | U29: 45 | V29: 150 | W29: =U29*V29 -> 6750 | X29: 45 | Y29: 150 | Z29: =X29*Y29 -> 6750 | AA29: 45 | AB29: 150 | AC29: =AA29*AB29 -> 6750 | AD29: 135 | AE29: 7 | AF29: =AD29*AE29 -> 945 | AG29: 1 | AH29: =L29+O29+R29+U29+X29+AA29+AD29 -> 303 | AI29: =AJ29 -> 121295 | AJ29: =N29+Q29+T29+W29+Z29+AC29+AF29 -> 121295 | AK29: 8 | AM29: =D29='10.06.2022 КП'!D66 -> TRUE | AN29: =E29='10.06.2022 КП'!E66 -> TRUE | AO29: =F29='10.06.2022 КП'!F66 -> TRUE | AP29: =G29='10.06.2022 КП'!G66 -> TRUE | AQ29: =H29='10.06.2022 КП'!H66 -> TRUE
A30: 54 | B30: ГБУ КК "ЦОП по гребле на байдарках и каноэ" | C30: гребля на байдарках и каноэ | D30: Первенство Краснодарского края (марафон) | E30: юниоры, юниорки до 19 лет | F30: 44790 | G30: 44792 | H30: г. Тимашевск | I30: юниоры, юниорки до 19 лет | J30: 44790 | K30: 44792 | M30: 3400 | N30: =L30*M30 -> 0 | P30: 2900 | Q30: =O30*P30 -> 0 | S30: 2800 | T30: =R30*S30 -> 0 | U30: 12 | V30: 150 | W30: =U30*V30 -> 1800 | X30: 12 | Y30: 150 | Z30: =X30*Y30 -> 1800 | AA30: 12 | AB30: 150 | AC30: =AA30*AB30 -> 1800 | AD30: 36 | AE30: 7 | AF30: =AD30*AE30 -> 252 | AG30: 1 | AH30: =L30+O30+R30+U30+X30+AA30+AD30 -> 72 | AI30: =AJ30 -> 5652 | AJ30: =N30+Q30+T30+W30+Z30+AC30+AF30 -> 5652 | AK30: 8 | AM30: =D30='10.06.2022 КП'!D67 -> TRUE | AN30: =E30='10.06.2022 КП'!E67 -> TRUE | AO30: =F30='10.06.2022 КП'!F67 -> TRUE | AP30: =G30='10.06.2022 КП'!G67 -> TRUE | AQ30: =H30='10.06.2022 КП'!H67 -> TRUE
D31: ГРЕБНОЙ СПОРТ | AM31: =D31='10.06.2022 КП'!D68 -> TRUE | AN31: =E31='10.06.2022 КП'!E68 -> TRUE | AO31: =F31='10.06.2022 КП'!F68 -> TRUE | AP31: =G31='10.06.2022 КП'!G68 -> TRUE | AQ31: =H31='10.06.2022 КП'!H68 -> TRUE
A32: 60 | B32: ГБУ КК "ЦОП гребного спорта" | C32: гребной спорт | D32: Первенство Краснодарского края | E32: 2004-2007 г.г.р. | F32: 44805 | G32: 44807 | H32: г. Краснодар | I32: 2004-2007 г.г.р. | J32: 44805 | K32: 44807 | M32: 3400 | N32: =L32*M32 -> 0 | P32: 2900 | Q32: =O32*P32 -> 0 | S32: 2800 | T32: =R32*S32 -> 0 | U32: 54 | V32: 150 | W32: =U32*V32 -> 8100 | X32: 54 | Y32: 150 | Z32: =X32*Y32 -> 8100 | AA32: 54 | AB32: 150 | AC32: =AA32*AB32 -> 8100 | AD32: 162 | AE32: 7 | AF32: =AD32*AE32 -> 1134 | AG32: 1 | AH32: =L32+O32+R32+U32+X32+AA32+AD32 -> 324 | AI32: =AJ32 -> 25434 | AJ32: =N32+Q32+T32+W32+Z32+AC32+AF32 -> 25434 | AK32: 9 | AM32: =D32='10.06.2022 КП'!D74 -> TRUE | AN32: =E32='10.06.2022 КП'!E74 -> TRUE | AO32: =F32='10.06.2022 КП'!F74 -> TRUE | AP32: =G32='10.06.2022 КП'!G74 -> TRUE | AQ32: =H32='10.06.2022 КП'!H74 -> TRUE
A33: 61 | B33: ГБУ КК "ЦОП гребного спорта" | C33: гребной спорт | D33: Первенство Краснодарского края | E33: 2000-2007 г.г.р. | F33: 44807 | G33: 44809 | H33: г. Краснодар | I33: 2000-2007 г.г.р. | J33: 44807 | K33: 44809 | M33: 3400 | N33: =L33*M33 -> 0 | P33: 2900 | Q33: =O33*P33 -> 0 | S33: 2800 | T33: =R33*S33 -> 0 | U33: 80 | V33: 150 | W33: =U33*V33 -> 12000 | X33: 80 | Y33: 150 | Z33: =X33*Y33 -> 12000 | AA33: 80 | AB33: 150 | AC33: =AA33*AB33 -> 12000 | AD33: 240 | AE33: 7 | AF33: =AD33*AE33 -> 1680 | AG33: 1 | AH33: =L33+O33+R33+U33+X33+AA33+AD33 -> 480 | AI33: =AJ33 -> 37680 | AJ33: =N33+Q33+T33+W33+Z33+AC33+AF33 -> 37680 | AK33: 9 | AM33: =D33='10.06.2022 КП'!D75 -> TRUE | AN33: =E33='10.06.2022 КП'!E75 -> TRUE | AO33: =F33='10.06.2022 КП'!F75 -> TRUE | AP33: =G33='10.06.2022 КП'!G75 -> TRUE | AQ33: =H33='10.06.2022 КП'!H75 -> TRUE
A34: 62 | B34: ГБУ КК "ЦОП гребного спорта" | C34: гребной спорт | D34: Краевые соревнования | E34: 2009-2012 г.г.р. | F34: 44826 | G34: 44829 | H34: г. Краснодар | I34: 2009-2012 г.г.р. | J34: 44826 | K34: 44829 | M34: 3400 | N34: =L34*M34 -> 0 | P34: 2900 | Q34: =O34*P34 -> 0 | S34: 2800 | T34: =R34*S34 -> 0 | U34: 26 | V34: 150 | W34: =U34*V34 -> 3900 | X34: 26 | Y34: 150 | Z34: =X34*Y34 -> 3900 | AA34: 26 | AB34: 150 | AC34: =AA34*AB34 -> 3900 | AD34: 78 | AE34: 7 | AF34: =AD34*AE34 -> 546 | AG34: 1 | AH34: =L34+O34+R34+U34+X34+AA34+AD34 -> 156 | AI34: =AJ34 -> 12246 | AJ34: =N34+Q34+T34+W34+Z34+AC34+AF34 -> 12246 | AK34: 9 | AM34: =D34='10.06.2022 КП'!D76 -> TRUE | AN34: =E34='10.06.2022 КП'!E76 -> TRUE | AO34: =F34='10.06.2022 КП'!F76 -> TRUE | AP34: =G34='10.06.2022 КП'!G76 -> TRUE | AQ34: =H34='10.06.2022 КП'!H76 -> TRUE
A35: 63 | B35: ГБУ КК "ЦОП гребного спорта" | C35: гребной спорт | D35: Краевые соревнования "Надежды Кубани" | E35: 2008 г.р. и старше | F35: 44826 | G35: 44829 | H35: г. Краснодар | I35: 2008 г.р. и старше | J35: 44826 | K35: 44829 | M35: 3400 | N35: =L35*M35 -> 0 | P35: 2900 | Q35: =O35*P35 -> 0 | S35: 2800 | T35: =R35*S35 -> 0 | U35: 32 | V35: 150 | W35: =U35*V35 -> 4800 | X35: 32 | Y35: 150 | Z35: =X35*Y35 -> 4800 | AA35: 32 | AB35: 150 | AC35: =AA35*AB35 -> 4800 | AD35: 96 | AE35: 7 | AF35: =AD35*AE35 -> 672 | AG35: 1 | AH35: =L35+O35+R35+U35+X35+AA35+AD35 -> 192 | AI35: =AJ35 -> 15072 | AJ35: =N35+Q35+T35+W35+Z35+AC35+AF35 -> 15072 | AK35: 9 | AM35: =D35='10.06.2022 КП'!D77 -> TRUE | AN35: =E35='10.06.2022 КП'!E77 -> TRUE | AO35: =F35='10.06.2022 КП'!F77 -> TRUE | AP35: =G35='10.06.2022 КП'!G77 -> TRUE | AQ35: =H35='10.06.2022 КП'!H77 -> TRUE
D36: ГРЕБНОЙ СЛАЛОМ | AM36: =D36='10.06.2022 КП'!D78 -> TRUE | AN36: =E36='10.06.2022 КП'!E78 -> TRUE | AO36: =F36='10.06.2022 КП'!F78 -> TRUE | AP36: =G36='10.06.2022 КП'!G78 -> TRUE | AQ36: =H36='10.06.2022 КП'!H78 -> TRUE
A37: 67 | B37: КОО ФГСКК | C37: гребной слалом | D37: Первенство Краснодарского края | E37: юноши, девушки до 15 лет | F37: 44743 | G37: 44748 | H37: пос. Никитино (Мостовский район) | I37: юноши, девушки до 15 лет | J37: 44743 | K37: 44748 | M37: 3400 | N37: =L37*M37 -> 0 | P37: 2900 | Q37: =O37*P37 -> 0 | S37: 2800 | T37: =R37*S37 -> 0 | U37: 20 | V37: 150 | W37: =U37*V37 -> 3000 | X37: 20 | Y37: 150 | Z37: =X37*Y37 -> 3000 | AA37: 20 | AB37: 150 | AC37: =AA37*AB37 -> 3000 | AD37: 60 | AE37: 7 | AF37: =AD37*AE37 -> 420 | AG37: 1 | AH37: =L37+O37+R37+U37+X37+AA37+AD37 -> 120 | AI37: =AJ37 -> 9420 | AJ37: =N37+Q37+T37+W37+Z37+AC37+AF37 -> 9420 | AK37: 7 | AM37: =D37='10.06.2022 КП'!D82 -> TRUE | AN37: =E37='10.06.2022 КП'!E82 -> TRUE | AO37: =F37='10.06.2022 КП'!F82 -> TRUE | AP37: =G37='10.06.2022 КП'!G82 -> TRUE | AQ37: =H37='10.06.2022 КП'!H82 -> TRUE
A38: 68 | B38: КОО ФГСКК | C38: гребной слалом | D38: Первенство Краснодарского края | E38: мальчики, девочки до 13 лет | F38: 44748 | G38: 44752 | H38: пос. Никитино (Мостовский район) | I38: мальчики, девочки до 13 лет | J38: 44748 | K38: 44752 | M38: 3400 | N38: =L38*M38 -> 0 | P38: 2900 | Q38: =O38*P38 -> 0 | S38: 2800 | T38: =R38*S38 -> 0 | U38: 20 | V38: 150 | W38: =U38*V38 -> 3000 | X38: 20 | Y38: 150 | Z38: =X38*Y38 -> 3000 | AA38: 20 | AB38: 150 | AC38: =AA38*AB38 -> 3000 | AD38: 60 | AE38: 7 | AF38: =AD38*AE38 -> 420 | AG38: 1 | AH38: =L38+O38+R38+U38+X38+AA38+AD38 -> 120 | AI38: =AJ38 -> 9420 | AJ38: =N38+Q38+T38+W38+Z38+AC38+AF38 -> 9420 | AK38: 7 | AM38: =D38='10.06.2022 КП'!D83 -> TRUE | AN38: =E38='10.06.2022 КП'!E83 -> TRUE | AO38: =F38='10.06.2022 КП'!F83 -> TRUE | AP38: =G38='10.06.2022 КП'!G83 -> TRUE | AQ38: =H38='10.06.2022 КП'!H83 -> TRUE
D39: ДЗЮДО | AM39: =D39='10.06.2022 КП'!D84 -> TRUE | AN39: =E39='10.06.2022 КП'!E84 -> TRUE | AO39: =F39='10.06.2022 КП'!F84 -> TRUE | AP39: =G39='10.06.2022 КП'!G84 -> TRUE | AQ39: =H39='10.06.2022 КП'!H84 -> TRUE
A40: 73 | B40: ГБУ КК "ЦОП по самбо и дзюдо"/ КРСОО "Федерация дзюдо" | C40: дзюдо | D40: Первенство Краснодарского края по дзюдо среди юниоров и юниорок до 21 года | E40: юниоры, юниорки (до 21 года) | F40: 44818 | G40: 44821 | H40: г. Армавир | I40: юниоры, юниорки (до 21 года) | J40: 44818 | K40: 44821 | M40: 3400 | N40: =L40*M40 -> 0 | P40: 2900 | Q40: =O40*P40 -> 0 | S40: 2800 | T40: =R40*S40 -> 0 | U40: 18 | V40: 150 | W40: =U40*V40 -> 2700 | X40: 18 | Y40: 150 | Z40: =X40*Y40 -> 2700 | AA40: 34 | AB40: 150 | AC40: =AA40*AB40 -> 5100 | AD40: 70 | AE40: 7 | AF40: =AD40*AE40 -> 490 | AG40: 1 | AH40: =L40+O40+R40+U40+X40+AA40+AD40 -> 140 | AI40: =AJ40 -> 10990 | AJ40: =N40+Q40+T40+W40+Z40+AC40+AF40 -> 10990 | AK40: 9 | AM40: =D40='10.06.2022 КП'!D89 -> TRUE | AN40: =E40='10.06.2022 КП'!E89 -> TRUE | AO40: =F40='10.06.2022 КП'!F89 -> TRUE | AP40: =G40='10.06.2022 КП'!G89 -> TRUE | AQ40: =H40='10.06.2022 КП'!H89 -> TRUE
D41: КАРАТЭ | AM41: =D41='10.06.2022 КП'!D90 -> TRUE | AN41: =E41='10.06.2022 КП'!E90 -> TRUE | AO41: =F41='10.06.2022 КП'!F90 -> TRUE | AP41: =G41='10.06.2022 КП'!G90 -> TRUE | AQ41: =H41='10.06.2022 КП'!H90 -> TRUE
D42: КОННЫЙ СПОРТ | AM42: =D42='10.06.2022 КП'!D92 -> TRUE | AN42: =E42='10.06.2022 КП'!E92 -> TRUE | AO42: =F42='10.06.2022 КП'!F92 -> TRUE | AP42: =G42='10.06.2022 КП'!G92 -> TRUE | AQ42: =H42='10.06.2022 КП'!H92 -> TRUE
A43: 88 | B43: ГБУ КК "СШОР по конному спорту"/РОО "Федерация конного спорта Краснодарского края" | C43: конный спорт | D43: Краевые соревнования по конкуру на приз Законодательного Собрания Краснодарского края | E43: мальчики и девочки юноши и девушки мужчины и женщины | F43: 44819 | G43: 44822 | H43: пос. Южный (Динской район) | I43: мальчики и девочки юноши и девушки мужчины и женщины | J43: 44819 | K43: 44822 | M43: 3400 | N43: =L43*M43 -> 0 | P43: 2900 | Q43: =O43*P43 -> 0 | S43: 2800 | T43: =R43*S43 -> 0 | U43: 32 | V43: 150 | W43: =U43*V43 -> 4800 | X43: 24 | Y43: 150 | Z43: =X43*Y43 -> 3600 | AA43: 24 | AB43: 150 | AC43: =AA43*AB43 -> 3600 | AD43: 96 | AE43: 7 | AF43: =AD43*AE43 -> 672 | AG43: 1 | AH43: =L43+O43+R43+U43+X43+AA43+AD43 -> 176 | AI43: =AJ43 -> 12672 | AJ43: =N43+Q43+T43+W43+Z43+AC43+AF43 -> 12672 | AK43: 9 | AM43: =D43='10.06.2022 КП'!D106 -> TRUE | AN43: =E43='10.06.2022 КП'!E106 -> TRUE | AO43: =F43='10.06.2022 КП'!F106 -> TRUE | AP43: =G43='10.06.2022 КП'!G106 -> TRUE | AQ43: =H43='10.06.2022 КП'!H106 -> TRUE
A44: 89 | B44: ГБУ КК "СШОР по конному спорту"/РОО "Федерация конного спорта Краснодарского края" | C44: конный спорт | D44: Краевые соревнования по конкуру "Кубок губернатора Краснодарского края" | E44: мальчики и девочки юноши и девушки мужчины и женщины | F44: 44826 | G44: 44829 | H44: пос. Южный (Динской район) | I44: мальчики и девочки юноши и девушки мужчины и женщины | J44: 44826 | K44: 44829 | L44: 8 | M44: 3400 | N44: =L44*M44 -> 27200 | P44: 2900 | Q44: =O44*P44 -> 0 | S44: 2800 | T44: =R44*S44 -> 0 | U44: 32 | V44: 150 | W44: =U44*V44 -> 4800 | X44: 24 | Y44: 150 | Z44: =X44*Y44 -> 3600 | AA44: 24 | AB44: 150 | AC44: =AA44*AB44 -> 3600 | AD44: 96 | AE44: 7 | AF44: =AD44*AE44 -> 672 | AG44: 1 | AH44: =L44+O44+R44+U44+X44+AA44+AD44 -> 184 | AI44: =AJ44 -> 39872 | AJ44: =N44+Q44+T44+W44+Z44+AC44+AF44 -> 39872 | AK44: 9 | AM44: =D44='10.06.2022 КП'!D107 -> TRUE | AN44: =E44='10.06.2022 КП'!E107 -> TRUE | AO44: =F44='10.06.2022 КП'!F107 -> TRUE | AP44: =G44='10.06.2022 КП'!G107 -> TRUE | AQ44: =H44='10.06.2022 КП'!H107 -> TRUE
D45: ЛЕГКАЯ АТЛЕТИКА | AM45: =D45='10.06.2022 КП'!D108 -> TRUE | AN45: =E45='10.06.2022 КП'!E108 -> TRUE | AO45: =F45='10.06.2022 КП'!F108 -> TRUE | AP45: =G45='10.06.2022 КП'!G108 -> TRUE | AQ45: =H45='10.06.2022 КП'!H108 -> TRUE
A46: 98 | B46: ГБУ КК "РЦСП по легкой атлетике" | C46: легкая атлетика | D46: Первенство Краснодарского края по эстафетам (юноши, девушки) | E46: 2005 -2006 гг.р. 2007 -2008 гг.р. 2009 2010 гг.р. | F46: 44820 | G46: 44822 | H46: г. Краснодар | I46: 2005 -2006 гг.р. 2007 -2008 гг.р. 2009 2010 гг.р. | J46: 44820 | K46: 44822 | M46: 3400 | N46: =L46*M46 -> 0 | P46: 2900 | Q46: =O46*P46 -> 0 | S46: 2800 | T46: =R46*S46 -> 0 | V46: 150 | W46: =U46*V46 -> 0 | Y46: 150 | Z46: =X46*Y46 -> 0 | AB46: 150 | AC46: =AA46*AB46 -> 0 | AD46: 288 | AE46: 7 | AF46: =AD46*AE46 -> 2016 | AG46: 1 | AH46: =L46+O46+R46+U46+X46+AA46+AD46 -> 288 | AI46: =AJ46 -> 2016 | AJ46: =N46+Q46+T46+W46+Z46+AC46+AF46 -> 2016 | AK46: 9 | AM46: =D46='10.06.2022 КП'!D117 -> TRUE | AN46: =E46='10.06.2022 КП'!E117 -> TRUE | AO46: =F46='10.06.2022 КП'!F117 -> TRUE | AP46: =G46='10.06.2022 КП'!G117 -> TRUE | AQ46: =H46='10.06.2022 КП'!H117 -> TRUE
A47: 99 | B47: ГБУ КК "РЦСП по легкой атлетике"/ГБУ КК "ЦОП по легкой атлетике" | C47: легкая атлетика | D47: Осеннее первенство Краснодарского края (юноши, девушки) | E47: 2005 г.р. и моложе (включая 2007 г.р.) | F47: 44827 | G47: 44829 | H47: г. Краснодар | I47: 2005 г.р. и моложе (включая 2007 г.р.) | J47: 44827 | K47: 44829 | M47: 3400 | N47: =L47*M47 -> 0 | P47: 2900 | Q47: =O47*P47 -> 0 | S47: 2800 | T47: =R47*S47 -> 0 | U47: 76 | V47: 150 | W47: =U47*V47 -> 11400 | X47: 42 | Y47: 150 | Z47: =X47*Y47 -> 6300 | AA47: 42 | AB47: 150 | AC47: =AA47*AB47 -> 6300 | AD47: 160 | AE47: 7 | AF47: =AD47*AE47 -> 1120 | AG47: 1 | AH47: =L47+O47+R47+U47+X47+AA47+AD47 -> 320 | AI47: =AJ47 -> 25120 | AJ47: =N47+Q47+T47+W47+Z47+AC47+AF47 -> 25120 | AK47: 9 | AM47: =D47='10.06.2022 КП'!D118 -> TRUE | AN47: =E47='10.06.2022 КП'!E118 -> TRUE | AO47: =F47='10.06.2022 КП'!F118 -> TRUE | AP47: =G47='10.06.2022 КП'!G118 -> TRUE | AQ47: =H47='10.06.2022 КП'!H118 -> TRUE
D48: ПУЛЕВАЯ СТРЕЛЬБА | AM48: =D48='10.06.2022 КП'!D131 -> TRUE | AN48: =E48='10.06.2022 КП'!E131 -> TRUE | AO48: =F48='10.06.2022 КП'!F131 -> TRUE | AP48: =G48='10.06.2022 КП'!G131 -> TRUE | AQ48: =H48='10.06.2022 КП'!H131 -> TRUE
A49: 116 | B49: ГБУ КК "ЦОП по СВС" | C49: пулевая стрельба | D49: Кубок Краснодарского края по стрельбе из малоколиберного оружия | E49: 14 лет и старше | F49: 44775 | G49: 44778 | H49: г. Краснодар | I49: 14 лет и старше | J49: 44775 | K49: 44778 | M49: 3400 | N49: =L49*M49 -> 0 | P49: 2900 | Q49: =O49*P49 -> 0 | S49: 2800 | T49: =R49*S49 -> 0 | U49: 20 | V49: 150 | W49: =U49*V49 -> 3000 | X49: 20 | Y49: 150 | Z49: =X49*Y49 -> 3000 | AA49: 20 | AB49: 150 | AC49: =AA49*AB49 -> 3000 | AD49: 60 | AE49: 7 | AF49: =AD49*AE49 -> 420 | AG49: 1 | AH49: =L49+O49+R49+U49+X49+AA49+AD49 -> 120 | AI49: =AJ49 -> 9420 | AJ49: =N49+Q49+T49+W49+Z49+AC49+AF49 -> 9420 | AK49: 8 | AM49: =D49='10.06.2022 КП'!D139 -> TRUE | AN49: =E49='10.06.2022 КП'!E139 -> TRUE | AO49: =F49='10.06.2022 КП'!F139 -> TRUE | AP49: =G49='10.06.2022 КП'!G139 -> TRUE | AQ49: =H49='10.06.2022 КП'!H139 -> TRUE
A50: 117 | B50: ГБУ КК "ЦОП по СВС" | C50: пулевая стрельба | D50: Первенство Краснодарского края по срельбе из малокалиберного и пневматического оружия | E50: до 15 лет | F50: 44796 | G50: 44799 | H50: г. Краснодар | I50: до 15 лет | J50: 44796 | K50: 44799 | M50: 3400 | N50: =L50*M50 -> 0 | P50: 2900 | Q50: =O50*P50 -> 0 | S50: 2800 | T50: =R50*S50 -> 0 | U50: 15 | V50: 150 | W50: =U50*V50 -> 2250 | X50: 15 | Y50: 150 | Z50: =X50*Y50 -> 2250 | AA50: 15 | AB50: 150 | AC50: =AA50*AB50 -> 2250 | AD50: 45 | AE50: 7 | AF50: =AD50*AE50 -> 315 | AG50: 1 | AH50: =L50+O50+R50+U50+X50+AA50+AD50 -> 90 | AI50: =AJ50 -> 7065 | AJ50: =N50+Q50+T50+W50+Z50+AC50+AF50 -> 7065 | AK50: 8 | AM50: =D50='10.06.2022 КП'!D140 -> TRUE | AN50: =E50='10.06.2022 КП'!E140 -> TRUE | AO50: =F50='10.06.2022 КП'!F140 -> TRUE | AP50: =G50='10.06.2022 КП'!G140 -> TRUE | AQ50: =H50='10.06.2022 КП'!H140 -> TRUE
A51: 118 | B51: ГБУ КК "ЦОП по СВС" | C51: пулевая стрельба | D51: Первенство Краснодарского края по стрельбе из пневматического оружия | E51: до 19 лет | F51: 44811 | G51: 44813 | H51: г. Краснодар | I51: до 19 лет | J51: 44811 | K51: 44813 | M51: 3400 | N51: =L51*M51 -> 0 | P51: 2900 | Q51: =O51*P51 -> 0 | S51: 2800 | T51: =R51*S51 -> 0 | U51: 12 | V51: 150 | W51: =U51*V51 -> 1800 | X51: 12 | Y51: 150 | Z51: =X51*Y51 -> 1800 | AA51: 12 | AB51: 150 | AC51: =AA51*AB51 -> 1800 | AD51: 36 | AE51: 7 | AF51: =AD51*AE51 -> 252 | AG51: 1 | AH51: =L51+O51+R51+U51+X51+AA51+AD51 -> 72 | AI51: =AJ51 -> 5652 | AJ51: =N51+Q51+T51+W51+Z51+AC51+AF51 -> 5652 | AK51: 9 | AM51: =D51='10.06.2022 КП'!D141 -> TRUE | AN51: =E51='10.06.2022 КП'!E141 -> TRUE | AO51: =F51='10.06.2022 КП'!F141 -> TRUE | AP51: =G51='10.06.2022 КП'!G141 -> TRUE | AQ51: =H51='10.06.2022 КП'!H141 -> TRUE
D52: РЕГБИ | AM52: =D52='10.06.2022 КП'!D142 -> TRUE | AN52: =E52='10.06.2022 КП'!E142 -> TRUE | AO52: =F52='10.06.2022 КП'!F142 -> TRUE | AP52: =G52='10.06.2022 КП'!G142 -> TRUE | AQ52: =H52='10.06.2022 КП'!H142 -> TRUE
A53: 119 | B53: ГБУ КК "РЦСП по регби" | C53: регби | D53: Первенство Краснодарского края | E53: юноши до 17 лет | F53: 44618 | G53: 44835 | H53: МО Краснодарского края (с разъездами) | I53: юноши до 17 лет | J53: 44618 | K53: 44835 | M53: 3400 | N53: =L53*M53 -> 0 | P53: 2900 | Q53: =O53*P53 -> 0 | S53: 2800 | T53: =R53*S53 -> 0 | U53: 27 | V53: 150 | W53: =U53*V53 -> 4050 | X53: 27 | Y53: 150 | Z53: =X53*Y53 -> 4050 | AA53: 27 | AB53: 150 | AC53: =AA53*AB53 -> 4050 | AE53: 7 | AF53: =AD53*AE53 -> 0 | AG53: 1 | AH53: =L53+O53+R53+U53+X53+AA53+AD53 -> 81 | AI53: =AJ53 -> 12150 | AJ53: =N53+Q53+T53+W53+Z53+AC53+AF53 -> 12150 | AK53: 9 | AM53: =D53='10.06.2022 КП'!D143 -> TRUE | AN53: =E53='10.06.2022 КП'!E143 -> TRUE | AO53: =F53='10.06.2022 КП'!F143 -> TRUE | AP53: =G53='10.06.2022 КП'!G143 -> TRUE | AQ53: =H53='10.06.2022 КП'!H143 -> TRUE
A54: 126 | B54: ГБУ КК "РЦСП по регби" | C54: регби | D54: Чемпионат Краснодарского края по регби-пляжному | E54: мужчины | F54: 44814 | G54: 44814 | H54: с. Витязево, г. Анапа | I54: мужчины | J54: 44814 | K54: 44814 | L54: 1 | M54: 3400 | N54: =L54*M54 -> 3400 | O54: 1 | P54: 2900 | Q54: =O54*P54 -> 2900 | R54: 1 | S54: 2800 | T54: =R54*S54 -> 2800 | U54: 14 | V54: 150 | W54: =U54*V54 -> 2100 | X54: 14 | Y54: 150 | Z54: =X54*Y54 -> 2100 | AA54: 14 | AB54: 150 | AC54: =AA54*AB54 -> 2100 | AD54: 45 | AE54: 7 | AF54: =AD54*AE54 -> 315 | AG54: 1 | AH54: =L54+O54+R54+U54+X54+AA54+AD54 -> 90 | AI54: =AJ54 -> 15715 | AJ54: =N54+Q54+T54+W54+Z54+AC54+AF54 -> 15715 | AK54: 9 | AM54: =D54='10.06.2022 КП'!D150 -> TRUE | AN54: =E54='10.06.2022 КП'!E150 -> TRUE | AO54: =F54='10.06.2022 КП'!F150 -> TRUE | AP54: =G54='10.06.2022 КП'!G150 -> TRUE | AQ54: =H54='10.06.2022 КП'!H150 -> TRUE
D55: СПОРТИВНАЯ БОРЬБА (ГРЕКО-РИМСКАЯ БОРЬБА) | AM55: =D55='10.06.2022 КП'!D167 -> TRUE | AN55: =E55='10.06.2022 КП'!E167 -> TRUE | AO55: =F55='10.06.2022 КП'!F167 -> TRUE | AP55: =G55='10.06.2022 КП'!G167 -> TRUE | AQ55: =H55='10.06.2022 КП'!H167 -> TRUE
A56: 143 | B56: ГБУ КК "РЦСП по спортивной борьбе" | C56: спортивная борьба (греко-римская борьба) | D56: Краевые соревнования "Турнир памяти мастера спорта СССР Узун В.М." | E56: юноши до 18 лет | F56: 44785 | G56: 44787 | H56: г. Краснодар | I56: юноши до 18 лет | J56: 44785 | K56: 44787 | M56: 3400 | N56: =L56*M56 -> 0 | P56: 2900 | Q56: =O56*P56 -> 0 | S56: 2800 | T56: =R56*S56 -> 0 | U56: 12 | V56: 150 | W56: =U56*V56 -> 1800 | X56: 12 | Y56: 150 | Z56: =X56*Y56 -> 1800 | AA56: 24 | AB56: 150 | AC56: =AA56*AB56 -> 3600 | AD56: 48 | AE56: 7 | AF56: =AD56*AE56 -> 336 | AG56: 1 | AH56: =L56+O56+R56+U56+X56+AA56+AD56 -> 96 | AI56: =AJ56 -> 7536 | AJ56: =N56+Q56+T56+W56+Z56+AC56+AF56 -> 7536 | AK56: 8 | AM56: =D56='10.06.2022 КП'!D172 -> TRUE | AN56: =E56='10.06.2022 КП'!E172 -> TRUE | AO56: =F56='10.06.2022 КП'!F172 -> TRUE | AP56: =G56='10.06.2022 КП'!G172 -> TRUE | AQ56: =H56='10.06.2022 КП'!H172 -> TRUE
